Workbook
Name LU_Worksheet_1145076_18147: lookuplists!$A$1:$A$10
Name LU_Worksheet_1145076_18243: lookuplists!$B$1:$B$3
Name LU_Worksheet_1145076_18259: lookuplists!$C$1:$C$5

Sheet Client Input
B1: Radford McLagan Compensation Database (2024)
B2: Client Input
B3: We require all participants to provide the following information to enable dynamic data filtering and data validation. Where possible we have populated values previously provided to Aon in prior cycles or via a public source. We recommend reviewing and modifying to provide us with the most accurate information.
B5: Client Information (required for all participanting clients)
B6: Data Element Name | C6: Description | D6: Enter/Select Values
A7: PartName | B7: Client Name | C7: Enter the name of the participating organization. | D7: Grafana Labs
A8: PartLevel | B8: Client Level | C8: Select to indicate whether the participating organization represents the entire company or a sub-set of the company. If participant is a Subsidiary, select Multi-Profit or Group: ▪ Corporate - the entire company ▪ Multi-Profit or Group - a geographic region or global business line ▪ Single-Profit or Division - a single location or single business line ▪ Plant - a manufacturing cost center | D8: Corporate
A9: PFirmName | B9: Parent Company Name | C9: Enter parent company name when the 'Client Level' above is not 'Corporate'.
A10: PartCntry | B10: Client Location | C10: Select the headquarters location for the participating client. | D10: US
A11: PartCity | B11: Client City | C11: Enter the headquarters city for the participating client. | D11: New York
A12: PartState | B12: Client State | C12: For US headquartered clients, enter the headquarters state for the participating client. | D12: NY
A13: PartOwnshp | B13: Client Ownership | C13: Select the client's ownership type: ▪ Public ▪ Private: Venture Backed ▪ Private: Private Equity - Growth ▪ Private: Private Equity - Buyout ▪ Private: Other ▪ Not-For-Profit ▪ Government / State-Owned Enterprise | D13: Private: Venture Backed
A14: PartSub | B14: Subsidiary | C14: Select "Yes" to identify if the participating client is a subsidiary of a parent company: ▪ Yes
A15: PartInds | B15: Client Industry | C15: Select one of the standardized RMCD Industries that best represents your organization. See the Industry Definitions tab for detailed industry definitions. | D15: TS01 - Software Products/Services
B16: Client Industry Definition | C16: For reference only, the following represents the definition of the industry selected above. See the Industry Definitions tab for detailed industry definitions. | D16: =IFERROR(INDEX('Industry Definitions'!D6:D163,MATCH(D15,'Industry Definitions'!C6:C163,0)),"") -> Developers and producers of software products such as application software (downloadable or pre-packaged software products) for businesses or consumers, data security/data hosting, middleware/firmware and systems software. NOT companies creating apps to conduct their business (which fits another industry). Developers/creators of entertainment/gaming software - use Gaming/Multi-media (GE01).
A17: PartDesc | B17: Business Description | C17: Enter a high-level description of the participating client's primary product or service area (less than 50 characters). For energy utility companies only (electricity, natural gas, water), please also indicate whether the business operates as Regulated, Deregulated/Nonregulated, or Both (Regulated and Deregulated/Nonregulated). | D17: SaaS, Observability & Monitoring, Metrics
A18: PartLYRev | B18: Client Revenue Last Fiscal Year | C18: Enter the participating client's annual revenue from the last fiscal year in United States Dollars. Please reference the "Currencies" tab to convert the data from other currencies.
A19: PartHCount | B19: Total Headcount | C19: Enter the participating client's total number of employees at the time of submission.
B21: Additional Client Information (required if applicable)
B22: Data Element Name | C22: Description | D22: Enter/Select Values
A23: SalesChan | B23: Primary Sales Channel | C23: Select the participating client's primary sales channel: ▪ Direct / End User - Directly to the end user of a product or service ▪ Government Direct - Directly to the Federal/National government ▪ Original Equipment Manufacturer (OEM) - Directly to original equipment manufacturers ▪ Value-Added Reseller (VAR) - Directly to value-added resellers or systems integrators ▪ Distribution - Directly to distributors/dealers/agents ▪ Retail - Directly to retailers ▪ E-Commerce - Through a website ▪ No Sales | D23: Direct / End User
A24: LSCmpnyTyp | B24: Life Sciences Company Type | C24: For Life Sciences clients only, select the company type: ▪ Brand ▪ Generic and/or Biosimilar ▪ Combination - Generic and/or Biosimilar/Brand ▪ Medical Device – Capital Equipment ▪ Medical Device – Diagnostic Devices & Tools ▪ Medical Device – Hospital Products ▪ Medical Device – Implantable Devices ▪ Institutions and Foundations ▪ Other
A25: StageDevpt | B25: Stage of Development | C25: For Life Sciences clients, select the current stage of development. ▪ Product Definition (Startup/Pre-Alpha/Discovery) - The earliest stage of development which includes proof of concept, and an analysis of requirements, design, development, and various forms of early testing. ▪ Product Development (R&D/Alpha) - The first phase of testing which includes many known and unknown issues. Includes Preclinical Research and Product Classification, and determining whether or not life sciences product(s) should be tested in humans. ▪ Product Testing (Early-Stage) - The second phase of testing, often known as Beta, which may include a low number of known issues. In life sciences products, includes Pre-Market Notification, clinical trials (Phase I and Phase II), and early feasibility research. ▪ Product Testing (Late-Stage) - The final step in testing which includes a release candidate, prior to the launch of a finished product. Includes Pre-Market Submission, clinical trials (Phase III and Phase IV), and pivotal and post market research. ▪ Shipping Product (Revenue Generating) - Shipping Product (Revenue Generating) ▪ Profitable - Profitable | D25: Shipping Product (Revenue Generating)
B27: Cap Table and Private Company Details – this section is mandatory for privately-held companies.
B28: Data Element Name | C28: Description | D28: Enter/Select Values
A29: YearFound | B29: Year Founded | C29: Enter the year in which the company was founded (YYYY). | D29: 2014
A30: LastFundRd | B30: Last Funding Round | C30: Select the company's Last Round of Funding (Angel, Seed, Series A, Series B, Series C, Series D, Series E, Series F or Later).
A31: InvRaiseCp | B31: Invested Capital / Capital Raised | C31: Enter the company's total amount of Invested Capital / Capital Raised. If subject to tranche investment, include paid-in tranches only. (Please enter in USD - Whole Number Only).
A32: MRCompVal | B32: Most Recent Company Valuation | C32: Enter the company's Most Recent Company Valuation based on the latest financing round.
A33: MRCommSSP | B33: Most Recent Common Stock Share Price | C33: Enter the company's most recent common stock share price.
A34: MRPrefSSP | B34: Most Recent Preferred Stock Share Price | C34: Enter the company's most recent preferred stock share price.
A35: EquityType | B35: Equity Vehicles Granted to Employees | C35: Select which equity vehicles are granted to employees (Stock Options, Restricted Stock Units, Restricted Stock Awards, Stock Options & Restricted Stock Awards, Stock Appreciation Rights, Warrants, Profit Interest Units, Capital Interest Units)
A36: FullDShare | B36: Fully Diluted Shares | C36: Enter the total number of fully diluted shares. This includes all issued, unissued, vested, and unvested shares.
A37: ComHeldAll | B37: Common Stock Held by All Employees | C37: For all employees (executives and staff) enter the total number of common stock equivalent shares owned. Ownership may be from the receipt of founder shares, the exercise of stock options, and/or the settlement of restricted stock.
A38: PrfHeldAll | B38: Preferred Stock Held by All Employees | C38: For all employees (executives and staff) enter the total number of preferred shares, stated in common stock equivalent shares. Ownership is typically a result of investment of personal funds to purchase preferred shares.
A39: UnxEqtyAll | B39: Unexercised Equity Awards Held by All Employees | C39: For All Employees (executives and staff) enter the total number of common stock equivalent shares, vested/unvested unexercised options or unvested restricted stock.
A40: UnxWrntAll | B40: Unexercised Warrants Held by All Employees | C40: For All Employees (executives and staff) enter the total number of warrants held. Warrants are a derivative security that gives the holder the right to purchase securities from the issuer at a specific price within a certain time frame.
A41: ComHeldNoE | B41: Common Stock Held by Non-Employees | C41: For Non-Employees (VC Firms, Board Members, Outside Investors & Former Employees) enter the total number of common stock equivalent shares owned. Ownership may be from the receipt of founder shares, the exercise of stock options, and/or the settlement of restricted stock.
... A45: ShareAvail | B45: Shares Available for Grant in Equity Plans (Unissued Shares) | C45: Enter the Shares Available for Grant in Equity Plans (Unissued Shares).
B46: Calculated Equity Check | C46: For reference only, should be 0, or close: | D46: =D36-SUM(D37:D45) -> 0
B48: Financial Services Client Details – required for Financial Services clients only
B49: Data Element Name | C49: Description | D49: Enter/Select Values
A50: AsstUMgt | B50: Assets Under Management | C50: For Financial Services clients only, enter the global value for assets under management as of 31 December 2023.
A51: TotalAsset | B51: Total Assets | C51: For Financial Services clients only, enter total assets for the participating client as of 31 December 2023.
A52: FundMgtSty | B52: Fund's Management Style | C52: For Alternative Investment clients only, select the primary fund management style.
A53: CapIndpnt | B53: Captive / Independent | C53: For Alternative Investment clients only, select Captive / Independent or leave blank.
A54: AMInvsProd | B54: Principal Investment Product | C54: For Alternative Investment clients only, select the principal investment product.
A55: AMAltProd | B55: Principal Alternative Product | C55: For Alternative Investment clients only, select the principal alternative product.
A56: INSDirPrem | B56: Insurance Direct Written Premium | C56: For Insurance clients only, enter the direct written premium in United States Dollars (USD) value for the firm according to the most recently completed fiscal year.
A57: ResLoanPrd | B57: Residential Mortgage Loan Production | C57: For clients with a Mortgage business only, enter the last fiscal year annual residential mortgage loan production volume in United States Dollars (USD).

Sheet Firm Data
A1: PartName | B1: PartLevel | C1: PFirmName | D1: PartCntry | E1: PartCity | F1: PartState | G1: PartOwnshp | H1: PartSub | I1: PartInds | J1: PartDesc | K1: PartLYRev | L1: PartHCount | M1: SalesChan | N1: LSCmpnyTyp | O1: StageDevpt | P1: YearFound | Q1: LastFundRd | R1: InvRaiseCp | S1: MRCompVal | T1: MRCommSSP | U1: MRPrefSSP | V1: EquityType | W1: FullDShare | X1: ComHeldAll | Y1: PrfHeldAll | Z1: UnxEqtyAll | AA1: UnxWrntAll | AB1: ComHeldNoE | AC1: PrfHeldNoE | AD1: UnxEqtyNoE | AE1: UnxWrntNoE | AF1: ShareAvail | AG1: AsstUMgt | AH1: TotalAsset | AI1: CapIndpnt | AJ1: FundMgtSty | AK1: AMInvsProd | AL1: AMAltProd | AM1: INSDirPrem | AN1: ResLoanPrd
A2: Client Name | B2: Client Level | C2: Parent Company Name | D2: Client Location | E2: Client City | F2: Client State | G2: Client Ownership | H2: Subsidiary | I2: Client Industry | J2: Business Description | K2: Client Revenue Last Fiscal Year | L2: Total Headcount | M2: Primary Sales Channel | N2: Life Sciences Company Type | O2: Stage of Development | P2: Year Founded | Q2: Last Funding Round | R2: Invested Capital / Capital Raised | S2: Most Recent Company Valuation | T2: Most Recent Common Stock Share Price | U2: Most Recent Preferred Stock Share Price | V2: Equity Vehicles Granted to Employees | W2: Fully Diluted Shares | X2: Common Stock Held by All Employees | Y2: Preferred Stock Held by All Employees | Z2: Unexercised Equity Awards Held by All Employees | AA2: Unexercised Warrants Held by All Employees | AB2: Common Stock Held by Non-Employees | AC2: Preferred Stock Held by Non-Employees | AD2: Unexercised or Unearned Equity Awards Held by Non-Employees | AE2: Unexercised Warrants Held by Non-Employees | AF2: Shares Available for Grant in Equity Plans (Unissued Shares) | AG2: Assets Under Management | AH2: Total Assets | AI2: Fund's Management Style | AJ2: Captive / Independent | AK2: Principal Investment Product | AL2: Principal Alternative Product | AM2: Insurance Direct Written Premium | AN2: Residential Mortgage Loan Production
A3: =IFERROR('Client Input'!$D$7,"") -> Grafana Labs | B3: =IFERROR('Client Input'!$D$8,"") -> Corporate | C3: =IFERROR('Client Input'!$D$9,"") -> 0 | D3: =IFERROR('Client Input'!$D$10,"") -> US | E3: =IFERROR('Client Input'!$D$11,"") -> New York | F3: =IFERROR('Client Input'!$D$12,"") -> NY | G3: =IFERROR('Client Input'!$D$13,"") -> Private: Venture Backed | H3: =IFERROR('Client Input'!$D$14,"") -> 0 | I3: =IFERROR('Client Input'!$D$15,"") -> TS01 - Software Products/Services | J3: =IFERROR('Client Input'!$D$17,"") -> SaaS, Observability & Monitoring, Metrics | K3: =IFERROR('Client Input'!$D$18,"") -> 0 | L3: =IFERROR('Client Input'!$D$19,"") -> 0 | M3: =IFERROR('Client Input'!$D$23,"") -> Direct / End User | N3: =IFERROR('Client Input'!$D$24,"") -> 0 | O3: =IFERROR('Client Input'!$D$25,"") -> Shipping Product (Revenue Generating) | P3: =IFERROR('Client Input'!$D$29,"") -> 2014 | Q3: =IFERROR('Client Input'!$D$30,"") -> 0 | R3: =IFERROR('Client Input'!$D$31,"") -> 0 | S3: =IFERROR('Client Input'!$D$32,"") -> 0 | T3: =IFERROR('Client Input'!$D$33,"") -> 0 | U3: =IFERROR('Client Input'!$D$34,"") -> 0 | V3: =IFERROR('Client Input'!$D$35,"") -> 0 | W3: =IFERROR('Client Input'!$D$36,"") -> 0 | X3: =IFERROR('Client Input'!$D$37,"") -> 0 | Y3: =IFERROR('Client Input'!$D$38,"") -> 0 | Z3: =IFERROR('Client Input'!$D$39,"") -> 0 | AA3: =IFERROR('Client Input'!$D$40,"") -> 0 | AB3: =IFERROR('Client Input'!$D$41,"") -> 0 | AC3: =IFERROR('Client Input'!$D$42,"") -> 0 | AD3: =IFERROR('Client Input'!$D$43,"") -> 0 | AE3: =IFERROR('Client Input'!$D$44,"") -> 0 | AF3: =IFERROR('Client Input'!$D$45,"") -> 0 | AG3: =IFERROR('Client Input'!$D$50,"") -> 0 | AH3: =IFERROR('Client Input'!$D$51,"") -> 0 | AI3: =IFERROR('Client Input'!$D$52,"") -> 0 | AJ3: =IFERROR('Client Input'!$D$53,"") -> 0 | AK3: =IFERROR('Client Input'!$D$54,"") -> 0 | AL3: =IFERROR('Client Input'!$D$55,"") -> 0 | AM3: =IFERROR('Client Input'!$D$56,"") -> 0 | AN3: =IFERROR('Client Input'!$D$57,"") -> 0

Sheet Employee Input
B1: Radford McLagan Compensation Database (2024)
B2: Employee Input
B4: Unique Identity | D4: Key | I4: Job Attribute Codes | O4: Job Attribute Names | U4: Key | AE4: Executive | AL4: Currency | AM4: 2023 Compensation | CC4: 2024 Compensation | DK4: Additional | EZ4: Legacy Reference
B5: Client Code | C5: Employee Code | D5: Location / Area | F5: Postal Code | G5: City | H5: State | I5: Module Code | J5: Function Code | K5: Area Code | L5: Focus Code | M5: Level Code | N5: Job Code | O5: Module Name | P5: Function Name | Q5: Area Name | R5: Focus Name | S5: Level Name | T5: Job Title | U5: Employee Industry | V5: Business Unit Name | W5: Internal Job Title | X5: Internal Job Code | Y5: Manager Employee Code | Z5: Job Classification | AA5: Employment Status | AB5: Employee Status | AC5: Hire Date | AD5: Entry Into Current Role | AE5: Executive Revenue Responsibility | AF5: Executive Scope of Responsibility | AG5: Plant Headcount Responsibility | AH5: Executive Reporting Layer | AI5: Elected Officer | AJ5: Executive Geographic Responsibility | AK5: Founder | AL5: Compensation Currency | AM5: Last Fiscal Year Base Salary | AN5: Last Fiscal Year Monthly Pay | AO5: Last Fiscal Year Hourly Rate | AP5: Last Fiscal Year Minimum Hourly Rate | AQ5: Last Fiscal Year Maximum Hourly Rate | AR5: Last Fiscal Year Retirals | AS5: Last Fiscal Year Other Retirals | AT5: Last Fiscal Year Gratuity | AU5: Last Fiscal Year Cash Incentives Eligibility | AV5: Last Fiscal Year Cash Incentives Received | AW5: Last Fiscal Year Cash Incentives | AX5: Last Fiscal Year FS Commission | AY5: Last Fiscal Year Target Cash Incentives | AZ5: Last Fiscal Year Overtime | BA5: Last Fiscal Year Participation & Intéressement Award | BB5: Last Fiscal Year Bonus / Ex Gratia Amount | BC5: Last Fiscal Year Broker Paid Bonus | BD5: Last Fiscal Year Car Allowance | BE5: Last Fiscal Year Transportation Allowance | BF5: Last Fiscal Year Meal Allowance | BG5: Last Fiscal Year National Allowance | BH5: Last Fiscal Year Dearness Allowance | BI5: Last Fiscal Year Housing and Rent Allowance | BJ5: Last Fiscal Year Role-Based Allowance | BK5: Last Fiscal Year Site Allowance | BL5: Last Fiscal Year Shift Allowance | BM5: Last Fiscal Year Other Allowances | BN5: Equity Grant Currency | BO5: Last Fiscal Year Long-Term Incentives Eligibility | BP5: Last Fiscal Year Options / Stock Appreciation Rights Number of Shares | BQ5: Last Fiscal Year Options / Stock Appreciation Rights Share Price | BR5: Last Fiscal Year Restricted Stock Number of Shares | BS5: Last Fiscal Year Restricted Stock Share Price | BT5: Last Fiscal Year Performance Shares Target Number of Shares | BU5: Last Fiscal Year Performance Share Price | BV5: Last Fiscal Year Deferred Cash | BW5: Last Fiscal Year Long-Term Cash Incentive Grant Target Amount | BX5: Last Fiscal Year Other Long-Term Incentives | BY5: Last Fiscal Year Personal Number of Loans | BZ5: Last Fiscal Year Personal Production | CA5: Spot Recognition Awards | CB5: Total Billings | CC5: Current Fiscal Year Base Salary | CD5: Current Fiscal Year Monthly Pay | CE5: Current Fiscal Year Hourly Rate | CF5: Current Fiscal Year Minimum Hourly Rate | CG5: Current Fiscal Year Maximum Hourly Rate | CH5: Current Fiscal Year Cash Incentives Eligibility | CI5: Current Fiscal Year Target Cash Incentives | CJ5: Current Fiscal Year New Hire Cash Incentive | CK5: Current Fiscal Year Maximum Cash Incentives | CL5: Current Fiscal Year Retirals | CM5: Current Fiscal Year Other Retirals | CN5: Current Fiscal Year Gratuity | CO5: Internal Salary Grade | CP5: Internal Hourly Salary Grade Midpoint | CQ5: Internal Base Salary Grade Midpoint | CR5: Current Fiscal Year Car Allowance | CS5: Current Fiscal Year Car Allowance Received | CT5: Current Fiscal Year Transportation Allowance | CU5: Current Fiscal Year Meal Allowance | CV5: Current Fiscal Year National Allowance | CW5: Current Fiscal Year Dearness Allowance | CX5: Current Fiscal Year Housing and Rent Allowance | CY5: Current Fiscal Year Role-Based Allowance | CZ5: Current Fiscal Year Site Allowance | DA5: Current Fiscal Year Shift Allowance | DB5: Current Fiscal Year Other Allowances | DC5: New-Hire Long-Term Incentives Eligibility | DD5: Current Fiscal Year New-Hire Options / Stock Appreciation Rights Number of Shares | DE5: Current Fiscal Year New-Hire Options / Stock Appreciation Rights Share Price | DF5: Current Fiscal Year New-Hire Restricted Stock Number of Shares | DG5: Current Fiscal Year New-Hire Restricted Stock Share Price | DH5: Current Fiscal Year New-Hire Performance Shares Target Number of Shares | DI5: Current Fiscal Year New-Hire Performance Share Price | DJ5: Current Fiscal Year New-Hire Long-Term Cash Incentive Grant Amount | DK5: New-Hire Stock Received Last 12 Months | DL5: Shares Held & Unexercised Options | DM5: Last Fiscal Year Quota or Target Sales Volume | DN5: Last Fiscal Year Actual Sales Volume | DO5: Last Fiscal Year Quota/Actual Sales Volume Quota Modifier | DP5: Current Fiscal Year Quota Modifier | DQ5: Current Fiscal Year Quota or Target Sales Volume | DR5: Investment Banking Lockstep | DS5: Manager or Professional Indicator | DT5: Consulting Client Industry Focus | DU5: Solutions Technical Alignment | DV5: New Hire Detail | DW5: Life Sciences Product Alignment | DX5: Restaurant Concept Type Alignment | DY5: Energy & Mining Specialty /Commodities Alignment | DZ5: Mining Residential Type | EA5: Mining Work Environment & Work Pattern | EB5: Energy & Mining General Roster Pattern | EC5: Energy Offshore Type | ED5: Year of Birth | EE5: Gender | EF5: Ethnicity | EG5: Highest Degree Earned | EH5: Year Highest Degree Earned | EI5: New University Graduate | EJ5: Weekly Hours | EK5: Full Time Equivalent (%) | EL5: Worker Location Type | EM5: Performance Rating | EN5: Financial Services Corporate Title | EO5: Desk Manager Identifier | EP5: Consulting Billable Hours | EQ5: Wealth Management Client Segment | ER5: Wealth Management On-/Off-Shore Indicator | ES5: Wealth Management Client Geographic Focus | ET5: Financial Services Regulatory Designation | EU5: Financial Technology Business Alignment | EV5: Insurance Business Alignment | EW5: Investor Services Business Alignment | EX5: Private Equity Carried Interest Participant | EY5: Enterprise Bargaining Agreement/Award | EZ5: Legacy McLagan Client Code | FA5: Legacy Radford Client Code | FB5: 2023 Survey Code | FC5: 2023 Job Code | FD5: 2023 Survey Name | FE5: 2023 Job Name
B6: FirmCode | C6: EmpCode | D6: WorkCntry | F6: PostCode | G6: WorkCity | H6: WorkState | I6: SUBGROUP | J6: FUNCTION | K6: AREA | L6: FOCUS | M6: LEVEL | N6: JobCode | O6: SUBGRP_NM | P6: FUNC_NM | Q6: AREA_NM | R6: FOCUS_NM | S6: LEVEL_NM | T6: JobTitle | U6: EmpInds | V6: EXBusUnit | W6: IntJobTitl | X6: IntJobCode | Y6: MgrEmpCode | Z6: JobClass | AA6: EmpStatus | AB6: PayStatus | AC6: HireDate | AD6: EntCurRole | AE6: EXRevResp | AF6: EXScopeRes | AG6: EXPlantHC | AH6: EXRepLayer | AI6: EXElectOff | AJ6: EXGeoRes | AK6: Founder | AL6: CurrCode | AM6: LYBaseSal | AN6: LYMonPay | AO6: LYHourRate | AP6: LYMinHour | AQ6: LYMaxHour | AR6: LYRetirals | AS6: LYOtherRet | AT6: LYGratuity | AU6: LYCashElig | AV6: LYCashRec | AW6: LYCashInc | AX6: LYFSCom | AY6: LYTCashInc | AZ6: LYOvertime | BA6: LYPartInt | BB6: LYBonxGrat | BC6: LYBrokrBon | BD6: LYCarAllow | BE6: LYTranAllw | BF6: LYMealAllw | BG6: LYNatAllow | BH6: LYDearAllw | BI6: LYHouseRnt | BJ6: LYRoleAllw | BK6: LYSiteAllw | BL6: LYShifAllw | BM6: LYOthrAllw | BN6: EquityPric CurrCode | BO6: ONLTIElig | BP6: ONOPNumShr | BQ6: ONOPShrPri | BR6: ONRSNumShr | BS6: ONRSShrPri | BT6: ONPSNumShr | BU6: ONPSShrPri | BV6: LYDefCash | BW6: ONCITarAmt | BX6: LYOthLonIn | BY6: LYPNLoans | BZ6: LYPerProd | CA6: SpotRecAwd | CB6: TotBilling | CC6: CYBaseSal | CD6: CYMonPay | CE6: CYHourRate | CF6: CYMinHour | CG6: CYMaxHour | CH6: CYCashElig | CI6: CYTCashInc | CJ6: NHCashBon | CK6: CYMaxBonus | CL6: CYRetirals | CM6: CYOtherRet | CN6: CYGratuity | CO6: SalGrade | CP6: HourSalGrd | CQ6: SalGradMid | CR6: CYCarAllow | CS6: CYCarAlRec | CT6: CYTranAllw | CU6: CYMealAllw | CV6: CYNatAllow | CW6: CYDearAllw | CX6: CYHouseRnt | CY6: CYRoleAllw | CZ6: CYSiteAllw | DA6: CYShifAllw | DB6: CYOthrAllw | DC6: NHLTIElig | DD6: NHOPNumShr | DE6: NHOPShrPri | DF6: NHRSNumShr | DG6: NHRSShrPri | DH6: NHPSNumShr | DI6: NHPSShrPri | DJ6: NHCITarAmt | DK6: NHStockAmt | DL6: SharesHeld | DM6: LYQuoTSV | DN6: LYQuoASV | DO6: LYQuoMod | DP6: CYQuoMod | DQ6: CYQuoTSV | DR6: IBLockstep | DS6: MgrProfInd | DT6: CNBusAlign | DU6: SolTechAli | DV6: NHDetail | DW6: LSProduct | DX6: RestConcpt | DY6: EnergySpec | DZ6: MinResType | EA6: MinWrkEnPT | EB6: EnMinRoPat | EC6: EnrgyOff | ED6: YearBirth | EE6: Gender | EF6: Ethnicity | EG6: HiDegEar | EH6: HiDegEarYr | EI6: NewGrad | EJ6: WeekHour | EK6: FTEquiv | EL6: WorkLocTyp | EM6: PerfRating | EN6: FSCorpTitl | EO6: DeskMgr | EP6: BilledHour | EQ6: WMClintSeg | ER6: WMOnOff | ES6: WMGeoFocus | ET6: FSRegDes | EU6: FTBusAlign | EV6: INBusAlign | EW6: ISBusAlign | EX6: PECarryInt | EY6: EntBargAgr | EZ6: Mcl_LgcyFC | FA6: Rwd_LgcyFC | FB6: LGYSURCODE | FC6: LGYJOB | FD6: LGYSURNAM | FE6: LGYJOBNAME
B7: Aon assigns a unique code to each RMCD participant. This can vary in instances where an additional unique identifier is required because clients submit divisions/business units separately. If you do not know this code, Aon will populate this element on your behalf. The appropriate Client Code should be included on the Employee Input tab for every employee submitted. | C7: For All Employees (Mandatory) Enter a unique alpha, numeric, or alphanumeric code for each employee in your submission. DO NOT use employee name or government ID number (e.g., Social Security Number). For continuing database participants, please use the same Employee Code for each employee every year in order for Aon to undertake full data validation and analysis of the submission. | D7: For All Employees (Mandatory) Enter the Location/Area ISO code where the employee is located. You can find the full list of valid ISO Location Codes on the Locations & Currencies tab in the Data Collection Template | F7: For All Employees where applicable (Mandatory) Enter zip code/postal code for each employee's work location, in particular for the US, UK and Australia. For permanent virtual employees, enter their residence location zip code/postal code. For employees who are temporarily working remotely, use office location to which they are assigned. If you are unable to enter a postal code for an employee, enter the city where the employee is physically located in the City data element field. The postal code data enables geographic reporting and differential analytics on HCA. | G7: For All Employees where applicable (Mandatory) If you are unable to provide the postal code for an employee, enter the name of the city where the employee is physically working. For permanent virtual employees, enter the city where the employee resides, if possible. | H7: For All Employees where applicable (Mandatory) For US employees enter 2 character state code where the employee works. For permanent virtual employees, enter the state where they reside, if possible. | I7: For All Employees (Mandatory) Enter the Module Code that covers the business area that each employee works in. Refer to the RMCD Jobs & Descriptions tab in the Data Collection Template for a list of all available benchmark jobs, codes and definitions. In addition, there are additional reference materials available on Human Capital Analytics. | J7: For All Employees (Mandatory) Enter the two-digit Function Code covering the primary activity that describe the employee job's core responsibilities. | K7: For All Employees (Mandatory) Enter the two-digit Area Code covering the principle specificity of expertise or product for which the job is responsible for and contributes to role differentiation. | L7: For All Employees (Mandatory) Enter the two-digit Focus Code covering the most precise specification of the job's responsibilities and/or within the product coverage. | M7: For All Employees (Mandatory) Enter the two-digit Level Code covering the normalized market level based on a consistent set of defined definitions. | N7: Provided by Aon For reference only, the job code will provide a concatenated view of the attribute breakout of the survey structure. Please do not use this field to submit changes to job matching. | O7: Provided by Aon For reference only, you do not need to update this column. Do not delete this column. This data element will be pre-populated with Job Module Name for the employees submitted in the prior year | P7: Provided by Aon For reference only, you do not need to update this column. Do not delete this column. This data element will be pre-populated with Job Module Name for the employees submitted in the prior year | Q7: Provided by Aon For reference only, you do not need to update this column. Do not delete this column. This data element will be pre-populated with Job Module Name for the employees submitted in the prior year | R7: Provided by Aon For reference only, you do not need to update this column. Do not delete this column. This data element will be pre-populated with Job Module Name for the employees submitted in the prior year | S7: Provided by Aon For reference only, you do not need to update this column. Do not delete this column. This data element will be pre-populated with Job Module Name for the employees submitted in the prior year | T7: Provided by Aon For reference only, you do not need to update this column. Do not delete this column. This data element will be pre-populated with the Full Job Title for the employees submitted in the prior year | U7: For All Employees (Mandatory) Enter the primary industry for each employee; see "Industries" tab for list of industry definitions. In general, the same industry will be reported for all employees in the participating company. However, if some employees support one industry while others work in a division or business unit supporting another industry, indicate the specific industry applicable to each employee. Each employee must be assigned to an industry. | V7: Mandatory for Executive Jobs and for all employees in a financial services organization | W7: For All Employees (Mandatory) Enter your internal company job title for each reported employee. Abbreviate the title if necessary. | X7: For All Employees (If Possible) Enter your company internal identifying job code for each reported employee; alpha or numeric characters are acceptable. Using internal job codes will help you identify your data when you match it to our benchmark jobs. | Y7: For All Employees (If Possible) Enter the Employee Code of the person to whom each employee directly reports. This assists Aon in the data validation process and will not appear in the final report. Each Employee Code reported in this column must also appear as an employee being reported in the data submission. | Z7: For Canada, United States and China Employees only (Mandatory) For Canada and United States Employees: Enter "Exempt from Overtime" for employees who are exempt from Employment Standards Act (ESA) or Fair Labor Standards Act (FLSA) overtime requirements. Enter "Overtime Eligible" for employees who are eligible to receive overtime pay (non-exempt). For China Employees: Enter "Manufacturing" or "Non-Manufacturing". Manufacturing indicates that the employee works in a manufacturing-centered environment or has their employee pay level anchored to that of the manufacturing sector. Employees from manufacturing operation units, sales or/and technical services operation units centering around large scale manufacturing operations typically belong to Manufacturing. Non-Manufacturing indicates that the employee works in a non-manufacturing environment where pay is generally based on non-manufacturing guidelines. Employees from location headquarters or corporate functions, large independent R&D centers and sales organizations are typically mapped to Non-Manufacturing. | AA7: For All Employees, if relevant Enter the Employment Status of every employee from the options below. ▪ T: Terminated - employee has been terminated during the last fiscal year or the current fiscal year ▪ N: New Hire - employee has been hired during the last fiscal year or the current fiscal year ▪ R: Transferred - employee has been transferred (i.e. moved to a different role within your firm) during the last fiscal year or the current fiscal year ▪ P: Promoted - the employee was promoted during the last fiscal year or the current fiscal year | AB7: For All Employees Enter the Employee Status of every employee from the options below. ▪ Full-Time - Full-time employee ▪ Part-Time - Part-time employee ▪ Union/Represented Full-Time - Represented employee by union/industry organization and a full-time employee ▪ Temporary International Assignment Full-Time - On a temporary expatriate assignment and a full-time employee ▪ Foreign Full-Time - Outside of the US, indicate if an employee is not a national of the location/area where they are located | AC7: For All Employees (Mandatory) Enter the employee's date of hire in the "MM/DD/YYYY" format. This data element is important for both data validation purposes as well as data filtering capabilities. | AD7: For All Employees (If Possible) Enter the employee's year of entry in current role (YYYY). | AE7: For Executive Jobs Only (Mandatory) Enter the executive's Company or Business Unit last fiscal year revenue responsibility, enter the value in the employee’s local currency. | AF7: For Executive Jobs Only (Mandatory) Select the Executive Scope of Responsibility for every executive or enter as applicable: ▪ Corporate - the entire company ▪ Multi-Profit or Group - a geographic region or global business line ▪ Single-Profit or Division - a single location or single business line ▪ Plant - a manufacturing cost center | AG7: For Plant Executive Jobs Only Enter the total headcount in each plant for each respective executive submitted. | AH7: For Executive Jobs Only (Mandatory) Enter the number of levels/layers the executive is below the top position job in the company (e.g. a direct report to the CEO is 1). | AI7: For Executive Jobs Only (Mandatory) Enter if the employee is considered by the company to be an officer of the company, in most cases by election of the Board of Directors. ▪ Yes ▪ No | AJ7: For Executive Jobs Only (Mandatory) Enter the employee's geographic scope of responsibility from the following options. ▪ Global - responsible for all regions and locations ▪ Region Asia Pacific - responsible for multiple locations in Asia Pacific ▪ Region EMEA - responsible for multiple locations in EMEA ▪ Region Latin America - responsible for multiple locations in Latin America ▪ Region North America - responsible for multiple locations in North America, or the United States ▪ Multi-Region - responsible for multiple locations ▪ Local - responsible for country/local | AK7: For All Private Companies (Mandatory), for Public Companies (If Possible) Enter “Yes” to indicate the employee is a founder of the company. | AL7: For All Employees (Mandatory) Enter the currency code that aligns to the Location/ Country for the employee used to report compensation. The currency reported should reflect the local currency for the Location/ Country in which the employee is located. Refer to the Locations & Currencies tab in the Data Collection Template if needed. | AM7: For All Employees (Mandatory) Enter the annual base salary rate for each employee for the last fiscal year, it must be reflective of a full-time equivalent and on an annual basis. If applicable, include the following in addition to the annual base salary rate: •bonuses that are part of annual salary (e.g., 13th/14th, etc. month salary); •fixed or seasonal bonuses or holiday allowances; •guaranteed fixed overtime; •"salary-sacrifice" allowances or payments (e.g., any amount by which the employee has elected to have base salary reduced in exchange for an allowance or other payment of a like amount); •allowances or payments made to offset social security contributions. Do not include overtime payments in this category which should be reported in the LFY Overtime data field. Exclude car allowance, other regular/fixed allowances, retirement contributions made by the company (e.g. Superannuation, Provident Fund), incentives payments/variable pay, lead premiums, shift differentials and overtime payments. Exclude any portion of base salary that reflects a benefits load (e.g., that portion of the “integral and ordinary salary” in Colombia attributed to a benefits load). For Retail & Hospitality Module jobs (except Store Operations and Restaurant & Dining Operations Support jobs), use this column to report annualized pay. Use LFY Hourly Rate for Store Operations and Restaurant & Dining Operations Support jobs to report hourly pay rate. Use LFY Monthly pay for Malaysia Healthcare employees to report monthly pay. | AN7: For Malaysia Healthcare employees (Mandatory) Enter the monthly base salary which was effective for the last fiscal year (inclusive of the recent merit increases / salary adjustments). | AO7: For Retail & Hospitality Module (Store Operations and Restaurant & Dining Operations Support jobs only); for Healthcare Module (Professional & Support jobs only) (Mandatory) Enter the hourly base rate for the last fiscal year. Exclude the following: car allowance, other regular/fixed allowances, retirement contributions made by the company, incentives payments/variable pay, lead premiums, shift differentials and overtime payments. | AP7: For Retail & Hospitality Module (Store Operations and Restaurant & Dining Operations Support jobs only); for Healthcare Module (Professional & Support jobs only) (Mandatory) If formal, traditional base salary ranges are used, enter the minimum hourly start point of the range for the position for the last fiscal year. If the company does not use formal base salary ranges but has established a base salary control point, enter the minimum hourly reference point. | AQ7: For Retail & Hospitality Module (Store Operations and Restaurant & Dining Operations Support jobs only); for Healthcare Module (Professional & Support jobs only) (Mandatory) If formal, traditional base salary ranges are used, enter the maximum hourly start point of the range for the position for the last fiscal year. If the company does not use formal base salary ranges but has established a base salary control point, enter the maximum hourly reference point. | AR7: For All Eligible Australia, India and New Zealand Employees (Mandatory) Enter the annualized amount of retirement contributions made by the company for the employee for the last fiscal year. For employees located in Australia, enter the value of employer paid superannuation contribution. For India, provide value of employer contribution to provident fund. For New Zealand employees, provide the full dollar value of employer retirement contributions excluding employee contributions (KiwiSaver). If your organization has a legacy superannuation program for employees, please place this figure in “LFY Other Retirals”. Tip: For Australia, retirals are generally 10.5% of pay. For New Zealand, the default KiwiSaver contribution is 3% of total pay. For other retirals please refer to 'LFY Gratuity' or 'Last Fiscal Year Annual Other Retirals' data elements. | AS7: For All Eligible India Employees and New Zealand Employees (Mandatory) For India employees, enter the Annual National Pension Scheme contribution or any other form of Superannuation Fund payment made by employer for the last fiscal year. This will contain all other allowance paid in a fund as a retiral. Do not include superannuation allowance paid directly to employee (to be included in LFY Other Allowances). For New Zealand employees, if you currently run a Superannuation program outside of KiwiSaver, please enter the employer contribution for the last fiscal year. | AT7: For All Eligible India Employees (Mandatory) Enter the employee's annual gratuity received by an employee as a result of the Payment of Gratuity Act. It is paid when an employee leaves the firm after particular number of years of service. It generally applies to organizations with more than 10 employees and is typically defined at 4.81% of Basic Salary. | AU7: For All Employees (Mandatory) Enter “Yes” or “No” to indicate the employee’s eligibility for a performance-based bonus, cash profit sharing, compulsory profit sharing (e.g., Plan de participation in France), commission/sales incentive, or other incentive in the last fiscal year. Exclude company-wide discretionary bonus plans which in theory all employees are eligible. However, if certain positions typically receive a bonus under such discretionary plans, enter "Yes" for those positions. Exclude non-performance related bonuses, such as relocation bonus, retention bonus, fixed holiday or seasonal bonus, etc. If the employee is a new-hire and was hired too late in the year to be eligible, still enter "Yes" if the employee would have been eligible had they been in the position the entire year. | AV7: For All Employees (Mandatory) Enter “Yes” or “No" to indicate whether the employee received a commissions/sales incentive, discretionary bonus, performance-based bonus, cash profit sharing, MBO, KSO, or other incentive for the company’s last complete fiscal year. | AW7: For All Receiving Employees (Mandatory) Enter the full amount of all cash payments the employee received for the company’s last fiscal year including: • the performance-based cash bonus; • cash profit sharing; • compulsory profit sharing (excl. Participation & Intéressement Awards in France); • commissions/sales incentive; • other discretionary bonus; • other cash incentives; • lump sum payments made in lieu of a salary increase • Report the amount earned for the last year, even if actually paid this year. Enter “0” in the Last Fiscal Year Cash Incentives column if the employee was eligible to receive a bonus, but did not receive one based on company, division, or individual performance. If the actual amount represents a partial year award, report an annualized figure for non-sales employees only. Exclude non-performance related bonuses, such as relocation bonus, retention bonus, fixed holiday or seasonal bonus, etc. Report Bonus / Ex Gratia amount for India in ‘LFY Bonus / Ex Gratia Amount’ | AX7: For Financial Services Employees Only (If Possible) Enter all CASH payments related to commission plans from the last fiscal year (including trailers, over-rides and referral awards). If an employee is paid a draw plus commission, DO NOT report draw amounts in the Base Salary columns, instead report their total commission (which includes draw + commission payments in excess of the draw) in the Last Fiscal Year Commissions column. | AY7: For All Eligible Employees (Mandatory) Report the annual target cash incentive for the last fiscal year in this field in whole numbers (do not report percentage of base pay). Target incentives include sales incentives/commissions, non-sales plan bonus (if applicable), and cash profit sharing (if applicable). | AZ7: For All Receiving Employees (Mandatory) Enter the total sum of all overtime payments earned in the last fiscal year. Do not add overtime into the last or current fiscal year salary fields. Allowances should not be included in the Overtime field. | BA7: For All Employees in France, where relevant (Mandatory) Please provide the aggregated amount awarded to the employee for the last fiscal year. Participation Award is a profit sharing scheme imposed by the French employment law to all firms with more than 50 employees based locally. Intéressement Award is a common profit sharing scheme in France that is not a legal obligation and can be awarded in addition to the "Participation Award". Both awards are generally voluntarily deferred in a fund for about 5 years for tax saving reasons. | BB7: For All Eligible India Employees (Mandatory for eligible employees) Enter the Bonus / Ex Gratia amount for all eligible employees for the last fiscal year. This covers only the Annual Bonus amount paid to employees under the ‘Payment of Bonus Act’. This amount is often provided to lower grades or employees with low basic salary and usually varies between 8.33% - 20% of basic salary. Employees who are not covered under the Payment of Bonus Act may receive Ex Gratia at the discretion of management. | BC7: For Wealth Management employees (If Possible) Where relevant, enter all cash payments related to last fiscal year incentive plans (whether paid in last or current fiscal year). Exclude prior year deferrals paid out in the last fiscal year and recent long-term incentive grants (e.g., stock, options, mandatory cash deferrals). Enter “0” in the Broker Paid Bonus column if the employee was eligible to receive a bonus, but did not receive one based on company, division, or individual performance. If an employee worked a partial year in the last fiscal year, report an annualized bonus equivalent. If Broker Paid bonus cannot be annualized to a full-year equivalent, report current fiscal year salary only and indicate that the employee was not eligible to receive broker paid bonus. | BD7: For All Companies that Provide Car Allowances (Mandatory) Enter the annualized amount of the car allowance paid to the employee in the last fiscal year. If the employee has a choice of either car or allowance, enter the amount of the annual car allowance the employee would be receiving if the car allowance option had been chosen. If the employee receives a company-provided car, enter the annualized car lease amount that the company pays (not the value of the car). For cash car allowances, report allowances that are intended to cover the typical cost of owning and operating a car. Exclude transportation allowances that are intended to cover only the cost of commutation (report these allowances in the Last Fiscal Year Transportation Allowance field). For all countries except India, if cash car allowance amount or car lease amount is being reported, also include the amount of any allowance the employee may receive for fuel, insurance, maintenance etc. | BE7: For All Companies that Provide Transportation Allowances - excluding the United States Employees (Mandatory) Enter the total amount of all fixed transportation allowances paid to the employee on a regular basis to cover the cost of commuting to the workplace (e.g., monthly or annually). Enter the full annualized amount for the last fiscal year as a separate item from base salary or incentives. This includes parking and mileage allowances. Exclude car allowances. | BF7: For All Companies that Provide Meal Allowances - excluding the United States Employees (Mandatory) Enter the annualized amount of all fixed meal allowances paid to the employee on a regular basis (e.g., monthly or annually). Enter the full annualized amount for the last fiscal year as a separate item from base salary or incentives. Meal allowances may be in the form of a cash stipend or allowance, a voucher or payment card, or some other payment system specifically for meals. | BG7: For All Eligible Middle East & Africa Employees (Mandatory) Enter the cash allowance paid exclusively to citizens of the home location for the last fiscal year. National allowance is a cash allowance paid exclusively to citizens of the home location to help lower the cost of living under the remit of social protection mechanisms. | BH7: For All Eligible India Employees (Mandatory) Enter the dearness allowance amount for all eligible employees for the last fiscal year. The dearness allowance is a cost of living adjustment allowance paid to certain organizations. It is usually calculated as a percentage of an employee's basic salary. The guidelines that govern the dearness allowance vary according to where one lives and is a fully taxable allowance. | BI7: For All Companies that Provide Housing Allowances (Mandatory) Enter the employee's annual housing allowance amount or the annual value of the lease (whole number), enter the full amount paid in the last fiscal year. For India Employees only, enter the employee's annual housing rent allowance amount (this will be the tax exempt HRA allowance). | BJ7: For All Eligible Employees (Mandatory) Enter the total Role-Based Allowances paid to the employee in the last fiscal year. Role-Based Allowances (RBAs) are fixed remuneration typically based on role, function, experience, and technical expertise that are paid alongside salary in response to the EU's Capital Requirements Directive or other position based responsibilities. RBAs do not typically count toward benefits or pension contribution (except where required under local law). In Financial Services, they may be subject to periodic review and may be removed when/if an employee is no longer considered to be a Material Risk Taker. Do not include function allowances paid to an employee temporarily assuming a more demanding role with additional duties or responsibilities. | BK7: For Energy and Mining Companies Only Enter the annualized identifiable cash allowance specifically paid in recognition of an employee residing permanently at site. Please enter any superannuation payable on this item in the Last Fiscal Year Other Retirals field. | BL7: For Energy and Mining Companies Only Enter the annual cash allowance paid in respect of an employee working on a variable shift basis e.g. night shift and weekend work. Please enter any superannuation payable on this item in the Last Fiscal Year Other Retirals field. | BM7: For All Companies that Provide Allowances - excluding the United States Employees (Mandatory) Enter the aggregated, annualized total of all other allowances not covered in the specific allowance categories in the Data Collection Template, for the last fiscal year. For example: employee education allowance; personal travel allowance; club memberships; furniture; children’s education; uniform allowance; professional development allowance; medical allowance; entertainment allowance; hardship allowance; gardener allowance; city compensatory allowance; personal pay; project pay allowance (for Mining/ Energy companies) etc.), enter the current fiscal year annualized amount of fixed cash allowances or other cash payments paid to the employee on a regular basis (e.g., monthly or annually) for the current fiscal year as a separate item from base salary or incentives. For Malaysia Healthcare employees only, examples include annualized education allowances like post basic allowance, degree allowance, competency/certification allowance, license allowances, etc. Also include variable allowances which are paid to the employee upon delivering of services or activities (i.e. on call allowance, shift allowances, shaving allowance, etc). For all other Companies, exclude shift differentials, on-call and overtime pay; exclude car allowance, if any, which is reported separately. Fixed or seasonal bonuses, holiday allowances, guaranteed fixed overtime and salary-sacrifice allowances should be included in "Last Fiscal Year Base Salary". | BN7: For All Employees Receiving Long-Term Incentives Enter the currency code aligned to each employee's equity grant. There are scenarios where the currency is either aligned with the cash compensation currency or varies if the equity is supplied in the company's headquartered currency. | BO7: For All Employees (Mandatory) Enter “Yes” or “No" to indicate the employee's eligibility of participation in a long-term incentive plan for an employee. | BP7: For All Company Employees Receiving Options/SARs (Mandatory) Enter the number of stock options or stock appreciation rights (SARs) the employee actually received for the last fiscal year. If more than one option/SAR grant was awarded, report the sum total of all options/SARs granted. If an employee received long-term incentives as part of a new-hire awards plan, enter the value for the new-hire specific incentive in the relevant new-hire field (which may not be present in the Data Collection template if this is not a standard industry practice). | BQ7: For All Company Employees Receiving Options/SARs (Mandatory) Enter the grant price per share for ongoing stock options or stock appreciation rights (SARs) received for the last fiscal. Enter the price in the equity currency provided, do not reflect a discount or premium. If more than one option/SAR grant was made, provide the weighted average grant price. If an employee received long-term incentives as part of a new-hire awards plan, enter the value for the new-hire specific incentive in the relevant new-hire field (which may not be present in the Data Collection template if this is not a standard industry practice). | BR7: For All Company Employees Receiving Restricted Stock/Units (Mandatory) Enter the number of Restricted Stock shares/units the employee was granted for the last performance year, these may have been paid out in the first quarter of the current fiscal year in line with pay review dates. If more than one grant occurred for the last fiscal year, report the sum total number. If an employee received long-term awards as part of a new-hire incentive, enter the value for the new-hire specific incentive in the relevant field (which may not be present in the Data Collection template if this is not a standard industry practice). | BS7: For All Company Employees Receiving Restricted Stock/Units (Mandatory) Enter the Restricted Stock share/unit fair market value (typically the stock price at the time the award was granted). Enter the fair market value in the equity currency provided, do not incorporate any discount or premium to the market value. If more than one grant was made, provide the weighted average fair market value. If an employee received long-term awards as part of a new-hire incentive, enter the value for the new-hire specific incentive in the relevant new-hire field (which may not be present in the Data Collection template if this is not a standard industry practice). | BT7: For All Company Employees Receiving Performance Shares/Units (Mandatory) Enter the number of performance shares/units granted to the employee for the last fiscal year as an ongoing award. This field should only include grants that are subject to full or partial forfeiture if specified performance conditions are not achieved. Depending on performance, all of the award, none of the award, a portion of the award, or an amount greater than the grant may ultimately vest. Report the number of shares/units that would be earned for "on target" performance (not the maximum award possible). If more than one grant occurred for the last fiscal year, report the sum total number of shares. | BU7: For All Company Employees Receiving Performance Shares/Units (Mandatory) Enter the Performance share fair market value (typically stock price on date of grant). Enter the Fair Market Value in the equity currency provided. If more than one grant was made, provide the weighted average fair market value. | BV7: The portion of 2023 bonus subject to mandatory deferral awarded in a cash vehicle; not the amount of previously deferred cash paid out in 2023. Deferred Cash should also include deferred performance fees (the percentage of performance fees achieved by an investment fund that is awarded as a deferral to a portfolio manager or research analyst). Exclude any amounts that vest within the calendar year (i.e., 3 or 6 month vesting period); these should be included in the 2023 Last Fiscal Year Cash Incentive column. Any voluntary deferrals should be included in the 2023 Last Fiscal Year Cash Incentive column. For portfolio managers, report any mandatory deferrals into "firm managed" mutual funds in the Last Fiscal Year Deferred Cash column. Note: Only awards that are subject to time-based vesting should be included in this column (awards subject to performance-based vesting should be reported under one of the two 2023 Performance Vested Awards columns). Awards that vest within the year they are awarded should be captured in the 2023 Last Fiscal Year Cash Incentive field. | BW7: For All Employees Receiving Long-Term Cash Incentives (Mandatory) Enter the target long-term cash incentive amount that the employee was targeted to receive during or at the end of the last fiscal year, assuming 100% of performance objectives will be achieved. Report target grant amounts as an absolute value (not a percentage), ensure the data is provided in the currency indicated in the Equity Grant Currency field. | BX7: For All Employees Eligible (Mandatory) Enter the communicated value at the time of grant of any other applicable long-term / deferred incentives (e.g., investment partnerships, promissory notes, phantom stock) for the last fiscal year. Only include time-vested awards in this field. For portfolio managers, report any mandatory deferrals into "firm managed" mutual funds in the appropriate Long-Term Cash Incentive data fields. | BY7: In the Mortgage Banking module, for each Producer (individual contributors), enter the total NUMBER loans closed from January 1, 2023 to December 31, 2023. For each Mortgage Loan Processor or Loan Closer (individual contributors), the total NUMBER of loans processed / closed from January 1, 2023 to December 31, 2023. For each Mortgage Underwriter (individual contributor), please indicate the total NUMBER of ‘decisions’ made from January 1, 2023 to December 1, 2023. The number for ‘decisions’ is classified as the total number of customer applications an Underwriter either accepted or denied. | BZ7: In the Mortgage Banking module, for each Producer (individual contributors), enter the total production value for transaction volume (i.e., loan $ volume) closed from January 1, 2023 to December 31, 2023. Values should be entered in local currency. | CA7: For employees mapped to Consulting Services module, list of all Spot Recognition awards at face value granted in the last fiscal year in employee’s local currency | CB7: For the Consulting Services module, enter the total amount of client billings attributed to each individual employee in local currency. | CC7: For All Employees (Mandatory) Enter the annual base salary rate for each employee for the current fiscal year, it must be reflective of a full-time equivalent and on an annual basis. If applicable, include the following in addition to the annual base salary rate: •bonuses that are part of annual salary (e.g., 13th/14th, etc. month salary); •fixed or seasonal bonuses or holiday allowances; •guaranteed fixed overtime; •"salary-sacrifice" allowances or payments (e.g., any amount by which the employee has elected to have base salary reduced in exchange for an allowance or other payment of a like amount); •allowances or payments made to offset social security contributions. Exclude car allowance, other regular/fixed allowances, retirement contributions made by the company (e.g. Superannuation, Provident Fund), incentives payments/variable pay, lead premiums, shift differentials and overtime payments. Exclude any portion of base salary that reflects a benefits load (e.g., that portion of the “integral and ordinary salary” in Colombia attributed to a benefits load). For Retail & Hospitality Module jobs (except Store Operations and Restaurant & Dining Operations Support jobs), use this column to report annualized pay. Use Current Fiscal Year Hourly Rate for Store Operations and Restaurant & Dining Operations Support jobs to report hourly pay rate. Use Current Fiscal Year Monthly pay for Malaysia Healthcare employees to report monthly pay. | CD7: For Malaysia Healthcare employees (Mandatory) Enter the monthly base salary which is effective in the current fiscal year (inclusive of the recent merit increases / salary adjustments). | CE7: For Retail & Hospitality Module (Store Operations and Restaurant & Dining Operations Support jobs only); for Healthcare Module (Professional & Support jobs only) (Mandatory) Enter the hourly base rate for the current fiscal year. Exclude the following: car allowance, other regular/fixed allowances, retirement contributions made by the company, incentives payments/variable pay, lead premiums, shift differentials and overtime payments. | CF7: For Retail & Hospitality Module (Store Operations and Restaurant & Dining Operations Support jobs only); for Healthcare Module (Professional & Support jobs only) (Mandatory) If formal, traditional base salary ranges are used, enter the minimum hourly start point of the range for the position for the current fiscal year. If the company does not use formal base salary ranges but has established a base salary control point, enter the minimum hourly reference point. | CG7: For Retail & Hospitality Module (Store Operations and Restaurant & Dining Operations Support jobs only); for Healthcare Module (Professional & Support jobs only) (Mandatory) If formal, traditional base salary ranges are used, enter the maximum hourly start point of the range for the position for the current fiscal year. If the company does not use formal base salary ranges but has established a base salary control point, enter the maximum hourly reference point. | CH7: For All Employees (Mandatory) Enter “Yes” or “No” to indicate the employee’s eligibility for a performance-based bonus, cash profit sharing, compulsory profit sharing (e.g., Plan de participation in France), commission/sales incentive, or other incentive in the current fiscal year. Exclude company-wide discretionary bonus plans which in theory all employees are eligible. However, if certain positions typically receive a bonus under such discretionary plans, enter "Yes" for those positions. Exclude non-performance related bonuses, such as relocation bonus, retention bonus, fixed holiday or seasonal bonus, etc. | CI7: For All Eligible Employees (Mandatory) Report the annual target cash incentive for the current fiscal year in this field in whole numbers (do not report percentage of base pay). Target incentives include sales incentives/commissions, non-sales plan bonus (if applicable), and cash profit sharing (if applicable). | CJ7: For New-Hire Employees Only (If Possible) Enter new-hire/starting bonus awards, granted as part of a new-hire award plan, to employees hired in last 12 months (whole number) e.g. Sign On Bonus. Continue to report cash incentives awarded to employees as part of the annual compensation review in the Last Fiscal Year Cash Incentives field, even for employees hired in the last 12 months. | CK7: For All Employees Eligible (If Possible) Enter the employee's maximum bonus as an absolute value for the current fiscal year. Maximum incentives are earned at truly superior levels of performance and represent the highest bonus amount that can be earned. Leave blank if your organization does not have maximum awards. Example: For an employee with a current fiscal year salary of $100,000 and a current fiscal year maximum bonus of 150%, input '150,000'. | CL7: For All Eligible Australia, India and New Zealand Employees (Mandatory) Enter the annualized amount of retirement contributions that will be made by the company for the employee for the full current fiscal year. For employees located in Australia, enter the value of employer paid superannuation contribution. For India, provide value of employer contribution to provident fund. For New Zealand employees, provide the full dollar value of employer retirement contributions excluding employee contributions (KiwiSaver). If your organization has a legacy superannuation program for employees, please place this figure in “Current Fiscal Year Other Retirals”. Tip: For Australia, retirals are generally 11% of pay. For New Zealand, the default KiwiSaver contribution is 3% of total pay. For other retirals please refer to 'Current Fiscal Year Gratuity' or 'Current Fiscal Year Annual Other Retirals' data elements. | CM7: For All Eligible India Employees and New Zealand Employees (Mandatory) For India employees, enter the Annual National Pension Scheme contribution or any other form of Superannuation Fund payment that will be made by employer for the full current fiscal year. This will contain all other allowance paid in a fund as a retiral. Do not include superannuation allowance paid directly to employee (to be included in LFY Other Allowances). For New Zealand employees, if you currently run a Superannuation program outside of KiwiSaver, please enter the full employer contribution for the current fiscal year. | CN7: For All Eligible India Employees (Mandatory) Enter the employee's annual gratuity that will be received by an employee as a result of the Payment of Gratuity Act. It is paid when an employee leaves the firm after particular number of years of service. It generally applies to organizations with more than 10 employees and is typically defined at 4.81% of Basic Salary. | CO7: For All Employees (If Possible) Enter your internal base salary grade identifier (numeric and/or alpha). Leave this field blank if you do not use internal salary ranges/grades. This assists Aon in the data validation process and will not appear in the final report. | CP7: For Retail & Hospitality Module (Store Operations and Restaurant & Dining Operations Support jobs only); for Healthcare Module (Professional & Support jobs only) (Mandatory) Enter the employee's hourly Salary Grade Midpoint. | CQ7: For All Employees, excluding India and Retail & E-Commerce Module Store Operations and Restaurant & Dining Operations Support jobs (If Possible) If formal, traditional base salary ranges are used, enter the annualized midpoint value for the base salary range/grade. If the company does not use formal base salary ranges but has established a base salary control point or market reference point, enter that annualized value. Leave blank if the company does not have salary ranges, control points or market reference points. For Retail & E-Commerce Module Store Operations and Restaurant & Dining Operations Support jobs, leave blank and complete column 'Salary Grade Midpoint'. | CR7: For All Companies that Provide Car Allowances (Mandatory) Enter the annualized amount of the car allowance to be paid to the employee in the full current fiscal year. If the employee has a choice of either car or allowance, enter the amount of the annual car allowance the employee would be receiving if the car allowance option had been chosen. If the employee receives a company-provided car, enter the annualized car lease amount that the company pays (not the value of the car). For cash car allowances, report allowances that are intended to cover the typical cost of owning and operating a car. Exclude transportation allowances that are intended to cover only the cost of commutation (report these allowances in the Current Fiscal Year Transportation Allowance field). For all countries except India, if cash car allowance amount or car lease amount is being reported, also include the amount of any allowance the employee may receive for fuel, insurance, maintenance etc. | CS7: For All Companies (Mandatory) For the current fiscal year, enter "Company Car" for company-provided car (company leased, purchased, contract hire, etc.), "Allowance" for cash allowance, "Choice of Car or Allowance" if employee has a choice of either car or allowance, or "No Car or Allowance" for not eligible. This indicates whether the employee is receiving a cash car allowance or the use of a company-provided car (on a take-home basis) for the current fiscal year. Enter "Fuel reimbursement and Car Maintenance". Fuel Reimbursement may be a fixed monthly allowance or a reimbursement up to a fixed limit or on actuals. It is derived by monthly number of liters multiplied by the rate of fuel per liter multiplied by twelve. Car Maintenance allows a colleague to claim reimbursement for running and maintenance expenses. | CT7: For All Companies that Provide Transportation Allowances, excluding the United States Employees (Mandatory) Enter the total amount of all fixed transportation allowances to be paid to the employee on a regular basis to cover the cost of commuting to the workplace (e.g., monthly or annually). Enter the full annualized amount for the current fiscal year as a separate item from base salary or incentives. This includes parking and mileage allowances. Exclude car allowances. | CU7: For All Companies that Provide Meal Allowances, excluding the United States Employees (Mandatory) Enter the annualized amount of all fixed meal allowances paid to the employee on a regular basis (e.g., monthly or annually). Enter the full annualized amount for the current fiscal year as a separate item from base salary or incentives. Meal allowances may be in the form of a cash stipend or allowance, a voucher or payment card, or some other payment system specifically for meals. | CV7: For All Eligible Middle East & Africa Employees (Mandatory) Enter the cash allowance to be paid exclusively to citizens of the home location for the current fiscal year. National allowance is a cash allowance paid exclusively to citizens of the home location to help lower the cost of living under the remit of social protection mechanisms. | CW7: For All Eligible India Employees (Mandatory) Enter the dearness allowance amount for all eligible employees for the current fiscal year. The dearness allowance is a cost of living adjustment allowance paid to certain organizations. It is usually calculated as a percentage of an employee's basic salary. The guidelines that govern the dearness allowance vary according to where one lives and is a fully taxable allowance. | CX7: For All Companies that Provide Housing Allowances (Mandatory) Enter the employee's annual housing allowance amount or the annual value of the lease (whole number), enter the full amount to be paid in the current fiscal year. For India Employees only, enter the employee's annual housing rent allowance amount (this will be the tax exempt HRA allowance). | CY7: For All Eligible Employees (Mandatory) Enter the total Role-Based Allowances to be paid to the employee in the current fiscal year. Role-Based Allowances (RBAs) are fixed remuneration typically based on role, function, experience, and technical expertise that are paid alongside salary in response to the EU's Capital Requirements Directive or other position based responsibilities. RBAs do not typically count toward benefits or pension contribution (except where required under local law). In Financial Services, they may be subject to periodic review and may be removed when/if an employee is no longer considered to be a Material Risk Taker. Do not include function allowances paid to an employee temporarily assuming a more demanding role with additional duties or responsibilities. | CZ7: For Energy and Mining Companies Only Enter the annualized identifiable cash allowance specifically to be paid in recognition of an employee residing permanently at site. Please enter any superannuation payable on this item in the Current Fiscal Year Other Retirals field. | DA7: For Energy and Mining Companies Only Enter the annual cash allowance to be paid in respect of an employee working on a variable shift basis e.g. night shift and weekend work. Please enter any superannuation payable on this item in the Current Fiscal Year Other Retirals field. | DB7: For All Companies that Provide Allowances, excluding the United States Employees (Mandatory) Enter the aggregated, annualized total of all other allowances not covered in the specific allowance categories in the Data Collection Template, for the current fiscal year. For example: employee education allowance; personal travel allowance; club memberships; furniture; children’s education; uniform allowance; professional development allowance; medical allowance; entertainment allowance; hardship allowance; gardener allowance; city compensatory allowance; personal pay; project pay allowance (for Mining/ Energy companies) etc.), enter the current fiscal year annualized amount of fixed cash allowances or other cash payments paid to the employee on a regular basis (e.g., monthly or annually) for the current fiscal year as a separate item from base salary or incentives. For Malaysia Healthcare employees only, examples include annualized education allowances like post basic allowance, degree allowance, competency/certification allowance, license allowances, etc. Also include variable allowances which are paid to the employee upon delivering of services or activities (i.e. on call allowance, shift allowances, shaving allowance, etc). For all other Companies, exclude shift differentials, on-call and overtime pay; exclude car allowance, if any, which is reported separately. Fixed or seasonal bonuses, holiday allowances, guaranteed fixed overtime and salary-sacrifice allowances should be included in "Current Fiscal Year Base Salary". | DC7: For All Employees (Mandatory) Enter “Yes” or “No” to indicate the employee's eligibility of participation in a new-hire long-term incentive plan. Only indicate "Yes" for employees hired during the last 12 months who are eligible for a new-hire long-term incentive. Indicate "No" for all other employees. | DD7: For All Company Employees Receiving Options/SARs (Mandatory) Enter the number of stock options or stock appreciation rights (SARs) the employee received as a new-hire incentive in the last 12 months (whole number). | DE7: For All Company Employees Receiving Options/SARs (Mandatory) Enter the grant price per share for stock options or stock appreciation rights (SARs) received by the employee as a new-hire incentive in the last 12 months. Enter the price in the equity currency provided. | DF7: For All Company Employees Receiving Restricted Stock/Units (Mandatory) Enter the number of shares/units the employee actually received as a new-hire incentive in the last 12 months. | DG7: For All Company Employees Receiving Restricted Stock/Units (Mandatory) Enter the per share/unit fair market value (typically stock price on date of grant) for restricted stock/unit awards received by the employee as a new-hire incentive in the last 12 months. Enter the Fair Market Value in the equity currency provided. | DH7: For All Company Employees Receiving Performance Shares/Units (If applicable) Enter the target number of performance shares/units awarded to the employee as a new-hire award incentive in the last 12 months. Report the number of shares/units that would be earned for "on target" performance (not the maximum award possible). Receipt of actual Performance Shares/Units is subject to achievement of pre-defined performance objectives with multi-year time horizons – report the target award at the time of grant. | DI7: For All Company Employees Receiving Performance Shares/Units (If applicable) Enter the per share fair market value (typically stock price on date of grant) of performance share/unit awards received as a new-hire incentive in the last 12 months. Enter the Fair Market Value in the equity currency provided. | DJ7: For All Employees Receiving Long-Term Cash Incentives (Mandatory) Enter the target long-term cash incentive amount that the new-hire is targeted to receive during or at the end of the current fiscal year, assuming 100% of performance objectives will be achieved. Report target grant amounts awarded in the last 12 months in local currency. | DK7: For Private Companies (Mandatory) If the employee was hired in the last 12 months, enter the number of shares granted at hire (options, restricted stock, stock grants). | DL7: For Private Companies (Mandatory) Enter the total number of shares held including unexercised options. Enter all shares, including founder shares, shares from exercised stock options, profit interests, settled and unsettled restricted stock awards, plus unexercised stock options both vested and unvested. | DM7: For Select Sales Employees Only Report the annualized quota or sales target for the last sales plan year. Enter the value in the employee’s local currency. For field sales management positions, report the quota for which they or their employees were responsible. For individual contributor sales account managers, report individual or team quotas. Please provide annual quota or target sales volume for the last sales plan year for all sales jobs except: Telemarketing, Apps/Systems Engineering, Operations/Sales Support and Relationship Management. For these job codes, please leave this field blank. If the employee has been with the company or in the present job for less than one year, leave all Last Fiscal Year sales specific compensation fields blank. | DN7: For Select Sales Employees Only Report the actual sales volume amount for which the individual employee was responsible during the last complete sales plan year. For field sales management positions, report the actual sales volume for which they or their employees were responsible. For individual contributor sales account managers, report individual or team actual volume. Please provide actual sales volume for all sales jobs except: Telemarketing, Apps/Systems Engineering, Operations/Sales Support and Relationship Management. For these job codes, please leave this field blank. If the employee has been with the company or in the present job for less than one year, leave all LFY sales specific compensation fields blank. | DO7: For Select Sales Employees Only For each employee, enter "Individual" for individual quota or "Team" for team quota. Designates if LFY quota or target sales volume is based on individual or team quota. Note: This field corresponds to LFY Quota/Target and Actual Sales Volume. Please provide LFY quota/actual sales volume modifier for all sales jobs except: Telemarketing, Apps/Systems Engineering, Operations/Sales Support and Relationship Management. For these job codes, please leave this field blank. If the employee has been with the company or in the present job for less than one year, leave all LFY sales specific compensation fields blank. | DP7: For Select Sales Employees Only For each employee, enter "Individual" for individual quota or "Team" for team quota. Designate if Current Fiscal Year quota or target sales volume is based on individual or team quota. This field corresponds to Current Fiscal Year Quota or Target Sales Volume. Please provide Current Fiscal Year quota modifier for all sales jobs except: Telemarketing, Apps/Systems Engineering, Operations/Sales Support and Relationship Management. For these job codes, please leave this field blank. If the employee has been with the company or in the present job for less than one year, leave all LFY sales specific compensation fields blank. | DQ7: For Select Sales Employees Only Report the annualized quota or sales target for the current sales plan year. Enter the value in the employee’s local currency. For field sales management positions, report the quota for which they or their employees were responsible. For individual contributor sales account managers, report individual or team quotas. Please provide annual quota or target sales volume for the current sales plan year for all sales jobs except: Telemarketing, Apps/Systems Engineering, Operations/Sales Support and Relationship Management. For these job codes, please leave this field blank. | DR7: For All Global Markets & Investment Banking Employees (Mandatory) Enter each employee within the Investment Banking class structure as follows: - 1st Year Managing Director - 3rd Year Director - 2nd Year Director - 1st Year Director - 3rd Year Vice President - 2nd Year Vice President - 1st Year Vice President - 3rd Full Year Associate - 2nd Full Year Associate - 1st Full Year Associate - New Associate in Summer through Year-End Stub Period (e.g., MBA grads) - New ‘Associate’ between 24-to-36-month tenure for firms with 2-year ANL program - 3rd Year Analyst - 2nd Year Analyst - 1st Year Analyst | DS7: For Infrastructure and Consulting & Professional Services jobs matched to Financial Services & Advisory Level (Mandatory) Enter if the employee is a "Manager" or "Professional (Individual Contributor)", if it is not possible to determine this, choose "Professional (Individual Contributor)". | DT7: For All Consulting & Professional Employees (Mandatory) Enter the corresponding client industry focus that reflects the focus of the individual employee and/or business line. - Consumer Products / Marketing / Retail - Energy / Utilities - Financial Services - Generalist - Government - Health Care - Industrials / Basic Materials / Capital Goods - Real Estate - Tech / Media / Telecom | DU7: For all solutions aligned sales employees, enter the technical knowledge to which each employee is aligned using the following codes: - Amazon Web Services - Ariba - Dynamics - EPIC - Guidewire - Hyperion - Lync - Oracle - PeopleSoft - SAP - SuccessFactors - Salesforce.com - SharePoint - WorkDay - Pega - ServiceNow - None - Other | DV7: Indication that if the employee was a first year recruit out of an undergraduate or graduate school program using one of the following codes: - Undergraduate - Graduate - Experienced Hire | DW7: For Life Sciences clients only (Mandatory) For employees matched to a Life Sciences Sales or Clinical Development job enter a specific product code using the product codes and definitions outlined on the 'Life Sciences Products' tab in the Data Collection Template. | DX7: For Restaurant clients only (Mandatory) For employees matched to a Restaurant job enter a specific concept using the concept codes and definitions outlined on the 'Restaurant Concept' tab in the Data Collection Template. | DY7: For Energy & Mining clients only (Mandatory) Enter Specialty/Commodities code that applies to each employee, select from the valid options, and definitions, on the 'Energy & Mining Specialty' tab in the Data Collection Template. | DZ7: For Mining Clients (If Possible) Enter how employee commutes to and from site: "Drive In/Drive Out" if employee commutes to and from site for each roster swing and is provided with accommodation by the organization for the duration of the swing. " Fly In/Fly Out" if employee commutes to and from site for each roster swing and is provided with accommodation by the organization for the duration of the swing. "Residential" if employee commutes to and from the site at the commencement and end of each day/shift and may reside in own residence or have accommodation provided by the organization. | EA7: For Mining Clients (If Possible) Enter the employees physical work location; where the individual role is located: "Surface/Open Cut Day Work" - Employee is working on the surface or within an Open Pit. This could be at an open cut mine, or in a predominantly surface role at either an open cut or underground mine. While the hours of work and starting / finishing times may vary, Day rosters are typically based on a five day week, Monday through Friday. Some weekend work may be rostered for overtime. Also includes 9 day fortnight and 19 day month patterns. Typical example Roster Patterns in this category are: 5D2rx8hrs; 5D2r4D3rx9hrs; 4D3rx12hrs. "Surface/Open Cut Shift Continuous " - Employee is working on the surface or within an Open Pit. This could be at an open cut mine, or in a predominantly surface role at either an open cut or underground mine. Employees who are rostered to work Days, (Afternoons) and Nights over seven days of the week, over 365 days of the year including public holidays are Continuous Shift Workers. Continuous Shift Work patterns must be rotating and contain Nights to be included in this category. In addition, employees who provide a “bridge” between non-continuous rosters by working Days and/or Nights over the weekend (typically Friday through Sunday shifts or Saturday through Monday shifts), typically in the Coal Mining industry, are also classified as Continuous Shift Workers "Surface/Open Cut Shift Non-Continuous " - Employee is working on the surface or within an Open Pit. This could be at an open cut mine, or in a predominantly surface role at either an open cut or underground mine. A Non-Continuous Shift Worker is typically rostered to work between Monday and Friday on rotating or fixed shifts, or over seven days of the week, including public holidays, on fixed shifts. Shifts may rotate between Days, (Afternoons) and Nights or the worker may be permanently rostered to Days, (Afternoons or) Night Shift. An employee who is rostered to work Days over seven days of the week, including public holidays, is a Non-Continuous Shift Worker. "Underground Shift Day Work" - Employee is working underground. This would be at an underground mine operation where the role is located predominantly underground. If the employee is working at an underground site but working on the surface then please select the work environment of Surface. While the hours of work and starting / finishing times may vary, Day rosters are typically based on a five day week, Monday through Friday. Some weekend work may be rostered for overtime. Also includes 9 day fortnight and 19 day month patterns. Typical example Roster Patterns in this category are: 5D2rx8hrs; 5D2r4D3rx9hrs; 4D3rx12hrs. "Underground Shift Continuous" - Employee is working underground. This would be at an underground mine operation where the role is located predominantly underground. If the employee is working at an underground site but working on the surface then please select the work environment of Surface. Employees who are rostered to work Days, (Afternoons) and Nights over seven days of the week, over 365 days of the year including public holidays are Continuous Shift Workers. Continuous Shift Work patterns must be rotating and contain Nights to be included in this category. In addition, employees who provide a “bridge” between non-continuous rosters by working Days and/or Nights over the weekend (typically Friday through Sunday shifts or Saturday through Monday shifts), typically in the Coal Mining industry, are also classified as Continuous Shift Workers "Underground Shift Non-Continuous" - Employee is working underground. This would be at an underground mine operation where the role is located predominantly underground. If the employee is working at an underground site but working on the surface then please select the work environment of Surface. A Non-Continuous Shift Worker is typically rostered to work between Monday and Friday on rotating or fixed shifts, or over seven days of the week, including public holidays, on fixed shifts. Shifts may rotate between Days, (Afternoons) and Nights or the worker may be permanently rostered to Days, (Afternoons or) Night Shift. An employee who is rostered to work Days over seven days of the week, including public holidays, is a Non-Continuous Shift Worker. | EB7: For Energy and Mining Clients (If Possible) Select employee's general roster. Required for all Mining Companies and for Energy Offshore Companies. 2/1 - is typically a FIFO roster which refers to working two weeks on and then having one week off. This would typically consist of 12-hour shifts worked for 14 days straight, prior to having seven days off. 5/2 - is mostly applied to a head office role which refers to working 5 days and then having 2 days off. These rosters are also applicable to support workers on site and hours worked will vary. Site based roles may also work this roster type depending on the sites location. The employee would work days only Monday to Friday with no weekend work. 8/6 - is normally consists of 12 hour shifts working both day and night, 8 days on, 6 days off. Typically a FIFO roster, working day and night shift. 9/5 - normally consists of 12 hour shifts working 9 days on, 5 days off. Typically works a day or shift non-continuous work pattern. Even - The even time roster refers to an employee working an equal amount of time spent at work as time spent off work - examples include 28/28, 14/14, 7/7 days, 3D3N6rx12hrs, 4D4N8rx12hrs, 2D3r2D2r3D2rx12hrs Other - Please select Other if your employee does not work any of the standard roster panels provided | EC7: For Energy and Mining clients (If Possible) Enter "Yes" or "No" if the employee is in an Energy or Mining Offshore Role. | ED7: For All Employees (If Possible) Enter the employee's birth year (YYYY), do not provide the employee's full date of birth. | EE7: For All Employees (If Possible) Enter the employee's gender from the following options. ▪ Male ▪ Female ▪ Other | EF7: For US Employees Only (If Possible) Enter the employee's ethnicity/race as outlined by U.S. Census Bureau: ▪ American Indian or Alaskan Native ▪ Asian ▪ Black or African American ▪ Hispanic or Latino ▪ Native Hawaiian or Other Pacific Islander ▪ White ▪ Other | EG7: For All Employees (If Possible) Select the highest degree earned by the employee. ▪ Associate Degree ▪ Bachelors ▪ Masters ▪ PhD ▪ PhD & MD ▪ Juris Doctor ▪ Doctor of Dental Medicine ▪ PharmD ▪ Medical Doctor ▪ Foundation Degree ▪ Doctor of Veterinary Medicine | EH7: For All Employees (If Possible) Enter the Highest Degree Earned graduation year for each employee. Please use format YYYY (e.g. 2002, 2018). | EI7: For All Eligible Employees (If Possible) Enter the degree earned if the employee was recently hired as a new college graduate during the last 12 months. ▪ Bachelors ▪ Masters ▪ PhD | EJ7: For All Employees (If Possible) Enter the number of weekly hours the employee’s employment contract is based upon. | EK7: For part-time employees (Mandatory) and for all other employees (If Possible), please submit the percentage of full-time equivalent they work. Example, if an employee works 50% of the full-time equivalent please enter "50". | EL7: For All Employees (If Possible) Enter the employee's Worker Location type from the options below: - Office-Based: employee is physically in a company office every working day - Hybrid: employee is working a minimum of one day a week in a company office - Virtual: employee is fully working at their residence | EM7: For All Employees (If Possible) Enter the employee’s performance rating for the last fiscal year based on your firm’s performance criteria ranking system (e.g., 1 - substantially below expectations to 5 - substantially above expectations). For market alignment, the lowest level of performance should be a lower number. | EN7: For Financial Services Employees Only (If Possible) Enter the employee's corporate title in the current fiscal year from the options below: - Managing Director (or Chairman, Vice Chairman, First Vice President or Executive Vice President) - Director (or Principal, Senior Vice President or Executive Director) - Vice President - Assistant Vice President (or Officer below Vice President) - Associate - Analyst - Employees below Analyst who are NOT Overtime Eligible - Employees below Analyst who are Overtime Eligible | EO7: For All Global Markets & Investment Banking Employees (If Possible) Enter Yes’ if the employee is the Sales or Trading Desk Manager (MD level) or "No" if they are not the desk manager. | EP7: For the employees mapped to the Consulting & Professional Services module (If Possible) Enter the employee's total billed hours for the last performance year completed. | EQ7: For All Wealth Management Employees (If Possible) Enter the employees Wealth Management Client Segment alignment from the following options: - Mass Affluent (US Only) - Affluent - High Net Worth - Ultra High Net Worth | ER7: For Wealth Management Employees (If Possible) Enter the appropriate Offshore or Onshore indicator as outlined below: - Offshore: includes Private Bankers who are primarily responsible for relationships with non-domestic based clients. - Onshore: includes Private Bankers who are primarily responsible for relationships with domestic based clients. | ES7: For Wealth Management Employees (If Possible) Enter the Client Geographic Focus for each respective employee from the following options: - Global - United States - Canada - Latin America - Asia Pacific - Europe - Northern Europe - United Kingdom - Scandinavia - Southern Europe - Western Europe - Switzerland - Russia & Eastern Europe - Middle East - Levant - Africa - South Africa | ET7: For Financial Services Employees Only (If Possible) Enter “Yes” for those employees who have been designated as Identified Staff / Material Risk Taker / Code Staff / Covered Employee (or equivalent) under one or more of the various financial services regulatory pay regimes. Such designation is typically based on falling into one of the following categories: Senior executives (including executives on the main board) and others who are responsible for oversight and/or day-to-day management of the organization's firm-wide activities or material business lines. Individual employees, including non-executive employees, whose activities may expose the organization to material amounts of risk. Other criteria as appropriate under applicable regulatory requirements – examples include senior control function employees; those with pay levels or structures in excess of certain thresholds; regulator-approved roles. Those identified as “Identified Staff” as a result of belonging to a group of employees who in the aggregate may expose the organization to material amounts of risk should not be included here. | EU7: For Financial Technology Employees Only (If Possible) Enter the corresponding industry alignment that reflects the focus of the individual employee and/or business line: - Firm-wide / Multi-Line Business - Alternative Financing / Marketplace Lending - Blockchain / Crypto - Capital Markets - Insurtech - IT Outsourcing & Services / Data Management - Payment Solutions - Risk / Compliance - Research / Market Data - Wealth Management | EV7: For Insurance Clients (If Possible) Enter the business alignment code and name that applies to each employee, select from the valid options and definitions on the Insurance Business Alignment tab. | EW7: For Investor Services Employees (If Possible) Enter the Investor Services Business Alignment from the following options: - Alternatives - Custody / Depositary Receipts - Corporate Trust - Third Party Administration | EX7: For Private Equity Employees (If Possible) If the employee is a participant in a current active Carried Interest Plan (i.e. has the employee received an allocation for a carried interest scheme that is actively investing): - Participant – employee is a participant by receiving points in an active Carried Interest Plan - Not a participant – employee is not a participant and has not been allocated points in an active Carried Interest Plan | EY7: For All Eligible Australia Employees (If Possible) Enter "Yes" or "No" to indicate if the employee's employment terms and conditions are underpinned by an Enterprise Bargaining Agreement/Award. | EZ7: Aon provided 2023 McLagan client code | FA7: Aon provided 2023 Radford client code | FB7: For reference purposes only, this field provides the legacy survey code from 2023 participation. | FC7: For reference purposes only, this field provides the legacy job code from 2023 participation. | FD7: For reference purposes only, this field provides the legacy survey name from 2023 participation. | FE7: For reference purposes only, this field provides the legacy job name from 2023 participation.
B8: Example Row | C8: Example10 | D8: Valid Options Examples (please refer to Location and Currency Codes tab) | F8: 06905 | G8: Stamford | H8: CT | I8: INF | J8: CB | K8: PM | L8: PM | M8: M3 | N8: CB.PMPM.M3 | O8: Infrastructure | P8: Corporate & Business Services | Q8: Project Management | R8: Project Management | S8: Management | T8: Corporate & Business Services - Project Management - Project Management | U8: Valid Options Examples (please refer to Industry Definitions) | V8: Human Capital Solutions | W8: Project Manager | X8: 121509 | Y8: Example1 | Z8: Valid Options List | AA8: Valid Options List | AB8: Valid Options List | AC8: 43130 | AD8: 2022 | AE8: $$$$.$$ | AF8: Valid Options List | AG8: #### | AH8: 1 | AI8: Valid Options List | AJ8: Valid Options List | AK8: Valid Options List | AL8: Valid Options Examples (please refer to Locations & Currencies) | AM8: $$$$.$$ | AN8: $$$$.$$ | AO8: $$.$$ | AP8: $$.$$ | AQ8: $$.$$ | AR8: $$$$.$$ | AS8: $$$$.$$ | AT8: $$$$.$$ | AU8: Valid Options List | AV8: Valid Options List | AW8: $$$$.$$ | AX8: $$$$.$$ | AY8: $$$$.$$ | AZ8: $$$$.$$ | BA8: $$$$.$$ | BB8: $$$$.$$ | BC8: $$$$.$$ | BD8: $$$$.$$ | BE8: $$$$.$$ | BF8: $$$$.$$ | BG8: $$$$.$$ | BH8: $$$$.$$ | BI8: $$$$.$$ | BJ8: $$$$.$$ | BK8: $$$$.$$ | BL8: $$$$.$$ | BM8: $$$$.$$ | BN8: Valid Options Examples (please refer to Location and Currency Codes tab) | BO8: Valid Options List | BP8: ##.## | BQ8: $$$$.$$ | BR8: ##.## | BS8: $$$$.$$ | BT8: ##.## | BU8: $$$$.$$ | BV8: $$$$.$$ | BW8: $$$$.$$ | BX8: $$$$.$$ | BY8: 10 | BZ8: $$$$.$$ | CA8: $$$$.$$ | CB8: $$$$.$$ | CC8: $$$$.$$ | CD8: $$$$.$$ | CE8: $$.$$ | CF8: $$$$.$$ | CG8: $$$$.$$ | CH8: Valid Options List | CI8: $$$$.$$ | CJ8: $$$$.$$ | CK8: $$$$.$$ | CL8: $$$$.$$ | CM8: $$$$.$$ | CN8: $$$$.$$ | CO8: 5 | CP8: $$$$.$$ | CQ8: $$$$.$$ | CR8: $$$$.$$ | CS8: Valid Options List | CT8: $$$$.$$ | CU8: $$$$.$$ | CV8: $$$$.$$ | CW8: $$$$.$$ | CX8: $$$$.$$ | CY8: $$$$.$$ | CZ8: $$$$.$$ | DA8: $$$$.$$ | DB8: $$$$.$$ | DC8: Valid Options List | DD8: ##.## | DE8: $$$$.$$ | DF8: ##.## | DG8: $$$$.$$ | DH8: ##.## | DI8: $$$$.$$ | DJ8: $$$$.$$ | DK8: ##.## | DL8: ##.## | DM8: $$$$.$$ | DN8: ##.## | DO8: Valid Options List | DP8: Valid Options List | DQ8: $$$$.$$ | DR8: Valid Options List | DS8: Valid Options List | DT8: Valid Options List | DU8: Valid Options List | DV8: Valid Options List | DW8: Valid Options Examples (please refer to Life Sciences Alignment) | DX8: Valid Options List | DY8: Valid Options Examples (please refer to Energy & Mining Specialty) | DZ8: Valid Options List | EA8: Valid Options List | EB8: Valid Options List | EC8: Valid Options List | ED8: 1995 | EE8: Valid Options List | EF8: Valid Options List | EG8: Valid Options List | EH8: 2017 | EI8: Valid Options List | EJ8: 40 | EK8: 100 | EL8: Valid Options List | EM8: 5 | EN8: Valid Options List | EO8: Valid Options List | EP8: 50 | EQ8: Valid Options List | ER8: Valid Options List | ES8: Valid Options List | ET8: Yes | EU8: Valid Options List | EV8: Valid Options Examples (please refer to Insurance Business Alignment) | EW8: Valid Options List | EX8: Valid Options List | EY8: Valid Options List | EZ8: Example Row | FA8: Example Row | FB8: US.FININF | FC8: OP.MADA.06 | FD8: United States - Financial Services - Infrastructure | FE8: Operations - Multi-Area - Static Data / Data Management - Manager
B9: 26118CX0 | C9: 100683 | D9: AE | E9: United Arab Emirates | F9: 473828 | G9: Dubai | H9: Dubai | I9: TEC | J9: EN | K9: SO | L9: DE | M9: M4 | N9: EN.SODE.M4 | O9: Technology Solutions | P9: Engineering | Q9: Software | R9: Software Development Engineering | S9: Senior Manager / Associate Director (M4) | T9: Engineering - Software - Software Development Engineering | U9: TS01 - Software Products/Services | W9: Senior Manager, Engineering | X9: Senior Manager, Engineering | Y9: 100717 | AA9: P | AB9: Full-Time | AC9: 44487 | AD9: 2024 | AL9: AED | AM9: 661873.21 | AU9: No | AV9: No | AW9: 0 | AY9: 0 | BN9: USD | BO9: Yes | BP9: 5676 | BQ9: 6.34 | CC9: 728060.53 | CH9: No | CI9: 0 | CO9: 11 United Arab Emirates Base - USD | CQ9: 187151 | DC9: No | DK9: 0 | ED9: 1994 | EE9: Male | EJ9: 40 | EK9: 100 | EL9: Virtual
B10: 26118CX0 | C10: 100455 | D10: AR | E10: Argentina | F10: 1676 | G10: Santos Lugares | H10: Buenos Aires | I10: TEC | J10: EN | K10: SO | L10: DE | M10: P4 | N10: EN.SODE.P4 | O10: Technology Solutions | P10: Engineering | Q10: Software | R10: Software Development Engineering | S10: Advanced (P4) | T10: Engineering - Software - Software Development Engineering | U10: TS01 - Software Products/Services | W10: Staff Software Engineer | X10: Staff Software Engineer | Y10: 100189 | AB10: Full-Time | AC10: 44256 | AD10: 2022 | AL10: ARS | AM10: 36122100 | AU10: No | AV10: No | AW10: 0 | AY10: 0 | BN10: USD | BO10: Yes | BP10: 5676 | BQ10: 6.34 | CC10: 37259947 | CH10: No | CI10: 0 | CO10: 10 Argentina Base - USD | CQ10: 116415 | DC10: No | DK10: 0 | ED10: 1978 | EE10: Male | EJ10: 40 | EK10: 100 | EL10: Virtual
B11: 26118CX0 | C11: 100775 | D11: AR | E11: Argentina | F11: 5539 | G11: El Challao | H11: Mendoza | I11: TEC | J11: EN | K11: SO | L11: DE | M11: P5 | N11: EN.SODE.P5 | O11: Technology Solutions | P11: Engineering | Q11: Software | R11: Software Development Engineering | S11: Expert (P5) | T11: Engineering - Software - Software Development Engineering | U11: TS01 - Software Products/Services | W11: Principal Software Engineer | X11: Principal Software Engineer I | Y11: 101982 | AB11: Full-Time | AC11: 44573 | AD11: 2023 | AL11: ARS | AM11: 50541029 | AU11: No | AV11: No | AW11: 0 | AY11: 0 | BN11: USD | BO11: Yes | BP11: 14196 | BQ11: 6.34 | CC11: 52057262 | CH11: No | CI11: 0 | CO11: 11 Argentina Base - USD | CQ11: 132082 | DC11: No | DK11: 0 | ED11: 1967 | EE11: Male | EJ11: 40 | EK11: 100 | EL11: Virtual
B12: 26118CX0 | C12: 100776 | D12: AR | E12: Argentina | F12: C1426AQT | G12: Buenos Aires | H12: Buenos Aires | I12: TEC | J12: EN | K12: SO | L12: DE | M12: P3 | N12: EN.SODE.P3 | O12: Technology Solutions | P12: Engineering | Q12: Software | R12: Software Development Engineering | S12: Career (P3) | T12: Engineering - Software - Software Development Engineering | U12: TS01 - Software Products/Services | W12: Senior Software Engineer | X12: Senior Software Engineer | Y12: 101550 | AA12: P | AB12: Full-Time | AC12: 44508 | AD12: 2024 | AL12: ARS | AM12: 27034471 | AU12: No | AV12: No | AW12: 0 | AY12: 0 | BN12: USD | BO12: Yes | BP12: 1656 | BQ12: 6.34 | CC12: 29737918 | CH12: No | CI12: 0 | CO12: 09 Argentina Base - USD | CQ12: 102750 | DC12: No | DK12: 0 | ED12: 1987 | EE12: Male | EJ12: 40 | EK12: 100 | EL12: Virtual
B13: 26118CX0 | C13: 100817 | D13: AR | E13: Argentina | F13: 1712 | G13: Castelar | H13: Buenos Aires | I13: TEC | J13: EN | K13: SO | L13: DE | M13: P3 | N13: EN.SODE.P3 | O13: Technology Solutions | P13: Engineering | Q13: Software | R13: Software Development Engineering | S13: Career (P3) | T13: Engineering - Software - Software Development Engineering | U13: TS01 - Software Products/Services | W13: Senior Software Engineer | X13: Senior Software Engineer | Y13: 100639 | AB13: Full-Time | AC13: 44543 | AD13: 2023 | AL13: ARS | AM13: 30091703 | AU13: No | AV13: No | AW13: 0 | AY13: 0 | BN13: USD | BO13: Yes | BP13: 8260 | BQ13: 6.34 | CC13: 31445829 | CH13: No | CI13: 0 | CO13: 09 Argentina Base - USD | CQ13: 102750 | DC13: No | DK13: 0 | ED13: 1982 | EE13: Male | EJ13: 40 | EK13: 100 | EL13: Virtual
B14: 26118CX0 | C14: 100838 | D14: AR | E14: Argentina | F14: 1429 | G14: Capital Federal | H14: Buenos Aires | I14: TEC | J14: EN | K14: SO | L14: DE | M14: P4 | N14: EN.SODE.P4 | O14: Technology Solutions | P14: Engineering | Q14: Software | R14: Software Development Engineering | S14: Advanced (P4) | T14: Engineering - Software - Software Development Engineering | U14: TS01 - Software Products/Services | W14: Staff Software Engineer | X14: Staff Software Engineer | Y14: 102078 | AB14: Full-Time | AC14: 44578 | AD14: 2023 | AL14: ARS | AM14: 32543529 | AU14: No | AV14: No | AW14: 0 | AY14: 0 | BN14: USD | BO14: Yes | BP14: 13210 | BQ14: 6.34 | CC14: 33601194 | CH14: No | CI14: 0 | CO14: 10 Argentina Base - USD | CQ14: 116415 | DC14: No | DK14: 0 | ED14: 1995 | EE14: Male | EJ14: 40 | EK14: 100 | EL14: Virtual
B15: 26118CX0 | C15: 100902 | D15: AR | E15: Argentina | F15: 1642 | G15: San Isidro | H15: Buenos Aires | I15: INF | J15: HR | K15: TM | L15: TA | M15: P4 | N15: HR.TMTA.P4 | O15: Infrastructure | P15: Human Resources | Q15: Talent Management | R15: Talent Acquisition | S15: Advanced (P4) | T15: Human Resources - Talent Management - Talent Acquisition | U15: TS01 - Software Products/Services | W15: Senior Recruiter | X15: Senior Recruiter I | Y15: 100530 | AB15: Full-Time | AC15: 44613 | AD15: 2023 | AL15: ARS | AM15: 26791106 | AU15: No | AV15: No | AW15: 0 | AY15: 0 | BN15: USD | BO15: Yes | BP15: 5638 | BQ15: 6.34 | CC15: 28130662 | CH15: No | CI15: 0 | CO15: 08 Argentina Base - USD | CQ15: 91025 | DC15: No | DK15: 0 | ED15: 1988 | EE15: Female | EJ15: 40 | EK15: 100 | EL15: Virtual
B16: 26118CX0 | C16: 101164 | D16: AR | E16: Argentina | F16: 1429 | G16: Caba | H16: Buenos Aires | I16: TEC | J16: EN | K16: SO | L16: DE | M16: P4 | N16: EN.SODE.P4 | O16: Technology Solutions | P16: Engineering | Q16: Software | R16: Software Development Engineering | S16: Advanced (P4) | T16: Engineering - Software - Software Development Engineering | U16: TS01 - Software Products/Services | W16: Staff Software Engineer | X16: Staff Software Engineer | Y16: 101548 | AB16: Full-Time | AC16: 44746 | AD16: 2023 | AL16: ARS | AM16: 30832941 | AU16: No | AV16: No | AW16: 0 | AY16: 0 | BN16: USD | BO16: Yes | BP16: 13210 | BQ16: 6.34 | CC16: 31835012 | CH16: No | CI16: 0 | CO16: 10 Argentina Base - USD | CQ16: 116415 | DC16: No | DK16: 0 | ED16: 1995 | EE16: Male | EJ16: 40 | EK16: 100 | EL16: Virtual
B17: 26118CX0 | C17: 101185 | D17: AR | E17: Argentina | F17: 1900 | G17: La Plata | H17: Buenos Aires | I17: TEC | J17: EN | K17: SO | L17: DE | M17: P3 | N17: EN.SODE.P3 | O17: Technology Solutions | P17: Engineering | Q17: Software | R17: Software Development Engineering | S17: Career (P3) | T17: Engineering - Software - Software Development Engineering | U17: TS01 - Software Products/Services | W17: Senior Frontend Engineer | X17: Senior Software Engineer | Y17: 101881 | AA17: N | AB17: Full-Time | AC17: 45419 | AD17: 2024 | AL17: ARS | AU17: No | AV17: No | AW17: 0 | AY17: 0 | BN17: USD | BO17: No | BP17: 2485 | BQ17: 6.34 | CC17: 28492941 | CH17: No | CI17: 0 | CO17: 09 Argentina Base - USD | CQ17: 102750 | DC17: Yes | DD17: 0 | DE17: 6.34 | DF17: 14462 | DG17: 9.01 | DK17: 14462 | ED17: 1989 | EE17: Female | EJ17: 40 | EK17: 100 | EL17: Virtual
B18: 26118CX0 | C18: 101257 | D18: AR | E18: Argentina | F18: 1842 | G18: Monte Grande | H18: Buenos Aires | I18: TEC | J18: EN | K18: SO | L18: DE | M18: P3 | N18: EN.SODE.P3 | O18: Technology Solutions | P18: Engineering | Q18: Software | R18: Software Development Engineering | S18: Career (P3) | T18: Engineering - Software - Software Development Engineering | U18: TS01 - Software Products/Services | W18: Senior Software Engineer | X18: Senior Software Engineer | Y18: 100639 | AB18: Full-Time | AC18: 44802 | AD18: 2023 | AL18: ARS | AM18: 28492941 | AU18: No | AV18: No | AW18: 0 | AY18: 0 | BN18: USD | BO18: Yes | BP18: 2485 | BQ18: 6.34 | CC18: 29418962 | CH18: No | CI18: 0 | CO18: 09 Argentina Base - USD | CQ18: 102750 | DC18: No | DK18: 0 | ED18: 1995 | EE18: Male | EJ18: 40 | EK18: 100 | EL18: Virtual
B19: 26118CX0 | C19: 101839 | D19: AR | E19: Argentina | F19: 5000 | G19: Cordoba | H19: Cordoba | I19: TEC | J19: EN | K19: SO | L19: DE | M19: P2 | N19: EN.SODE.P2 | O19: Technology Solutions | P19: Engineering | Q19: Software | R19: Software Development Engineering | S19: Developing (P2) | T19: Engineering - Software - Software Development Engineering | U19: TS01 - Software Products/Services | W19: Software Engineer | X19: Software Engineer II | Y19: 101548 | AB19: Full-Time | AC19: 45167 | AD19: 2023 | AL19: ARS | AM19: 21511176 | AU19: No | AV19: No | AW19: 0 | AY19: 0 | BN19: USD | BO19: Yes | BP19: 12000 | BQ19: 6.34 | CC19: 22694291 | CH19: No | CI19: 0 | CO19: 07 Argentina Base - USD | CQ19: 80826 | DC19: No | DK19: 0 | ED19: 1993 | EE19: Male | EJ19: 40 | EK19: 100 | EL19: Virtual
B20: 26118CX0 | C20: 101914 | D20: AR | E20: Argentina | F20: 1406 | G20: Ciudad Autonoma de Buenos Aires | H20: Capital Federal | I20: TEC | J20: EN | K20: SO | L20: DE | M20: P3 | N20: EN.SODE.P3 | O20: Technology Solutions | P20: Engineering | Q20: Software | R20: Software Development Engineering | S20: Career (P3) | T20: Engineering - Software - Software Development Engineering | U20: TS01 - Software Products/Services | W20: Senior Software Engineer | X20: Senior Software Engineer | Y20: 100346 | AA20: N | AB20: Full-Time | AC20: 45300 | AD20: 2024 | AL20: ARS | AU20: No | AV20: No | AW20: 0 | AY20: 0 | BN20: USD | BO20: No | BP20: 0 | BQ20: 6.34 | CC20: 37259947 | CH20: No | CI20: 0 | CO20: 09 Argentina Base - USD | CQ20: 102750 | DC20: Yes | DD20: 21000 | DE20: 6.34 | DF20: 0 | DG20: 9.01 | DK20: 21000 | ED20: 1989 | EE20: Male | EJ20: 40 | EK20: 100 | EL20: Virtual
B21: 26118CX0 | C21: 102025 | D21: AR | E21: Argentina | F21: 1604 | G21: Florida Oeste | H21: Buenos Aires | I21: TEC | J21: EN | K21: SO | L21: DE | M21: P3 | N21: EN.SODE.P3 | O21: Technology Solutions | P21: Engineering | Q21: Software | R21: Software Development Engineering | S21: Career (P3) | T21: Engineering - Software - Software Development Engineering | U21: TS01 - Software Products/Services | W21: Senior Software Engineer | X21: Senior Software Engineer | Y21: 100808 | AA21: N | AB21: Full-Time | AC21: 45419 | AD21: 2024 | AL21: ARS | AU21: No | AV21: No | AW21: 0 | AY21: 0 | BN21: USD | BO21: No | BP21: 0 | BQ21: 6.34 | CC21: 37259947 | CH21: No | CI21: 0 | CO21: 09 Argentina Base - USD | CQ21: 102750 | DC21: Yes | DD21: 0 | DE21: 6.34 | DF21: 16562 | DG21: 9.01 | DK21: 16562 | ED21: 1975 | EE21: Male | EJ21: 40 | EK21: 100 | EL21: Virtual
B22: 26118CX0 | C22: 100487 | D22: AT | E22: Austria | F22: 4072 | G22: Alkoven | H22: Upper Austria | I22: SLS | J22: SA | K22: FS | L22: DN | M22: P4 | N22: SA.FSDN.P4 | O22: Sales | P22: Sales | Q22: Field Sales - Sales Account Management | R22: Direct Sales - New Accounts | S22: Advanced (P4) | T22: Sales - Field Sales - Sales Account Management - Direct Sales - New Accounts | U22: TS01 - Software Products/Services | W22: Senior Enterprise Account Executive | X22: Senior Enterprise Account Executive | Y22: 101260 | AA22: P | AB22: Full-Time | AC22: 44319 | AD22: 2024 | AL22: EUR | AM22: 112500 | AU22: Yes | AV22: Yes | AW22: 155003.92 | AY22: 112500 | BN22: USD | BO22: Yes | BP22: 0 | BQ22: 6.34 | CC22: 112500 | CH22: Yes | CI22: 112500 | CO22: Sales 06 Austria Sales | CQ22: 107500 | DC22: No | DK22: 0 | DO22: Individual | DP22: Individual | ED22: 1981 | EE22: Male | EJ22: 38.5 | EK22: 100 | EL22: Virtual
B23: 26118CX0 | C23: 100497 | D23: AT | E23: Austria | F23: 6850 | G23: Dornbirn | H23: Vorarlberg | I23: TEC | J23: EN | K23: SO | L23: DE | M23: P4 | N23: EN.SODE.P4 | O23: Technology Solutions | P23: Engineering | Q23: Software | R23: Software Development Engineering | S23: Advanced (P4) | T23: Engineering - Software - Software Development Engineering | U23: TS01 - Software Products/Services | W23: Staff Software Engineer | X23: Staff Software Engineer | Y23: 101795 | AA23: P | AB23: Full-Time | AC23: 44333 | AD23: 2024 | AL23: EUR | AM23: 111751.88 | AU23: No | AV23: No | AW23: 0 | AY23: 0 | BN23: USD | BO23: Yes | BP23: 4260 | BQ23: 6.34 | CC23: 122927.07 | CH23: No | CI23: 0 | CO23: 10 Austria Base | CQ23: 133128 | DC23: No | DK23: 0 | ED23: 1984 | EE23: Male | EJ23: 38.5 | EK23: 100 | EL23: Virtual
B24: 26118CX0 | C24: 100580 | D24: AT | E24: Austria | F24: 5202 | G24: Salzburg | H24: Salzburg | I24: SLS | J24: SA | K24: AS | L24: PS | M24: P4 | N24: SA.ASPS.P4 | O24: Sales | P24: Sales | Q24: Applications / Systems Engineering | R24: Post-Sales - Sales Plan | S24: Advanced (P4) | T24: Sales - Applications / Systems Engineering - Post-Sales - Sales Plan | U24: TS01 - Software Products/Services | W24: Senior Observability Architect | X24: Senior Observability Architect | Y24: 100543 | AB24: Full-Time | AC24: 44438 | AD24: 2023 | AL24: EUR | AM24: 112855.58 | AU24: Yes | AV24: Yes | AW24: 32425.13 | AY24: 48370.014 | BN24: USD | BO24: Yes | BP24: 1800 | BQ24: 6.34 | CC24: 91454.52 | CH24: Yes | CI24: 39197.499 | CO24: SE 04 Austria SE | CQ24: 98117 | DC24: No | DK24: 0 | DO24: Individual | DP24: Individual | ED24: 1988 | EE24: Male | EJ24: 30 | EK24: 100 | EL24: Virtual
B25: 26118CX0 | C25: 100758 | D25: AT | E25: Austria | F25: 1020 | G25: Vienna | H25: Vienna | I25: TEC | J25: EN | K25: SO | L25: DE | M25: P3 | N25: EN.SODE.P3 | O25: Technology Solutions | P25: Engineering | Q25: Software | R25: Software Development Engineering | S25: Career (P3) | T25: Engineering - Software - Software Development Engineering | U25: TS01 - Software Products/Services | W25: Senior Software Engineer | X25: Senior Software Engineer | Y25: 100919 | AB25: Full-Time | AC25: 44529 | AD25: 2022 | AL25: EUR | AM25: 109096 | AU25: No | AV25: No | AW25: 0 | AY25: 0 | BN25: USD | BO25: Yes | BP25: 2485 | BQ25: 6.34 | CC25: 115096.28 | CH25: No | CI25: 0 | CO25: 09 Austria Base | CQ25: 117499 | DC25: No | DK25: 0 | ED25: 1985 | EE25: Male | EJ25: 38.5 | EK25: 100 | EL25: Virtual
B26: 26118CX0 | C26: 101150 | D26: AT | E26: Austria | F26: 7111 | G26: Parndorf | H26: Burgenland | I26: TEC | J26: EN | K26: SO | L26: DE | M26: M3 | N26: EN.SODE.M3 | O26: Technology Solutions | P26: Engineering | Q26: Software | R26: Software Development Engineering | S26: Manager (M3) | T26: Engineering - Software - Software Development Engineering | U26: TS01 - Software Products/Services | W26: Engineering Manager | X26: Manager, Engineering | Y26: 100717 | AB26: Full-Time | AC26: 44809 | AD26: 2022 | AL26: EUR | AM26: 134225 | AU26: No | AV26: No | AW26: 0 | AY26: 0 | BN26: USD | BO26: Yes | BP26: 3311 | BQ26: 6.34 | CC26: 138251.75 | CH26: No | CI26: 0 | CO26: 10 Austria Base | CQ26: 133128 | DC26: No | DK26: 0 | ED26: 1989 | EE26: Male | EJ26: 38.5 | EK26: 100 | EL26: Virtual
B27: 26118CX0 | C27: 101240 | D27: AT | E27: Austria | F27: 9130 | G27: Poggersdorf | H27: Carinthia | I27: TEC | J27: EN | K27: SO | L27: DE | M27: P3 | N27: EN.SODE.P3 | O27: Technology Solutions | P27: Engineering | Q27: Software | R27: Software Development Engineering | S27: Career (P3) | T27: Engineering - Software - Software Development Engineering | U27: TS01 - Software Products/Services | W27: Senior Software Engineer | X27: Senior Software Engineer | Y27: 101559 | AB27: Full-Time | AC27: 44816 | AD27: 2022 | AL27: EUR | AM27: 113850 | AU27: No | AV27: No | AW27: 0 | AY27: 0 | BN27: USD | BO27: Yes | BP27: 2485 | BQ27: 6.34 | CC27: 120111.75 | CH27: No | CI27: 0 | CO27: 09 Austria Base | CQ27: 117499 | DC27: No | DK27: 0 | ED27: 1984 | EE27: Male | EJ27: 38.5 | EK27: 100 | EL27: Virtual
B28: 26118CX0 | C28: 101335 | D28: AT | E28: Austria | F28: 8055 | G28: Graz | H28: Styria | I28: TEC | J28: EN | K28: SO | L28: DE | M28: P4 | N28: EN.SODE.P4 | O28: Technology Solutions | P28: Engineering | Q28: Software | R28: Software Development Engineering | S28: Advanced (P4) | T28: Engineering - Software - Software Development Engineering | U28: TS01 - Software Products/Services | W28: Staff Software Engineer | X28: Staff Software Engineer | Y28: 101241 | AB28: Full-Time | AC28: 44900 | AD28: 2022 | AL28: EUR | AM28: 131905 | AU28: No | AV28: No | AW28: 0 | AY28: 0 | BN28: USD | BO28: Yes | BP28: 0 | BQ28: 6.34 | CC28: 136191.91 | CH28: No | CI28: 0 | CO28: 10 Austria Base | CQ28: 133128 | DC28: No | DK28: 0 | ED28: 1981 | EE28: Male | EJ28: 38.5 | EK28: 100 | EL28: Virtual
B29: 26118CX0 | C29: 101556 | D29: AT | E29: Austria | F29: 1120 | G29: Wien | H29: Vienna | I29: TEC | J29: EN | K29: SO | L29: DE | M29: P2 | N29: EN.SODE.P2 | O29: Technology Solutions | P29: Engineering | Q29: Software | R29: Software Development Engineering | S29: Developing (P2) | T29: Engineering - Software - Software Development Engineering | U29: TS01 - Software Products/Services | W29: Developer Experience Engineer | X29: Developer Experience Engineer | Y29: 101042 | AB29: Full-Time | AC29: 45041 | AD29: 2023 | AL29: EUR | AM29: 91785 | AU29: No | AV29: No | AW29: 0 | AY29: 0 | BN29: USD | BO29: Yes | BP29: 15000 | BQ29: 6.34 | CC29: 96833.18 | CH29: No | CI29: 0 | CO29: 07 Austria Base | CQ29: 92428 | DC29: No | DK29: 0 | ED29: 1999 | EE29: Male | EJ29: 38.5 | EK29: 100 | EL29: Virtual
B30: 26118CX0 | C30: 101624 | D30: AT | E30: Austria | F30: 3012 | G30: Wolfsgraben | H30: Lower Austria | I30: SLS | J30: SA | K30: AS | L30: RS | M30: M5 | N30: SA.ASRS.M5 | O30: Sales | P30: Sales | Q30: Applications / Systems Engineering | R30: Pre-Sales - Sales Plan | S30: Director (M5) | T30: Sales - Applications / Systems Engineering - Pre-Sales - Sales Plan | U30: TS01 - Software Products/Services | W30: Director, Solutions Engineering | X30: Director, Solutions Engineering | Y30: 101519 | AB30: Full-Time | AC30: 45041 | AD30: 2024 | AL30: EUR | AM30: 175000 | AU30: Yes | AV30: Yes | AW30: 19245.75 | AY30: 75000.1 | BN30: USD | BO30: Yes | BP30: 30000 | BQ30: 6.34 | CC30: 185500.01 | CH30: Yes | CI30: 79500.11 | CO30: SE 10 Austria SE | CQ30: 161123 | DC30: No | DK30: 0 | DO30: Team | DP30: Team | ED30: 1988 | EE30: Male | EJ30: 38.5 | EK30: 100 | EL30: Virtual
B31: 26118CX0 | C31: 100101 | D31: AU | E31: Australia | F31: 6015 | G31: City Beach | H31: Western Australia | I31: EXE | J31: EN | K31: GL | L31: CC | M31: E5 | N31: EN.GLCC.E5 | O31: Executive | P31: Engineering | Q31: General | R31: Chief Technical Officer - Corporate | S31: Executive 5 (E5) | T31: Engineering - General - Chief Technical Officer - Corporate | U31: TS01 - Software Products/Services | V31: Grafana Labs | W31: CTO & Co-Founder | X31: Co-Founder | Y31: 100102 | AB31: Full-Time | AC31: 41913 | AD31: 2021 | AF31: Corporate | AH31: 1 | AJ31: Global | AK31: Yes | AL31: AUD | AM31: 350500 | AR31: 40307.5 | AU31: Yes | AV31: Yes | AW31: 64302.4 | AY31: 112160 | BN31: USD | BO31: Yes | BP31: 0 | BQ31: 6.34 | CC31: 350500 | CH31: Yes | CI31: 112160 | CL31: 40307.5 | CO31: SLT Australia SLT | CQ31: 500000 | DC31: No | DK31: 0 | ED31: 1982 | EE31: Male | EJ31: 40 | EK31: 100 | EL31: Virtual
B32: 26118CX0 | C32: 100625 | D32: AU | E32: Australia | F32: 4350 | G32: East Toowoomba | H32: Queensland | I32: INF | J32: CS | K32: FS | L32: TS | M32: P3 | N32: CS.FSTS.P3 | O32: Infrastructure | P32: Customer Service / Support | Q32: Field Support | R32: Technical Support Engineering | S32: Career (P3) | T32: Customer Service / Support - Field Support - Technical Support Engineering | U32: TS01 - Software Products/Services | W32: Technical Support Engineer | X32: Technical Support Engineer I | Y32: 101295 | AB32: Full-Time | AC32: 44405 | AD32: 2022 | AL32: AUD | AM32: 164673.6 | AR32: 18937.46 | AU32: No | AV32: No | AW32: 0 | AY32: 0 | BM32: 4940.21 | BN32: USD | BO32: Yes | BP32: 1200 | BQ32: 6.34 | CC32: 171260.54 | CH32: No | CI32: 0 | CL32: 19694.96 | CO32: 06 Australia Base | CQ32: 138298 | DB32: 5137.82 | DC32: No | DK32: 0 | ED32: 1982 | EE32: Male | EJ32: 40 | EK32: 100 | EL32: Virtual
B33: 26118CX0 | C33: 100667 | D33: AU | E33: Australia | F33: 3282 | G33: Koroit | H33: Victoria | I33: TEC | J33: EN | K33: SO | L33: DE | M33: M5 | N33: EN.SODE.M5 | O33: Technology Solutions | P33: Engineering | Q33: Software | R33: Software Development Engineering | S33: Director (M5) | T33: Engineering - Software - Software Development Engineering | U33: TS01 - Software Products/Services | W33: Engineering Director | X33: Director, Engineering | Y33: 100277 | AB33: Full-Time | AC33: 44452 | AD33: 2021 | AL33: AUD | AM33: 352437.28 | AR33: 40530.29 | AU33: No | AV33: No | AW33: 0 | AY33: 0 | BN33: USD | BO33: Yes | BP33: 11592 | BQ33: 6.34 | CC33: 352437.28 | CH33: No | CI33: 0 | CL33: 40530.29 | CO33: 12 Australia Base | CQ33: 292277 | DC33: No | DK33: 0 | ED33: 1968 | EE33: Male | EJ33: 40 | EK33: 100 | EL33: Virtual
B34: 26118CX0 | C34: 100740 | D34: AU | E34: Australia | F34: 2177 | G34: Sydney | H34: New South Wales | I34: INF | J34: CS | K34: FS | L34: TS | M34: P4 | N34: CS.FSTS.P4 | O34: Infrastructure | P34: Customer Service / Support | Q34: Field Support | R34: Technical Support Engineering | S34: Advanced (P4) | T34: Customer Service / Support - Field Support - Technical Support Engineering | U34: TS01 - Software Products/Services | W34: Technical Support Engineer | X34: Technical Support Engineer II | Y34: 101295 | AA34: P | AB34: Full-Time | AC34: 44494 | AD34: 2024 | AL34: AUD | AM34: 176030.4 | AR34: 20243.5 | AU34: No | AV34: No | AW34: 0 | AY34: 0 | BM34: 8801.52 | BN34: USD | BO34: Yes | BP34: 560 | BQ34: 6.34 | CC34: 181311.31 | CH34: No | CI34: 0 | CL34: 20850.8 | CO34: 07 Australia Base | CQ34: 157521 | DB34: 9065.57 | DC34: No | DK34: 0 | ED34: 1988 | EE34: Male | EJ34: 40 | EK34: 100 | EL34: Virtual
B35: 26118CX0 | C35: 100786 | D35: AU | E35: Australia | F35: 3216 | G35: Geelong | H35: Victoria | I35: TEC | J35: EN | K35: UU | L35: UD | M35: P3 | N35: EN.UUUD.P3 | O35: Technology Solutions | P35: Engineering | Q35: User Interface/User Experience (UI/UX) | R35: UI / UX Design | S35: Career (P3) | T35: Engineering - User Interface/User Experience (UI/UX) - UI / UX Design | U35: TS01 - Software Products/Services | W35: Senior Product Designer | X35: Senior Product Designer | Y35: 100561 | AB35: Full-Time | AC35: 44536 | AD35: 2022 | AL35: AUD | AM35: 171395.83 | AR35: 19710.52 | AU35: No | AV35: No | AW35: 0 | AY35: 0 | BN35: USD | BO35: Yes | BP35: 2485 | BQ35: 6.34 | CC35: 171395.83 | CH35: No | CI35: 0 | CL35: 19710.52 | CO35: 08 Australia Base | CQ35: 177401 | DC35: No | DK35: 0 | ED35: 1987 | EE35: Male | EJ35: 40 | EK35: 100 | EL35: Virtual
B36: 26118CX0 | C36: 101009 | D36: AU | E36: Australia | F36: 2064 | G36: Artarmon | H36: New South Wales | I36: SLS | J36: SA | K36: AS | L36: RS | M36: P6 | N36: SA.ASRS.P6 | O36: Sales | P36: Sales | Q36: Applications / Systems Engineering | R36: Pre-Sales - Sales Plan | S36: Principal / Consultant (P6) | T36: Sales - Applications / Systems Engineering - Pre-Sales - Sales Plan | U36: TS01 - Software Products/Services | W36: Principal Solutions Engineer | X36: Principal Solutions Engineer | Y36: 101994 | AB36: Full-Time | AC36: 44676 | AD36: 2022 | AL36: AUD | AM36: 229051.45 | AR36: 26340.92 | AU36: Yes | AV36: Yes | AW36: 43194.57 | AY36: 98165.038 | BN36: USD | BO36: Yes | BP36: 0 | BQ36: 6.34 | CC36: 229051.45 | CH36: Yes | CI36: 98165.038 | CL36: 26340.92 | CO36: SE 06 Australia SE | CQ36: 224359 | DC36: No | DK36: 0 | DO36: Individual | DP36: Individual | ED36: 1977 | EE36: Male | EJ36: 40 | EK36: 100 | EL36: Virtual
B37: 26118CX0 | C37: 101010 | D37: AU | E37: Australia | F37: 2065 | G37: St Leonards | H37: New South Wales | I37: SLS | J37: SA | K37: FS | L37: DN | M37: P3 | N37: SA.FSDN.P3 | O37: Sales | P37: Sales | Q37: Field Sales - Sales Account Management | R37: Direct Sales - New Accounts | S37: Career (P3) | T37: Sales - Field Sales - Sales Account Management - Direct Sales - New Accounts | U37: TS01 - Software Products/Services | W37: Enterprise Account Executive | X37: Enterprise Account Executive | Y37: 102110 | AB37: Full-Time | AC37: 44711 | AD37: 2022 | AL37: AUD | AM37: 148500 | AR37: 17077.5 | AU37: Yes | AV37: Yes | AW37: 76589.35 | AY37: 148500 | BN37: USD | BO37: Yes | BP37: 0 | BQ37: 6.34 | CC37: 155000.05 | CH37: Yes | CI37: 155000.05 | CL37: 17825.01 | CO37: Sales 05 Australia Sales | CQ37: 155000 | DC37: No | DK37: 0 | DO37: Individual | DP37: Individual | ED37: 1994 | EE37: Male | EJ37: 40 | EK37: 100 | EL37: Virtual
B38: 26118CX0 | C38: 101066 | D38: AU | E38: Australia | F38: 7008 | G38: Lenah Valley | H38: Tasmania | I38: TEC | J38: EN | K38: SO | L38: DE | M38: P4 | N38: EN.SODE.P4 | O38: Technology Solutions | P38: Engineering | Q38: Software | R38: Software Development Engineering | S38: Advanced (P4) | T38: Engineering - Software - Software Development Engineering | U38: TS01 - Software Products/Services | W38: Staff Software Engineer | X38: Staff Software Engineer | Y38: 100667 | AB38: Full-Time | AC38: 44712 | AD38: 2022 | AL38: AUD | AM38: 237475 | AR38: 27309.63 | AU38: No | AV38: No | AW38: 0 | AY38: 0 | BN38: USD | BO38: Yes | BP38: 3311 | BQ38: 6.34 | CC38: 244599.25 | CH38: No | CI38: 0 | CL38: 28128.91 | CO38: 10 Australia Base | CQ38: 226883 | DC38: No | DK38: 0 | ED38: 1988 | EE38: Male | EJ38: 40 | EK38: 100 | EL38: Virtual
B39: 26118CX0 | C39: 101190 | D39: AU | E39: Australia | F39: 4101 | G39: South Brisbane | H39: Queensland | I39: TEC | J39: EN | K39: SO | L39: DE | M39: P4 | N39: EN.SODE.P4 | O39: Technology Solutions | P39: Engineering | Q39: Software | R39: Software Development Engineering | S39: Advanced (P4) | T39: Engineering - Software - Software Development Engineering | U39: TS01 - Software Products/Services | W39: Senior Solutions Architect | X39: Senior Solutions Architect I | Y39: 100788 | AB39: Full-Time | AC39: 44795 | AD39: 2022 | AL39: AUD | AM39: 234300 | AR39: 26944.5 | AU39: No | AV39: No | AW39: 0 | AY39: 0 | BN39: USD | BO39: Yes | BP39: 2100 | BQ39: 6.34 | CC39: 246015 | CH39: No | CI39: 0 | CL39: 28291.73 | CO39: 10 Australia Base | CQ39: 226883 | DC39: No | DK39: 0 | ED39: 1992 | EE39: Male | EJ39: 40 | EK39: 100 | EL39: Virtual
B40: 26118CX0 | C40: 101194 | D40: AU | E40: Australia | F40: 2113 | G40: Sydney | H40: New South Wales | I40: SLS | J40: SA | K40: IS | L40: TL | M40: S3 | N40: SA.ISTL.S3 | O40: Sales | P40: Sales | Q40: Inside Sales / Telemarketing | R40: Lead Development | S40: Senior (S3) | T40: Sales - Inside Sales / Telemarketing - Lead Development | U40: TS01 - Software Products/Services | W40: Senior Sales Development Representative | X40: Senior Sales Development Representative | Y40: 101499 | AA40: P | AB40: Full-Time | AC40: 44774 | AD40: 2024 | AL40: AUD | AM40: 100000 | AR40: 11500 | AU40: Yes | AV40: Yes | AW40: 24152.76 | AY40: 42857.2 | BN40: USD | BO40: Yes | BP40: 456 | BQ40: 6.34 | CC40: 100000 | CH40: Yes | CI40: 42857.2 | CL40: 11500 | CO40: ISR 02 Australia 70/30 ISR | CQ40: 92750 | DC40: No | DK40: 0 | DO40: Individual | DP40: Individual | ED40: 1993 | EE40: Female | EJ40: 40 | EK40: 100 | EL40: Virtual
B41: 26118CX0 | C41: 101244 | D41: AU | E41: Australia | F41: 4005 | G41: Teneriffe | H41: Queensland | I41: TEC | J41: EN | K41: SO | L41: DE | M41: P4 | N41: EN.SODE.P4 | O41: Technology Solutions | P41: Engineering | Q41: Software | R41: Software Development Engineering | S41: Advanced (P4) | T41: Engineering - Software - Software Development Engineering | U41: TS01 - Software Products/Services | W41: Staff Software Engineer | X41: Staff Software Engineer | Y41: 100667 | AB41: Full-Time | AC41: 44823 | AD41: 2022 | AL41: AUD | AM41: 209674.5 | AR41: 24112.57 | AU41: No | AV41: No | AW41: 0 | AY41: 0 | BN41: USD | BO41: Yes | BP41: 5676 | BQ41: 6.34 | CC41: 216488.92 | CH41: No | CI41: 0 | CL41: 24896.23 | CO41: 10 Australia Base | CQ41: 226883 | DC41: No | DK41: 0 | ED41: 1978 | EE41: Male | EJ41: 40 | EK41: 100 | EL41: Virtual
B42: 26118CX0 | C42: 101295 | D42: AU | E42: Australia | F42: 6026 | G42: Perth | H42: Western Australia | I42: INF | J42: CS | K42: FS | L42: TS | M42: M4 | N42: CS.FSTS.M4 | O42: Infrastructure | P42: Customer Service / Support | Q42: Field Support | R42: Technical Support Engineering | S42: Senior Manager / Associate Director (M4) | T42: Customer Service / Support - Field Support - Technical Support Engineering | U42: TS01 - Software Products/Services | W42: Senior Manager, Technical Support | X42: Senior Manager, Technical Support | Y42: 100491 | AB42: Full-Time | AC42: 44851 | AD42: 2022 | AL42: AUD | AM42: 208000 | AR42: 23920 | AU42: No | AV42: No | AW42: 0 | AY42: 0 | BN42: USD | BO42: Yes | BP42: 2100 | BQ42: 6.34 | CC42: 214240 | CH42: No | CI42: 0 | CL42: 24637.6 | CO42: 08 Australia Base | CQ42: 177401 | DC42: No | DK42: 0 | ED42: 1978 | EE42: Male | EJ42: 40 | EK42: 100 | EL42: Virtual
B43: 26118CX0 | C43: 101325 | D43: AU | E43: Australia | F43: 3146 | G43: Glen Iris | H43: Victoria | I43: TEC | J43: EN | K43: SO | L43: DE | M43: P4 | N43: EN.SODE.P4 | O43: Technology Solutions | P43: Engineering | Q43: Software | R43: Software Development Engineering | S43: Advanced (P4) | T43: Engineering - Software - Software Development Engineering | U43: TS01 - Software Products/Services | W43: Staff Software Engineer | X43: Staff Software Engineer | Y43: 100667 | AB43: Full-Time | AC43: 44865 | AD43: 2022 | AL43: AUD | AM43: 233750 | AR43: 26881.25 | AU43: No | AV43: No | AW43: 0 | AY43: 0 | BN43: USD | BO43: Yes | BP43: 7095 | BQ43: 6.34 | CC43: 245437.5 | CH43: No | CI43: 0 | CL43: 28225.31 | CO43: 10 Australia Base | CQ43: 226883 | DC43: No | DK43: 0 | ED43: 1990 | EE43: Male | EJ43: 40 | EK43: 100 | EL43: Virtual
B44: 26118CX0 | C44: 101425 | D44: AU | E44: Australia | F44: 6171 | G44: Baldivis | H44: Western Australia | I44: INF | J44: CS | K44: FS | L44: TS | M44: P3 | N44: CS.FSTS.P3 | O44: Infrastructure | P44: Customer Service / Support | Q44: Field Support | R44: Technical Support Engineering | S44: Career (P3) | T44: Customer Service / Support - Field Support - Technical Support Engineering | U44: TS01 - Software Products/Services | W44: Technical Support Engineer | X44: Technical Support Engineer I | Y44: 101295 | AB44: Full-Time | AC44: 44935 | AD44: 2023 | AL44: AUD | AM44: 160581.12 | AR44: 18466.83 | AU44: No | AV44: No | AW44: 0 | AY44: 0 | BN44: USD | BO44: Yes | BP44: 12400 | BQ44: 6.34 | CC44: 165398.55 | CH44: No | CI44: 0 | CL44: 19020.83 | CO44: 06 Australia Base | CQ44: 138298 | DC44: No | DK44: 0 | ED44: 1984 | EE44: Male | EJ44: 40 | EK44: 100 | EL44: Virtual
B45: 26118CX0 | C45: 101532 | D45: AU | E45: Australia | F45: 2158 | G45: Middle Dural | H45: New South Wales | I45: INF | J45: CS | K45: FS | L45: TS | M45: P3 | N45: CS.FSTS.P3 | O45: Infrastructure | P45: Customer Service / Support | Q45: Field Support | R45: Technical Support Engineering | S45: Career (P3) | T45: Customer Service / Support - Field Support - Technical Support Engineering | U45: TS01 - Software Products/Services | W45: Support Engineer | X45: Technical Support Engineer I | Y45: 101295 | AB45: Full-Time | AC45: 45013 | AD45: 2023 | AL45: AUD | AM45: 140000 | AR45: 16100 | AU45: No | AV45: No | AW45: 0 | AY45: 0 | BN45: USD | BO45: Yes | BP45: 12400 | BQ45: 6.34 | CC45: 144200 | CH45: No | CI45: 0 | CL45: 16583 | CO45: 06 Australia Base | CQ45: 138298 | DC45: No | DK45: 0 | ED45: 1972 | EE45: Male | EJ45: 40 | EK45: 100 | EL45: Virtual
B46: 26118CX0 | C46: 101678 | D46: AU | E46: Australia | F46: 2040 | G46: Lilyfield | H46: New South Wales | I46: SLS | J46: SA | K46: FS | L46: DS | M46: M5 | N46: SA.FSDS.M5 | O46: Sales | P46: Sales | Q46: Field Sales - Sales Account Management | R46: Direct Sales | S46: Director (M5) | T46: Sales - Field Sales - Sales Account Management - Direct Sales | U46: TS01 - Software Products/Services | W46: Regional Sales Director, Enterprise | X46: Regional Sales Director II, Enterprise | Y46: 101033 | AB46: Full-Time | AC46: 45076 | AD46: 2023 | AL46: AUD | AM46: 255000 | AR46: 29325 | AU46: Yes | AV46: Yes | AW46: 97800.93 | AY46: 255000 | BN46: USD | BO46: Yes | BP46: 40000 | BQ46: 6.34 | CC46: 270000 | CH46: Yes | CI46: 270000 | CL46: 31050 | CO46: Sales 11 Australia Sales | CQ46: 255000 | DC46: No | DK46: 0 | DO46: Team | DP46: Team | ED46: 1989 | EE46: Female | EJ46: 40 | EK46: 100 | EL46: Virtual
B47: 26118CX0 | C47: 101907 | D47: AU | E47: Australia | F47: 2074 | G47: Turramurra | H47: New South Wales | I47: SLS | J47: SA | K47: FS | L47: DN | M47: P5 | N47: SA.FSDN.P5 | O47: Sales | P47: Sales | Q47: Field Sales - Sales Account Management | R47: Direct Sales - New Accounts | S47: Expert (P5) | T47: Sales - Field Sales - Sales Account Management - Direct Sales - New Accounts | U47: TS01 - Software Products/Services | W47: Strategic Account Executive | X47: Strategic Account Executive | Y47: 102110 | AA47: N | AB47: Full-Time | AC47: 45300 | AD47: 2024 | AL47: AUD | AU47: No | AV47: No | AW47: 0 | AY47: 0 | BN47: USD | BO47: No | BP47: 0 | BQ47: 6.34 | CC47: 210000 | CH47: Yes | CI47: 210000 | CL47: 23100 | CO47: Sales 07 Australia Sales | CQ47: 200000 | DC47: Yes | DD47: 24000 | DE47: 6.34 | DF47: 0 | DG47: 9.01 | DK47: 24000 | DP47: Individual | ED47: 1988 | EE47: Male | EJ47: 40 | EK47: 100 | EL47: Virtual
B48: 26118CX0 | C48: 101909 | D48: AU | E48: Australia | F48: 2090 | G48: Cremorne | H48: New South Wales | I48: SLS | J48: SA | K48: FS | L48: DN | M48: P4 | N48: SA.FSDN.P4 | O48: Sales | P48: Sales | Q48: Field Sales - Sales Account Management | R48: Direct Sales - New Accounts | S48: Advanced (P4) | T48: Sales - Field Sales - Sales Account Management - Direct Sales - New Accounts | U48: TS01 - Software Products/Services | W48: Senior Enterprise Account Executive | X48: Senior Enterprise Account Executive | Y48: 102110 | AA48: N | AB48: Full-Time | AC48: 45300 | AD48: 2024 | AL48: AUD | AU48: No | AV48: No | AW48: 0 | AY48: 0 | BN48: USD | BO48: No | BP48: 0 | BQ48: 6.34 | CC48: 185000 | CH48: Yes | CI48: 185000 | CL48: 20350 | CO48: Sales 06 Australia Sales | CQ48: 180000 | DC48: Yes | DD48: 18000 | DE48: 6.34 | DF48: 0 | DG48: 9.01 | DK48: 18000 | DP48: Individual | ED48: 1982 | EE48: Male | EJ48: 40 | EK48: 100 | EL48: Virtual
B49: 26118CX0 | C49: 101919 | D49: AU | E49: Australia | F49: 2036 | G49: Little Bay | H49: New South Wales | I49: SLS | J49: SA | K49: IS | L49: TL | M49: S2 | N49: SA.ISTL.S2 | O49: Sales | P49: Sales | Q49: Inside Sales / Telemarketing | R49: Lead Development | S49: Intermediate (S2) | T49: Sales - Inside Sales / Telemarketing - Lead Development | U49: TS01 - Software Products/Services | W49: Sales Development Representative | X49: Sales Development Representative | Y49: 101499 | AA49: N | AB49: Full-Time | AC49: 45300 | AD49: 2024 | AL49: AUD | AU49: No | AV49: No | AW49: 0 | AY49: 0 | BN49: USD | BO49: No | BP49: 0 | BQ49: 6.34 | CC49: 79800 | CH49: Yes | CI49: 34200.046 | CL49: 8778 | CO49: ISR 01 Australia 70/30 ISR | CQ49: 77350 | DC49: Yes | DD49: 3800 | DE49: 6.34 | DF49: 0 | DG49: 9.01 | DK49: 3800 | DP49: Individual | ED49: 1993 | EE49: Male | EJ49: 40 | EK49: 100 | EL49: Virtual
B50: 26118CX0 | C50: 101939 | D50: AU | E50: Australia | F50: 3073 | G50: Reservoir | H50: Victoria | I50: SLS | J50: SA | K50: FS | L50: OS | M50: P4 | N50: SA.FSOS.P4 | O50: Sales | P50: Sales | Q50: Field Sales - Sales Account Management | R50: OEM/VAR Sales | S50: Advanced (P4) | T50: Sales - Field Sales - Sales Account Management - OEM/VAR Sales | U50: TS01 - Software Products/Services | W50: Senior Channel Manager, APAC | X50: Senior Regional Channel Manager | Y50: 101426 | AA50: N | AB50: Full-Time | AC50: 45300 | AD50: 2024 | AL50: AUD | AU50: No | AV50: No | AW50: 0 | AY50: 0 | BN50: USD | BO50: No | BP50: 0 | BQ50: 6.34 | CC50: 165000 | CH50: Yes | CI50: 110000.06 | CL50: 18150 | CO50: CPM 06 Australia CPM | CQ50: 177360 | DC50: Yes | DD50: 14000 | DE50: 6.34 | DF50: 0 | DG50: 9.01 | DK50: 14000 | DP50: Team | ED50: 1989 | EE50: Male | EJ50: 40 | EK50: 100 | EL50: Virtual
B51: 26118CX0 | C51: 101994 | D51: AU | E51: Australia | F51: 3147 | G51: Ashburton | H51: Victoria | I51: SLS | J51: SA | K51: AS | L51: RS | M51: M4 | N51: SA.ASRS.M4 | O51: Sales | P51: Sales | Q51: Applications / Systems Engineering | R51: Pre-Sales - Sales Plan | S51: Senior Manager / Associate Director (M4) | T51: Sales - Applications / Systems Engineering - Pre-Sales - Sales Plan | U51: TS01 - Software Products/Services | W51: Senior Manager, Solutions Engineering | X51: Senior Manager, Solutions Engineering | Y51: 101624 | AA51: N | AB51: Full-Time | AC51: 45356 | AD51: 2024 | AL51: AUD | AU51: No | AV51: No | AW51: 0 | AY51: 0 | BN51: USD | BO51: No | BP51: 0 | BQ51: 6.34 | CC51: 237930 | CH51: Yes | CI51: 101969.9 | CL51: 26172.3 | CO51: SE 09 Australia SE | CQ51: 230719 | DC51: Yes | DD51: 40000 | DE51: 6.34 | DF51: 0 | DG51: 9.01 | DK51: 40000 | DP51: Team | ED51: 1974 | EE51: Male | EJ51: 40 | EK51: 100 | EL51: Virtual
B52: 26118CX0 | C52: 102010 | D52: AU | E52: Australia | F52: 2200 | G52: Bankstown | H52: New South Wales | I52: SLS | J52: SA | K52: AS | L52: RS | M52: P4 | N52: SA.ASRS.P4 | O52: Sales | P52: Sales | Q52: Applications / Systems Engineering | R52: Pre-Sales - Sales Plan | S52: Advanced (P4) | T52: Sales - Applications / Systems Engineering - Pre-Sales - Sales Plan | U52: TS01 - Software Products/Services | W52: Senior Solutions Engineer | X52: Senior Solutions Engineer | Y52: 101994 | AA52: N | AB52: Full-Time | AC52: 45356 | AD52: 2024 | AL52: AUD | AU52: No | AV52: No | AW52: 0 | AY52: 0 | BN52: USD | BO52: No | BP52: 0 | BQ52: 6.34 | CC52: 185500.01 | CH52: Yes | CI52: 79499.925 | CL52: 20405 | CO52: SE 04 Australia SE | CQ52: 174217 | DC52: Yes | DD52: 18000 | DE52: 6.34 | DF52: 0 | DG52: 9.01 | DK52: 18000 | DP52: Individual | ED52: 1990 | EE52: Male | EJ52: 40 | EK52: 100 | EL52: Virtual
B53: 26118CX0 | C53: 102232 | D53: AU | E53: Australia | F53: 2037 | G53: Forest Lodge | H53: New South Wales | I53: INF | J53: MK | K53: GL | L53: MF | M53: P3 | N53: MK.GLMF.P3 | O53: Infrastructure | P53: Marketing | Q53: General | R53: Multi-Focus | S53: Career (P3) | T53: Marketing - General - Multi-Focus | U53: TS01 - Software Products/Services | W53: Regional Marketing Manager | X53: Regional Marketing Manager | Y53: 100452 | AA53: N | AB53: Full-Time | AC53: 45538 | AD53: 2024 | AL53: AUD | AU53: No | AV53: No | AW53: 0 | AY53: 0 | BN53: USD | BO53: No | BP53: 0 | BQ53: 6.34 | CC53: 140000 | CH53: Yes | CI53: 14000 | CL53: 16100 | CO53: 06 Australia Base | CQ53: 138298 | DC53: Yes | DD53: 0 | DE53: 6.34 | DF53: 10500 | DG53: 9.01 | DK53: 10500 | ED53: 1982 | EE53: Male | EJ53: 40 | EK53: 100 | EL53: Virtual
B54: 26118CX0 | C54: 102299 | D54: AU | E54: Australia | F54: 2099 | G54: Dee Why | H54: New South Wales | I54: SLS | J54: SA | K54: FS | L54: DN | M54: P3 | N54: SA.FSDN.P3 | O54: Sales | P54: Sales | Q54: Field Sales - Sales Account Management | R54: Direct Sales - New Accounts | S54: Career (P3) | T54: Sales - Field Sales - Sales Account Management - Direct Sales - New Accounts | U54: TS01 - Software Products/Services | W54: Senior Commercial Account Executive | X54: Senior Commercial Account Executive | Y54: 102110 | AA54: N | AB54: Full-Time | AC54: 45566 | AD54: 2024 | AL54: AUD | AU54: No | AV54: No | AW54: 0 | AY54: 0 | BN54: USD | BO54: No | BP54: 0 | BQ54: 6.34 | CC54: 130000 | CH54: Yes | CI54: 130000 | CL54: 14950 | CO54: Sales 04 Australia Sales | CQ54: 127500 | DC54: Yes | DD54: 0 | DE54: 6.34 | DF54: 4570 | DG54: 9.01 | DK54: 4570 | DP54: Individual | ED54: 1986 | EE54: Male | EJ54: 40 | EK54: 100 | EL54: Virtual
B55: 26118CX0 | C55: 100205 | D55: BE | E55: Belgium | F55: 3511 | G55: Stokrooie | H55: Limburg | I55: TEC | J55: EN | K55: SO | L55: DE | M55: P5 | N55: EN.SODE.P5 | O55: Technology Solutions | P55: Engineering | Q55: Software | R55: Software Development Engineering | S55: Expert (P5) | T55: Engineering - Software - Software Development Engineering | U55: TS01 - Software Products/Services | W55: Principal Software Engineer | X55: Principal Software Engineer I | Y55: 101241 | AB55: Full-Time | AC55: 43773 | AD55: 2023 | AL55: EUR | AM55: 148920 | AU55: No | AV55: No | AW55: 0 | AY55: 0 | BN55: USD | BO55: Yes | BP55: 26810 | BQ55: 6.34 | CC55: 153759.9 | CH55: No | CI55: 0 | CO55: 11 Belgium Base | CQ55: 151043 | DC55: No | DK55: 0 | ED55: 1989 | EE55: Male | EJ55: 40 | EK55: 100 | EL55: Virtual
B56: 26118CX0 | C56: 100474 | D56: BE | E56: Belgium | F56: 3930 | G56: Hamont-Achel | H56: Limburg | I56: TEC | J56: EN | K56: SO | L56: DE | M56: P3 | N56: EN.SODE.P3 | O56: Technology Solutions | P56: Engineering | Q56: Software | R56: Software Development Engineering | S56: Career (P3) | T56: Engineering - Software - Software Development Engineering | U56: TS01 - Software Products/Services | W56: Senior Software Engineer | X56: Senior Software Engineer | Y56: 100790 | AB56: Full-Time | AC56: 44312 | AD56: 2023 | AL56: EUR | AM56: 117537.42 | AU56: No | AV56: No | AW56: 0 | AY56: 0 | BN56: USD | BO56: Yes | BP56: 2485 | BQ56: 6.34 | CC56: 121651.23 | CH56: No | CI56: 0 | CO56: 09 Belgium Base | CQ56: 117499 | DC56: No | DK56: 0 | ED56: 1994 | EE56: Male | EJ56: 40 | EK56: 100 | EL56: Virtual
B57: 26118CX0 | C57: 100511 | D57: BE | E57: Belgium | F57: 3460 | G57: Bekkevoort | H57: Flemish Brabant | I57: TEC | J57: EN | K57: SO | L57: DE | M57: P5 | N57: EN.SODE.P5 | O57: Technology Solutions | P57: Engineering | Q57: Software | R57: Software Development Engineering | S57: Expert (P5) | T57: Engineering - Software - Software Development Engineering | U57: TS01 - Software Products/Services | W57: Principal Software Engineer | X57: Principal Software Engineer I | Y57: 100969 | AA57: P | AB57: Full-Time | AC57: 44348 | AD57: 2024 | AL57: EUR | AM57: 168550.2 | AU57: No | AV57: No | AW57: 0 | AY57: 0 | BN57: USD | BO57: Yes | BP57: 7095 | BQ57: 6.34 | CC57: 173606.71 | CH57: No | CI57: 0 | CO57: 11 Belgium Base | CQ57: 151043 | DC57: No | DK57: 0 | ED57: 1988 | EE57: Male | EJ57: 40 | EK57: 100 | EL57: Virtual
B58: 26118CX0 | C58: 100694 | D58: BE | E58: Belgium | F58: 9000 | G58: Gent | H58: East Flanders | I58: TEC | J58: EN | K58: SO | L58: DE | M58: P4 | N58: EN.SODE.P4 | O58: Technology Solutions | P58: Engineering | Q58: Software | R58: Software Development Engineering | S58: Advanced (P4) | T58: Engineering - Software - Software Development Engineering | U58: TS01 - Software Products/Services | W58: Staff Software Engineer | X58: Staff Software Engineer | Y58: 102065 | AB58: Full-Time | AC58: 44501 | AD58: 2022 | AL58: EUR | AM58: 158503.07 | AU58: No | AV58: No | AW58: 0 | AY58: 0 | BN58: USD | BO58: Yes | BP58: 3311 | BQ58: 6.34 | CC58: 163258.16 | CH58: No | CI58: 0 | CO58: 10 Belgium Base | CQ58: 133128 | DC58: No | DK58: 0 | ED58: 1992 | EE58: Male | EJ58: 40 | EK58: 100 | EL58: Virtual
B59: 26118CX0 | C59: 101433 | D59: BE | E59: Belgium | F59: 4252 | G59: Geer | H59: Liege | I59: TEC | J59: EN | K59: SO | L59: PS | M59: P5 | N59: EN.SOPS.P5 | O59: Technology Solutions | P59: Engineering | Q59: Software | R59: Product / Application Security Engineering | S59: Expert (P5) | T59: Engineering - Software - Product / Application Security Engineering | U59: TS01 - Software Products/Services | W59: Staff Security Engineer | X59: Staff Security Engineer | Y59: 101739 | AB59: Full-Time | AC59: 44985 | AD59: 2023 | AL59: EUR | AM59: 134875 | AU59: No | AV59: No | AW59: 0 | AY59: 0 | BM59: 5395 | BN59: USD | BO59: Yes | BP59: 25000 | BQ59: 6.34 | CC59: 140270 | CH59: No | CI59: 0 | CO59: 11 Belgium Base | CQ59: 151043 | DB59: 5610.8 | DC59: No | DK59: 0 | ED59: 1991 | EE59: Male | EJ59: 40 | EK59: 100 | EL59: Virtual
B60: 26118CX0 | C60: 100592 | D60: BG | E60: Bulgaria | F60: 2240 | G60: Godech 2240 | H60: Sofia | I60: TEC | J60: EN | K60: SO | L60: DE | M60: P5 | N60: EN.SODE.P5 | O60: Technology Solutions | P60: Engineering | Q60: Software | R60: Software Development Engineering | S60: Expert (P5) | T60: Engineering - Software - Software Development Engineering | U60: TS01 - Software Products/Services | W60: Principal Software Engineer | X60: Principal Software Engineer I | Y60: 101795 | AB60: Full-Time | AC60: 44348 | AD60: 2022 | AL60: BGN | AM60: 219269.98 | AU60: No | AV60: No | AW60: 0 | AY60: 0 | BN60: USD | BO60: Yes | BP60: 8281 | BQ60: 6.34 | CC60: 219269.98 | CH60: No | CI60: 0 | CO60: 11 Bulgaria Base - EUR | CQ60: 119296 | DC60: No | DK60: 0 | ED60: 1988 | EE60: Male | EJ60: 40 | EK60: 100 | EL60: Virtual
B61: 26118CX0 | C61: 100603 | D61: BG | E61: Bulgaria | F61: 1202 | G61: Sofia | H61: Sofia | I61: TEC | J61: EN | K61: SO | L61: DE | M61: P4 | N61: EN.SODE.P4 | O61: Technology Solutions | P61: Engineering | Q61: Software | R61: Software Development Engineering | S61: Advanced (P4) | T61: Engineering - Software - Software Development Engineering | U61: TS01 - Software Products/Services | W61: Staff Software Engineer | X61: Staff Software Engineer | Y61: 100919 | AB61: Full-Time | AC61: 44348 | AD61: 2022 | AL61: BGN | AM61: 204029.55 | AU61: No | AV61: No | AW61: 0 | AY61: 0 | BN61: USD | BO61: Yes | BP61: 3311 | BQ61: 6.34 | CC61: 210660.51 | CH61: No | CI61: 0 | CO61: 10 Bulgaria Base - EUR | CQ61: 105197 | DC61: No | DK61: 0 | ED61: 1990 | EE61: Male | EJ61: 40 | EK61: 100 | EL61: Virtual
B62: 26118CX0 | C62: 101178 | D62: BG | E62: Bulgaria | F62: 1404 | G62: Sofia | H62: Sofia | I62: TEC | J62: EN | K62: PG | L62: PG | M62: P5 | N62: EN.PGPG.P5 | O62: Technology Solutions | P62: Engineering | Q62: Product Management | R62: Technology Product Management | S62: Expert (P5) | T62: Engineering - Product Management - Technology Product Management | U62: TS01 - Software Products/Services | W62: Staff Product Manager | X62: Staff Product Manager | Y62: 100278 | AA62: P | AB62: Full-Time | AC62: 44788 | AD62: 2024 | AL62: BGN | AM62: 248267.44 | AU62: No | AV62: No | AW62: 0 | AY62: 0 | BN62: USD | BO62: Yes | BP62: 4260 | BQ62: 6.34 | CC62: 255715.46 | CH62: No | CI62: 0 | CO62: 11 Bulgaria Base | CQ62: 233398 | DC62: No | DK62: 0 | ED62: 1988 | EE62: Male | EJ62: 40 | EK62: 100 | EL62: Virtual
B63: 26118CX0 | C63: 101371 | D63: BG | E63: Bulgaria | F63: 1309 | G63: Sofia | H63: Sofia | I63: TEC | J63: EN | K63: UU | L63: UD | M63: P4 | N63: EN.UUUD.P4 | O63: Technology Solutions | P63: Engineering | Q63: User Interface/User Experience (UI/UX) | R63: UI / UX Design | S63: Advanced (P4) | T63: Engineering - User Interface/User Experience (UI/UX) - UI / UX Design | U63: TS01 - Software Products/Services | W63: Staff Product Designer | X63: Staff Product Designer | Y63: 100715 | AB63: Full-Time | AC63: 44894 | AD63: 2022 | AL63: BGN | AM63: 365023.3 | AU63: No | AV63: No | AW63: 0 | AY63: 0 | BM63: 7462.4 | BN63: USD | BO63: Yes | BP63: 0 | BQ63: 6.34 | CC63: 192171.38 | CH63: No | CI63: 0 | CO63: 09 Bulgaria Base - EUR | CQ63: 92997 | DB63: 3928.68 | DC63: No | DK63: 0 | ED63: 1987 | EE63: Male | EJ63: 40 | EK63: 100 | EL63: Virtual
B64: 26118CX0 | C64: 100366 | D64: BR | E64: Brazil | F64: 22776070 | G64: Rio de Janeiro | H64: Rio de Janeiro | I64: TEC | J64: EN | K64: SO | L64: DE | M64: P4 | N64: EN.SODE.P4 | O64: Technology Solutions | P64: Engineering | Q64: Software | R64: Software Development Engineering | S64: Advanced (P4) | T64: Engineering - Software - Software Development Engineering | U64: TS01 - Software Products/Services | W64: Staff Software Engineer | X64: Staff Software Engineer | Y64: 100460 | AA64: P | AB64: Full-Time | AC64: 44172 | AD64: 2024 | AL64: BRL | AM64: 624687.66 | AU64: No | AV64: No | AW64: 0 | AY64: 0 | BN64: USD | BO64: Yes | BP64: 2485 | BQ64: 6.34 | CC64: 690404.8 | CH64: No | CI64: 0 | CO64: 10 Brazil Base - USD | CQ64: 124233 | DC64: No | DK64: 0 | ED64: 1992 | EE64: Male | EJ64: 40 | EK64: 100 | EL64: Virtual
B65: 26118CX0 | C65: 100485 | D65: BR | E65: Brazil | F65: 88063-710 | G65: Florianopolis | H65: Santa Catarina | I65: TEC | J65: EN | K65: SO | L65: DE | M65: P3 | N65: EN.SODE.P3 | O65: Technology Solutions | P65: Engineering | Q65: Software | R65: Software Development Engineering | S65: Career (P3) | T65: Engineering - Software - Software Development Engineering | U65: TS01 - Software Products/Services | W65: Senior Cloud Integrations Engineer | X65: Senior Cloud Integrations Engineer | Y65: 102078 | AB65: Full-Time | AC65: 44298 | AD65: 2023 | AL65: BRL | AM65: 501729.34 | AU65: No | AV65: No | AW65: 0 | AY65: 0 | BN65: USD | BO65: Yes | BP65: 6485 | BQ65: 6.34 | CC65: 518035.53 | CH65: No | CI65: 0 | CO65: 09 Brazil Base - USD | CQ65: 109624 | DC65: No | DK65: 0 | ED65: 1991 | EE65: Male | EJ65: 40 | EK65: 100 | EL65: Virtual
B66: 26118CX0 | C66: 100582 | D66: BR | E66: Brazil | F66: 83320-340 | G66: Pinhais | H66: Paraná | I66: TEC | J66: EN | K66: SO | L66: DE | M66: P4 | N66: EN.SODE.P4 | O66: Technology Solutions | P66: Engineering | Q66: Software | R66: Software Development Engineering | S66: Advanced (P4) | T66: Engineering - Software - Software Development Engineering | U66: TS01 - Software Products/Services | W66: Staff Software Engineer | X66: Staff Software Engineer | Y66: 100346 | AA66: P | AB66: Full-Time | AC66: 44410 | AD66: 2024 | AL66: BRL | AM66: 536231.18 | AU66: No | AV66: No | AW66: 0 | AY66: 0 | BN66: USD | BO66: Yes | BP66: 2485 | BQ66: 6.34 | CC66: 589854.32 | CH66: No | CI66: 0 | CO66: 10 Brazil Base - USD | CQ66: 124233 | DC66: No | DK66: 0 | ED66: 1985 | EE66: Male | EJ66: 40 | EK66: 100 | EL66: Virtual
B67: 26118CX0 | C67: 100583 | D67: BR | E67: Brazil | F67: 38405-305 | G67: Uberlândia | H67: Minas Gerais | I67: TEC | J67: EN | K67: SO | L67: DE | M67: P4 | N67: EN.SODE.P4 | O67: Technology Solutions | P67: Engineering | Q67: Software | R67: Software Development Engineering | S67: Advanced (P4) | T67: Engineering - Software - Software Development Engineering | U67: TS01 - Software Products/Services | W67: Staff Software Engineer | X67: Staff Software Engineer | Y67: 101559 | AB67: Full-Time | AC67: 44382 | AD67: 2022 | AL67: BRL | AM67: 560907.7 | AU67: No | AV67: No | AW67: 0 | AY67: 0 | BN67: USD | BO67: Yes | BP67: 3311 | BQ67: 6.34 | CC67: 586148.53 | CH67: No | CI67: 0 | CO67: 10 Brazil Base - USD | CQ67: 124233 | DC67: No | DK67: 0 | ED67: 1997 | EE67: Male | EJ67: 40 | EK67: 100 | EL67: Virtual
B68: 26118CX0 | C68: 100704 | D68: BR | E68: Brazil | F68: 05008-001 | G68: São Paulo | H68: São Paulo | I68: TEC | J68: EN | K68: SO | L68: DE | M68: P3 | N68: EN.SODE.P3 | O68: Technology Solutions | P68: Engineering | Q68: Software | R68: Software Development Engineering | S68: Career (P3) | T68: Engineering - Software - Software Development Engineering | U68: TS01 - Software Products/Services | W68: Senior Software Engineer | X68: Senior Software Engineer | Y68: 101982 | AB68: Full-Time | AC68: 44461 | AD68: 2023 | AL68: BRL | AM68: 455572.16 | AU68: No | AV68: No | AW68: 0 | AY68: 0 | BN68: USD | BO68: Yes | BP68: 6485 | BQ68: 6.34 | CC68: 485184.36 | CH68: No | CI68: 0 | CO68: 09 Brazil Base - USD | CQ68: 109624 | DC68: No | DK68: 0 | ED68: 1995 | EE68: Male | EJ68: 40 | EK68: 100 | EL68: Virtual
B69: 26118CX0 | C69: 100734 | D69: BR | E69: Brazil | F69: 71938540 | G69: Águas Claras | H69: Distrito Federal | I69: TEC | J69: EN | K69: SO | L69: DE | M69: P2 | N69: EN.SODE.P2 | O69: Technology Solutions | P69: Engineering | Q69: Software | R69: Software Development Engineering | S69: Developing (P2) | T69: Engineering - Software - Software Development Engineering | U69: TS01 - Software Products/Services | W69: Software Engineer | X69: Software Engineer II | Y69: 101290 | AB69: Full-Time | AC69: 44473 | AD69: 2022 | AL69: BRL | AM69: 405943.23 | AU69: No | AV69: No | AW69: 0 | AY69: 0 | BN69: USD | BO69: Yes | BP69: 2838 | BQ69: 6.34 | CC69: 428270.11 | CH69: No | CI69: 0 | CO69: 07 Brazil Base - USD | CQ69: 86186 | DC69: No | DK69: 0 | ED69: 1994 | EE69: Male | EJ69: 40 | EK69: 100 | EL69: Virtual
B70: 26118CX0 | C70: 100882 | D70: BR | E70: Brazil | F70: 88062271 | G70: Florianópolis | H70: Santa Catarina | I70: TEC | J70: EN | K70: SO | L70: DE | M70: P3 | N70: EN.SODE.P3 | O70: Technology Solutions | P70: Engineering | Q70: Software | R70: Software Development Engineering | S70: Career (P3) | T70: Engineering - Software - Software Development Engineering | U70: TS01 - Software Products/Services | W70: Senior Software Engineer | X70: Senior Software Engineer | Y70: 100969 | AB70: Full-Time | AC70: 44606 | AD70: 2022 | AL70: BRL | AM70: 544002.65 | AU70: No | AV70: No | AW70: 0 | AY70: 0 | BN70: USD | BO70: Yes | BP70: 4260 | BQ70: 6.34 | CC70: 573922.79 | CH70: No | CI70: 0 | CO70: 09 Brazil Base - USD | CQ70: 109624 | DC70: No | DK70: 0 | ED70: 1996 | EE70: Male | EJ70: 40 | EK70: 100 | EL70: Virtual
B71: 26118CX0 | C71: 101130 | D71: BR | E71: Brazil | F71: 33233-168 | G71: Lagoa Santa | H71: Minas Gerais | I71: TEC | J71: EN | K71: SO | L71: DE | M71: P3 | N71: EN.SODE.P3 | O71: Technology Solutions | P71: Engineering | Q71: Software | R71: Software Development Engineering | S71: Career (P3) | T71: Engineering - Software - Software Development Engineering | U71: TS01 - Software Products/Services | W71: Senior Software Engineer | X71: Senior Software Engineer | Y71: 100969 | AB71: Full-Time | AC71: 44746 | AD71: 2022 | AL71: BRL | AM71: 521543.63 | AU71: No | AV71: No | AW71: 0 | AY71: 0 | BN71: USD | BO71: Yes | BP71: 2485 | BQ71: 6.34 | CC71: 538493.8 | CH71: No | CI71: 0 | CO71: 09 Brazil Base - USD | CQ71: 109624 | DC71: No | DK71: 0 | ED71: 1992 | EE71: Male | EJ71: 40 | EK71: 100 | EL71: Virtual
B72: 26118CX0 | C72: 101248 | D72: BR | E72: Brazil | F72: 60130000 | G72: Fortaleza | H72: Ceará | I72: TEC | J72: EN | K72: UU | L72: UD | M72: P2 | N72: EN.UUUD.P2 | O72: Technology Solutions | P72: Engineering | Q72: User Interface/User Experience (UI/UX) | R72: UI / UX Design | S72: Developing (P2) | T72: Engineering - User Interface/User Experience (UI/UX) - UI / UX Design | U72: TS01 - Software Products/Services | W72: Product Designer | X72: Product Designer II | Y72: 100263 | AB72: Full-Time | AC72: 44837 | AD72: 2022 | AL72: BRL | AM72: 360179.91 | AU72: No | AV72: No | AW72: 0 | AY72: 0 | BN72: USD | BO72: Yes | BP72: 1656 | BQ72: 6.34 | CC72: 379989.81 | CH72: No | CI72: 0 | CO72: 06 Brazil Base - USD | CQ72: 75675 | DC72: No | DK72: 0 | ED72: 1988 | EE72: Male | EJ72: 40 | EK72: 100 | EL72: Virtual
B73: 26118CX0 | C73: 101403 | D73: BR | E73: Brazil | F73: 88200000 | G73: Tijucas | H73: Santa Catarina | I73: TEC | J73: EN | K73: SO | L73: DE | M73: P3 | N73: EN.SODE.P3 | O73: Technology Solutions | P73: Engineering | Q73: Software | R73: Software Development Engineering | S73: Career (P3) | T73: Engineering - Software - Software Development Engineering | U73: TS01 - Software Products/Services | W73: Senior Software Engineer | X73: Senior Software Engineer | Y73: 101550 | AA73: P | AB73: Full-Time | AC73: 44935 | AD73: 2024 | AL73: BRL | AM73: 427655.17 | AU73: No | AV73: No | AW73: 0 | AY73: 0 | BM73: 3422.95 | BN73: USD | BO73: Yes | BP73: 10000 | BQ73: 6.34 | CC73: 478973.81 | CH73: No | CI73: 0 | CO73: 09 Brazil Base - USD | CQ73: 109624 | DB73: 3833.71 | DC73: No | DK73: 0 | ED73: 1999 | EE73: Male | EJ73: 40 | EK73: 100 | EL73: Virtual
B74: 26118CX0 | C74: 101481 | D74: BR | E74: Brazil | F74: 71009070 | G74: Brasilia | H74: Distrito Federal | I74: SLS | J74: SA | K74: FS | L74: DS | M74: M5 | N74: SA.FSDS.M5 | O74: Sales | P74: Sales | Q74: Field Sales - Sales Account Management | R74: Direct Sales | S74: Director (M5) | T74: Sales - Field Sales - Sales Account Management - Direct Sales | U74: TS01 - Software Products/Services | W74: Regional Sales Director, LATAM | X74: Regional Sales Director II, Enterprise | Y74: 102167 | AB74: Full-Time | AC74: 44985 | AD74: 2023 | AL74: BRL | AM74: 822943.03 | AU74: Yes | AV74: Yes | AW74: 460011.45 | AY74: 822943.03 | BN74: USD | BO74: Yes | BP74: 35000 | BQ74: 6.34 | CC74: 822943.03 | CH74: Yes | CI74: 822943.03 | CO74: Sales 11 Brazil Sales | CQ74: 802500 | DC74: No | DK74: 0 | DO74: Team | DP74: Team | ED74: 1979 | EE74: Male | EJ74: 40 | EK74: 100 | EL74: Virtual
B75: 26118CX0 | C75: 102019 | D75: BR | E75: Brazil | F75: 05707400 | G75: Sao Paulo | H75: São Paulo | I75: SLS | J75: SA | K75: FS | L75: DN | M75: P3 | N75: SA.FSDN.P3 | O75: Sales | P75: Sales | Q75: Field Sales - Sales Account Management | R75: Direct Sales - New Accounts | S75: Career (P3) | T75: Sales - Field Sales - Sales Account Management - Direct Sales - New Accounts | U75: TS01 - Software Products/Services | W75: Senior Commercial Account Executive | X75: Senior Commercial Account Executive | Y75: 101481 | AA75: N | AB75: Full-Time | AC75: 45384 | AD75: 2024 | AL75: BRL | AU75: No | AV75: No | AW75: 0 | AY75: 0 | BN75: USD | BO75: No | BP75: 0 | BQ75: 6.34 | CC75: 420000 | CH75: Yes | CI75: 420000 | CO75: Sales 04 Brazil Sales | CQ75: 340000 | DC75: Yes | DD75: 0 | DE75: 6.34 | DF75: 7000 | DG75: 9.01 | DK75: 7000 | DP75: Individual | ED75: 1989 | EE75: Female | EJ75: 40 | EK75: 100 | EL75: Virtual
B76: 26118CX0 | C76: 102044 | D76: BR | E76: Brazil | F76: 06401-147 | G76: Barueri | H76: São Paulo | I76: SLS | J76: SA | K76: IS | L76: TL | M76: S2 | N76: SA.ISTL.S2 | O76: Sales | P76: Sales | Q76: Inside Sales / Telemarketing | R76: Lead Development | S76: Intermediate (S2) | T76: Sales - Inside Sales / Telemarketing - Lead Development | U76: TS01 - Software Products/Services | W76: Sales Development Representative | X76: Sales Development Representative | Y76: 100397 | AA76: N | AB76: Full-Time | AC76: 45419 | AD76: 2024 | AL76: BRL | AU76: No | AV76: No | AW76: 0 | AY76: 0 | BN76: USD | BO76: No | BP76: 0 | BQ76: 6.34 | CC76: 137200 | CH76: Yes | CI76: 58800.078 | CO76: ISR 01 Brazil 70/30 ISR | CQ76: 143500 | DC76: Yes | DD76: 3800 | DE76: 6.34 | DF76: 2660 | DG76: 9.01 | DK76: 6460 | DP76: Individual | ED76: 1989 | EE76: Male | EJ76: 40 | EK76: 100 | EL76: Virtual
B77: 26118CX0 | C77: 102061 | D77: BR | E77: Brazil | F77: 09090-010 | G77: Santo Andre | H77: São Paulo | I77: SLS | J77: SA | K77: IS | L77: TL | M77: S2 | N77: SA.ISTL.S2 | O77: Sales | P77: Sales | Q77: Inside Sales / Telemarketing | R77: Lead Development | S77: Intermediate (S2) | T77: Sales - Inside Sales / Telemarketing - Lead Development | U77: TS01 - Software Products/Services | W77: Sales Development Representative | X77: Sales Development Representative | Y77: 100397 | AA77: N | AB77: Full-Time | AC77: 45419 | AD77: 2024 | AL77: BRL | AU77: No | AV77: No | AW77: 0 | AY77: 0 | BN77: USD | BO77: No | BP77: 0 | BQ77: 6.34 | CC77: 137200 | CH77: Yes | CI77: 58800.078 | CO77: ISR 01 Brazil 70/30 ISR | CQ77: 143500 | DC77: Yes | DD77: 3800 | DE77: 6.34 | DF77: 0 | DG77: 9.01 | DK77: 3800 | DP77: Individual | ED77: 1994 | EE77: Male | EJ77: 40 | EK77: 100 | EL77: Virtual
B78: 26118CX0 | C78: 102155 | D78: BR | E78: Brazil | F78: 88034101 | G78: Florianópolis | H78: Santa Catarina | I78: TEC | J78: EN | K78: SO | L78: DE | M78: P2 | N78: EN.SODE.P2 | O78: Technology Solutions | P78: Engineering | Q78: Software | R78: Software Development Engineering | S78: Developing (P2) | T78: Engineering - Software - Software Development Engineering | U78: TS01 - Software Products/Services | W78: Software Engineer | X78: Software Engineer II | Y78: 100387 | AA78: N | AB78: Full-Time | AC78: 45510 | AD78: 2024 | AL78: BRL | AU78: No | AV78: No | AW78: 0 | AY78: 0 | BN78: USD | BO78: No | BP78: 0 | BQ78: 6.34 | CC78: 422300 | CH78: No | CI78: 0 | CO78: 07 Brazil Base | CQ78: 434969 | DC78: Yes | DD78: 0 | DE78: 6.34 | DF78: 12443 | DG78: 9.01 | DK78: 12443 | ED78: 1992 | EE78: Male | EJ78: 40 | EK78: 100 | EL78: Virtual
B79: 26118CX0 | C79: 102314 | D79: BR | E79: Brazil | F79: 05442080 | G79: Sao Paulo | H79: São Paulo | I79: SLS | J79: SA | K79: FS | L79: OS | M79: P5 | N79: SA.FSOS.P5 | O79: Sales | P79: Sales | Q79: Field Sales - Sales Account Management | R79: OEM/VAR Sales | S79: Expert (P5) | T79: Sales - Field Sales - Sales Account Management - OEM/VAR Sales | U79: TS01 - Software Products/Services | W79: Strategic Channel Manager | X79: Strategic Channel Manager | Y79: 102215 | AA79: N | AB79: Full-Time | AC79: 45601 | AD79: 2024 | AL79: BRL | AU79: No | AV79: No | AW79: 0 | AY79: 0 | BN79: USD | BO79: No | BP79: 0 | BQ79: 6.34 | CC79: 798000 | CH79: Yes | CI79: 532000.27 | CO79: CPM 07 Brazil CPM | CQ79: 779102 | DC79: Yes | DD79: 0 | DE79: 6.34 | DF79: 11670 | DG79: 9.01 | DK79: 11670 | DP79: Individual | ED79: 1973 | EE79: Male | EJ79: 40 | EK79: 100 | EL79: Virtual
B80: 26118CX0 | C80: 100104 | D80: CA | E80: Canada | F80: T9E 0Z1 | G80: Leduc | H80: Alberta | I80: INF | J80: CB | K80: AD | L80: EA | M80: P4 | N80: CB.ADEA.P4 | O80: Infrastructure | P80: Corporate & Business Services | Q80: Administrative Support | R80: Executive Assistant | S80: Advanced (P4) | T80: Corporate & Business Services - Administrative Support - Executive Assistant | U80: TS01 - Software Products/Services | W80: Executive Coordinator | X80: G&A Senior Executive Assistant | Y80: 100202 | Z80: Exempt from Overtime | AB80: Full-Time | AC80: 44865 | AD80: 2022 | AL80: CAD | AM80: 175000 | AU80: No | AV80: No | AW80: 0 | AY80: 0 | BN80: USD | BO80: Yes | BP80: 1656 | BQ80: 6.34 | CC80: 178500 | CH80: No | CI80: 0 | CO80: 07 Canada Base | CQ80: 151160 | DC80: No | DK80: 0 | ED80: 1979 | EE80: Female | EJ80: 40 | EK80: 100 | EL80: Virtual
B81: 26118CX0 | C81: 100128 | D81: CA | E81: Canada | F81: V7L 0H1 | G81: North Vancouver | H81: British Columbia | I81: TEC | J81: EN | K81: SO | L81: DE | M81: P3 | N81: EN.SODE.P3 | O81: Technology Solutions | P81: Engineering | Q81: Software | R81: Software Development Engineering | S81: Career (P3) | T81: Engineering - Software - Software Development Engineering | U81: TS01 - Software Products/Services | W81: Senior Software Engineer | X81: Senior Software Engineer | Y81: 101290 | Z81: Exempt from Overtime | AB81: Full-Time | AC81: 43325 | AD81: 2023 | AL81: CAD | AM81: 180058.42 | AU81: No | AV81: No | AW81: 0 | AY81: 0 | BN81: USD | BO81: Yes | BP81: 6485 | BQ81: 6.34 | CC81: 180058.42 | CH81: No | CI81: 0 | CO81: 09 Canada Base | CQ81: 192162 | DC81: No | DK81: 0 | ED81: 1993 | EE81: Male | EJ81: 40 | EK81: 100 | EL81: Virtual
B82: 26118CX0 | C82: 100177 | D82: CA | E82: Canada | F82: M4P 0B2 | G82: Toronto | H82: Ontario | I82: TEC | J82: EN | K82: SO | L82: DE | M82: P4 | N82: EN.SODE.P4 | O82: Technology Solutions | P82: Engineering | Q82: Software | R82: Software Development Engineering | S82: Advanced (P4) | T82: Engineering - Software - Software Development Engineering | U82: TS01 - Software Products/Services | W82: Staff Software Engineer | X82: Staff Software Engineer | Y82: 101290 | Z82: Exempt from Overtime | AB82: Full-Time | AC82: 43647 | AD82: 2022 | AL82: CAD | AM82: 244400 | AU82: No | AV82: No | AW82: 0 | AY82: 0 | BN82: USD | BO82: Yes | BP82: 7095 | BQ82: 6.34 | CC82: 254176 | CH82: No | CI82: 0 | CO82: 10 Canada Base | CQ82: 217720 | DC82: No | DK82: 0 | ED82: 1994 | EE82: Male | EJ82: 40 | EK82: 100 | EL82: Virtual
B83: 26118CX0 | C83: 100201 | D83: CA | E83: Canada | F83: J9H2A1 | G83: Gatineau | H83: Quebec | I83: SLS | J83: SA | K83: AS | L83: RS | M83: P3 | N83: SA.ASRS.P3 | O83: Sales | P83: Sales | Q83: Applications / Systems Engineering | R83: Pre-Sales - Sales Plan | S83: Career (P3) | T83: Sales - Applications / Systems Engineering - Pre-Sales - Sales Plan | U83: TS01 - Software Products/Services | W83: Solutions Engineer | X83: Solutions Engineer | Y83: 102288 | Z83: Exempt from Overtime | AB83: Full-Time | AC83: 43731 | AD83: 2022 | AL83: CAD | AM83: 125615.42 | AU83: Yes | AV83: Yes | AW83: 41297.49 | AY83: 53838.769 | BN83: USD | BO83: Yes | BP83: 560 | BQ83: 6.34 | CC83: 129383.84 | CH83: Yes | CI83: 55453.914 | CO83: SE 03 Canada SE | CQ83: 146769 | DC83: No | DK83: 0 | DO83: Individual | DP83: Individual | ED83: 1973 | EE83: Female | EJ83: 40 | EK83: 100 | EL83: Virtual
B84: 26118CX0 | C84: 100260 | D84: CA | E84: Canada | F84: V9C 3E5 | G84: Victoria | H84: British Columbia | I84: SLS | J84: SA | K84: AS | L84: SS | M84: P6 | N84: SA.ASSS.P6 | O84: Sales | P84: Sales | Q84: Applications / Systems Engineering | R84: Pre & Post-Sales - Sales Plan | S84: Principal / Consultant (P6) | T84: Sales - Applications / Systems Engineering - Pre & Post-Sales - Sales Plan | U84: TS01 - Software Products/Services | W84: Senior Principal Field Engineer | X84: Senior Principal Field Engineer | Y84: 101112 | Z84: Exempt from Overtime | AB84: Full-Time | AC84: 44487 | AD84: 2023 | AL84: CAD | AM84: 333060.92 | AU84: Yes | AV84: Yes | AW84: 47716.56 | AY84: 83265.23 | BN84: USD | BO84: Yes | BP84: 31358 | BQ84: 6.34 | CC84: 346383.37 | CH84: Yes | CI84: 86595.842 | CO84: 12 Canada Base | CQ84: 280472 | DC84: No | DK84: 0 | DO84: Individual | DP84: Individual | ED84: 1975 | EE84: Male | EJ84: 40 | EK84: 100 | EL84: Virtual
B85: 26118CX0 | C85: 100395 | D85: CA | E85: Canada | F85: K2J 3S8 | G85: Ottawa | H85: Ontario | I85: TEC | J85: EN | K85: SO | L85: DE | M85: P5 | N85: EN.SODE.P5 | O85: Technology Solutions | P85: Engineering | Q85: Software | R85: Software Development Engineering | S85: Expert (P5) | T85: Engineering - Software - Software Development Engineering | U85: TS01 - Software Products/Services | W85: Principal Software Engineer | X85: Principal Software Engineer I | Y85: 100717 | Z85: Exempt from Overtime | AA85: P | AB85: Full-Time | AC85: 44207 | AD85: 2024 | AL85: CAD | AM85: 235954.98 | AU85: No | AV85: No | AW85: 0 | AY85: 0 | BN85: USD | BO85: Yes | BP85: 5676 | BQ85: 6.34 | CC85: 259550.48 | CH85: No | CI85: 0 | CO85: 11 Canada Base | CQ85: 247021 | DC85: No | DK85: 0 | ED85: 1980 | EE85: Male | EJ85: 40 | EK85: 100 | EL85: Virtual
B86: 26118CX0 | C86: 100440 | D86: CA | E86: Canada | F86: P0M1M0 | G86: Coniston | H86: Ontario | I86: TEC | J86: EN | K86: SO | L86: DE | M86: P4 | N86: EN.SODE.P4 | O86: Technology Solutions | P86: Engineering | Q86: Software | R86: Software Development Engineering | S86: Advanced (P4) | T86: Engineering - Software - Software Development Engineering | U86: TS01 - Software Products/Services | W86: Staff Software Engineer | X86: Staff Software Engineer | Y86: 100790 | Z86: Exempt from Overtime | AB86: Full-Time | AC86: 44249 | AD86: 2023 | AL86: CAD | AM86: 202489.46 | AU86: No | AV86: No | AW86: 0 | AY86: 0 | BN86: USD | BO86: Yes | BP86: 11076 | BQ86: 6.34 | CC86: 213626.38 | CH86: No | CI86: 0 | CO86: 10 Canada Base | CQ86: 217720 | DC86: No | DK86: 0 | ED86: 1980 | EE86: Male | EJ86: 40 | EK86: 100 | EL86: Virtual
B87: 26118CX0 | C87: 100454 | D87: CA | E87: Canada | F87: V6H 1J3 | G87: Vancouver | H87: British Columbia | I87: TEC | J87: EN | K87: SO | L87: DE | M87: P4 | N87: EN.SODE.P4 | O87: Technology Solutions | P87: Engineering | Q87: Software | R87: Software Development Engineering | S87: Advanced (P4) | T87: Engineering - Software - Software Development Engineering | U87: TS01 - Software Products/Services | W87: Staff Software Engineer | X87: Staff Software Engineer | Y87: 100189 | Z87: Exempt from Overtime | AB87: Full-Time | AC87: 44270 | AD87: 2023 | AL87: CAD | AM87: 196318 | AU87: No | AV87: No | AW87: 0 | AY87: 0 | BN87: USD | BO87: Yes | BP87: 13210 | BQ87: 6.34 | CC87: 204170.72 | CH87: No | CI87: 0 | CO87: 10 Canada Base | CQ87: 217720 | DC87: No | DK87: 0 | ED87: 1990 | EE87: Male | EJ87: 40 | EK87: 100 | EL87: Virtual
B88: 26118CX0 | C88: 100458 | D88: CA | E88: Canada | F88: T2L 1K3 | G88: Calgary | H88: Alberta | I88: TEC | J88: EN | K88: SO | L88: DE | M88: P4 | N88: EN.SODE.P4 | O88: Technology Solutions | P88: Engineering | Q88: Software | R88: Software Development Engineering | S88: Advanced (P4) | T88: Engineering - Software - Software Development Engineering | U88: TS01 - Software Products/Services | W88: Staff Software Engineer | X88: Staff Software Engineer | Y88: 101559 | Z88: Exempt from Overtime | AB88: Full-Time | AC88: 44256 | AD88: 2021 | AL88: CAD | AM88: 211577.18 | AU88: No | AV88: No | AW88: 0 | AY88: 0 | BN88: USD | BO88: Yes | BP88: 3311 | BQ88: 6.34 | CC88: 218453.44 | CH88: No | CI88: 0 | CO88: 10 Canada Base | CQ88: 217720 | DC88: No | DK88: 0 | ED88: 1980 | EE88: Male | EJ88: 40 | EK88: 100 | EL88: Virtual
B89: 26118CX0 | C89: 100459 | D89: CA | E89: Canada | F89: G0S2C0 | G89: Saint-Antoine-De-Tilly | H89: Quebec | I89: TEC | J89: EN | K89: SO | L89: DE | M89: P4 | N89: EN.SODE.P4 | O89: Technology Solutions | P89: Engineering | Q89: Software | R89: Software Development Engineering | S89: Advanced (P4) | T89: Engineering - Software - Software Development Engineering | U89: TS01 - Software Products/Services | W89: Staff Software Engineer | X89: Staff Software Engineer | Y89: 102096 | Z89: Exempt from Overtime | AA89: P | AB89: Full-Time | AC89: 44270 | AD89: 2024 | AL89: CAD | AM89: 210059.88 | AU89: No | AV89: No | AW89: 0 | AY89: 0 | BN89: USD | BO89: Yes | BP89: 4260 | BQ89: 6.34 | CC89: 216886.83 | CH89: No | CI89: 0 | CO89: 10 Canada Base | CQ89: 217720 | DC89: No | DK89: 0 | ED89: 1993 | EE89: Male | EJ89: 40 | EK89: 100 | EL89: Virtual
B90: 26118CX0 | C90: 100460 | D90: CA | E90: Canada | F90: M5J2Y6 | G90: Toronto | H90: Ontario | I90: TEC | J90: EN | K90: SO | L90: DE | M90: M4 | N90: EN.SODE.M4 | O90: Technology Solutions | P90: Engineering | Q90: Software | R90: Software Development Engineering | S90: Senior Manager / Associate Director (M4) | T90: Engineering - Software - Software Development Engineering | U90: TS01 - Software Products/Services | W90: Senior Manager, Business Applications | X90: Senior Manager, Business Applications | Y90: 100645 | Z90: Exempt from Overtime | AB90: Full-Time | AC90: 44291 | AD90: 2023 | AL90: CAD | AM90: 282555 | AU90: No | AV90: No | AW90: 0 | AY90: 0 | BN90: USD | BO90: Yes | BP90: 3728 | BQ90: 6.34 | CC90: 282555 | CH90: No | CI90: 0 | CO90: 11 Canada Base | CQ90: 247021 | DC90: No | DK90: 0 | ED90: 1987 | EE90: Male | EJ90: 40 | EK90: 100 | EL90: Virtual
B91: 26118CX0 | C91: 100468 | D91: CA | E91: Canada | F91: T9N2J2 | G91: Bonnyville | H91: Alberta | I91: TEC | J91: EN | K91: SO | L91: DE | M91: P4 | N91: EN.SODE.P4 | O91: Technology Solutions | P91: Engineering | Q91: Software | R91: Software Development Engineering | S91: Advanced (P4) | T91: Engineering - Software - Software Development Engineering | U91: TS01 - Software Products/Services | W91: Staff Software Engineer | X91: Staff Software Engineer | Y91: 101559 | Z91: Exempt from Overtime | AB91: Full-Time | AC91: 44284 | AD91: 2022 | AL91: CAD | AM91: 212107.35 | AU91: No | AV91: No | AW91: 0 | AY91: 0 | BN91: USD | BO91: Yes | BP91: 0 | BQ91: 6.34 | CC91: 219000.84 | CH91: No | CI91: 0 | CO91: 10 Canada Base | CQ91: 217720 | DC91: No | DK91: 0 | ED91: 1980 | EE91: Male | EJ91: 40 | EK91: 100 | EL91: Virtual
B92: 26118CX0 | C92: 100545 | D92: CA | E92: Canada | F92: V5K 2B3 | G92: Vancouver | H92: British Columbia | I92: INF | J92: MK | K92: DI | L92: ON | M92: P2 | N92: MK.DION.P2 | O92: Infrastructure | P92: Marketing | Q92: Digital Marketing | R92: Online Marketing | S92: Developing (P2) | T92: Marketing - Digital Marketing - Online Marketing | U92: TS01 - Software Products/Services | W92: Demand Generation Associate | X92: Demand Generation Associate | Y92: 100279 | Z92: Exempt from Overtime | AB92: Full-Time | AC92: 44340 | AD92: 2022 | AL92: CAD | AM92: 111935.25 | AU92: No | AV92: No | AW92: 0 | AY92: 0 | BN92: USD | BO92: Yes | BP92: 560 | BQ92: 6.34 | CC92: 114173.96 | CH92: No | CI92: 0 | CO92: 03 Canada Base | CQ92: 91109 | DC92: No | DK92: 0 | ED92: 1990 | EE92: Male | EJ92: 40 | EK92: 100 | EL92: Virtual
B93: 26118CX0 | C93: 100881 | D93: CA | E93: Canada | F93: R2M 1P2 | G93: Winnipeg | H93: Manitoba | I93: TEC | J93: EN | K93: PG | L93: PG | M93: P5 | N93: EN.PGPG.P5 | O93: Technology Solutions | P93: Engineering | Q93: Product Management | R93: Technology Product Management | S93: Expert (P5) | T93: Engineering - Product Management - Technology Product Management | U93: TS01 - Software Products/Services | W93: GTM Staff Product Manager | X93: GTM Staff Product Manager | Y93: 100403 | Z93: Exempt from Overtime | AB93: Full-Time | AC93: 44593 | AD93: 2023 | AL93: CAD | AM93: 213488.1 | AU93: No | AV93: No | AW93: 0 | AY93: 0 | BN93: USD | BO93: Yes | BP93: 13210 | BQ93: 6.34 | CC93: 227364.83 | CH93: No | CI93: 0 | CO93: 11 Canada Base | CQ93: 247021 | DC93: No | DK93: 0 | ED93: 1974 | EE93: Male | EJ93: 40 | EK93: 100 | EL93: Virtual
B94: 26118CX0 | C94: 100892 | D94: CA | E94: Canada | F94: L9E1R4 | G94: Milton | H94: Ontario | I94: SLS | J94: SA | K94: AS | L94: RS | M94: P6 | N94: SA.ASRS.P6 | O94: Sales | P94: Sales | Q94: Applications / Systems Engineering | R94: Pre-Sales - Sales Plan | S94: Principal / Consultant (P6) | T94: Sales - Applications / Systems Engineering - Pre-Sales - Sales Plan | U94: TS01 - Software Products/Services | W94: Principal Solutions Engineer | X94: Principal Solutions Engineer | Y94: 102226 | Z94: Exempt from Overtime | AB94: Full-Time | AC94: 44613 | AD94: 2022 | AL94: CAD | AM94: 257952.17 | AU94: Yes | AV94: Yes | AW94: 36687.92 | AY94: 110551.08 | BN94: USD | BO94: Yes | BP94: 0 | BQ94: 6.34 | CC94: 257952.17 | CH94: Yes | CI94: 110551.08 | CO94: SE 06 Canada SE | CQ94: 207340 | DC94: No | DK94: 0 | DO94: Individual | DP94: Individual | ED94: 1987 | EE94: Male | EJ94: 40 | EK94: 100 | EL94: Virtual
B95: 26118CX0 | C95: 100900 | D95: CA | E95: Canada | F95: H4E 2A1 | G95: Montreal | H95: Quebec | I95: TEC | J95: EN | K95: SO | L95: DE | M95: P4 | N95: EN.SODE.P4 | O95: Technology Solutions | P95: Engineering | Q95: Software | R95: Software Development Engineering | S95: Advanced (P4) | T95: Engineering - Software - Software Development Engineering | U95: TS01 - Software Products/Services | W95: Staff Software Engineer | X95: Staff Software Engineer | Y95: 101545 | Z95: Exempt from Overtime | AB95: Full-Time | AC95: 44627 | AD95: 2022 | AL95: CAD | AM95: 231132 | AU95: No | AV95: No | AW95: 0 | AY95: 0 | BN95: USD | BO95: Yes | BP95: 3311 | BQ95: 6.34 | CC95: 238065.96 | CH95: No | CI95: 0 | CO95: 10 Canada Base | CQ95: 217720 | DC95: No | DK95: 0 | ED95: 1990 | EE95: Male | EJ95: 40 | EK95: 100 | EL95: Virtual
B96: 26118CX0 | C96: 100908 | D96: CA | E96: Canada | F96: K2T0L6 | G96: Ottawa | H96: Ontario | I96: SLS | J96: SA | K96: FS | L96: DN | M96: P5 | N96: SA.FSDN.P5 | O96: Sales | P96: Sales | Q96: Field Sales - Sales Account Management | R96: Direct Sales - New Accounts | S96: Expert (P5) | T96: Sales - Field Sales - Sales Account Management - Direct Sales - New Accounts | U96: TS01 - Software Products/Services | W96: Strategic Account Executive | X96: Strategic Account Executive | Y96: 101990 | Z96: Exempt from Overtime | AB96: Full-Time | AC96: 44614 | AD96: 2022 | AL96: CAD | AM96: 193500 | AU96: Yes | AV96: Yes | AW96: 126153.32 | AY96: 193500 | BN96: USD | BO96: Yes | BP96: 2280 | BQ96: 6.34 | CC96: 193500 | CH96: Yes | CI96: 193500 | CO96: Sales 07 Canada Sales | CQ96: 175000 | DC96: No | DK96: 0 | DO96: Individual | DP96: Individual | ED96: 1987 | EE96: Male | EJ96: 40 | EK96: 100 | EL96: Virtual
B97: 26118CX0 | C97: 100932 | D97: CA | E97: Canada | F97: V5B 4T4 | G97: Burnaby | H97: British Columbia | I97: TEC | J97: EN | K97: SO | L97: DE | M97: P3 | N97: EN.SODE.P3 | O97: Technology Solutions | P97: Engineering | Q97: Software | R97: Software Development Engineering | S97: Career (P3) | T97: Engineering - Software - Software Development Engineering | U97: TS01 - Software Products/Services | W97: Senior Software Engineer | X97: Senior Software Engineer | Y97: 101141 | Z97: Exempt from Overtime | AB97: Full-Time | AC97: 44613 | AD97: 2023 | AL97: CAD | AM97: 191889 | AU97: No | AV97: No | AW97: 0 | AY97: 0 | BN97: USD | BO97: Yes | BP97: 2485 | BQ97: 6.34 | CC97: 197645.67 | CH97: No | CI97: 0 | CO97: 09 Canada Base | CQ97: 192162 | DC97: No | DK97: 0 | ED97: 1988 | EE97: Male | EJ97: 40 | EK97: 100 | EL97: Virtual
B98: 26118CX0 | C98: 100965 | D98: CA | E98: Canada | F98: J3G 3M1 | G98: Beloeil | H98: Quebec | I98: SLS | J98: SA | K98: AS | L98: RS | M98: P5 | N98: SA.ASRS.P5 | O98: Sales | P98: Sales | Q98: Applications / Systems Engineering | R98: Pre-Sales - Sales Plan | S98: Expert (P5) | T98: Sales - Applications / Systems Engineering - Pre-Sales - Sales Plan | U98: TS01 - Software Products/Services | W98: Staff Solutions Engineer | X98: Staff Solutions Engineer | Y98: 102226 | Z98: Exempt from Overtime | AB98: Full-Time | AC98: 44641 | AD98: 2023 | AL98: CAD | AM98: 253592.46 | AU98: Yes | AV98: Yes | AW98: 34992.07 | AY98: 108682.63 | BN98: USD | BO98: Yes | BP98: 7000 | BQ98: 6.34 | CC98: 253592.46 | CH98: Yes | CI98: 108682.63 | CO98: SE 05 Canada SE | CQ98: 184681 | DC98: No | DK98: 0 | DO98: Individual | DP98: Individual | ED98: 1972 | EE98: Male | EJ98: 40 | EK98: 100 | EL98: Virtual
B99: 26118CX0 | C99: 100973 | D99: CA | E99: Canada | F99: S7J3P2 | G99: Saskatoon | H99: Saskatchewan | I99: TEC | J99: EN | K99: SO | L99: DE | M99: P3 | N99: EN.SODE.P3 | O99: Technology Solutions | P99: Engineering | Q99: Software | R99: Software Development Engineering | S99: Career (P3) | T99: Engineering - Software - Software Development Engineering | U99: TS01 - Software Products/Services | W99: Senior Software Engineer | X99: Senior Software Engineer | Y99: 100346 | Z99: Exempt from Overtime | AB99: Full-Time | AC99: 44655 | AD99: 2023 | AL99: CAD | AM99: 185763 | AU99: No | AV99: No | AW99: 0 | AY99: 0 | BN99: USD | BO99: Yes | BP99: 8753 | BQ99: 6.34 | CC99: 191800.3 | CH99: No | CI99: 0 | CO99: 09 Canada Base | CQ99: 192162 | DC99: No | DK99: 0 | ED99: 1991 | EE99: Male | EJ99: 40 | EK99: 100 | EL99: Virtual
B100: 26118CX0 | C100: 101106 | D100: CA | E100: Canada | F100: M6P 3C6 | G100: Toronto | H100: Ontario | I100: SLS | J100: SA | K100: FS | L100: DN | M100: P3 | N100: SA.FSDN.P3 | O100: Sales | P100: Sales | Q100: Field Sales - Sales Account Management | R100: Direct Sales - New Accounts | S100: Career (P3) | T100: Sales - Field Sales - Sales Account Management - Direct Sales - New Accounts | U100: TS01 - Software Products/Services | W100: Enterprise Account Executive | X100: Enterprise Account Executive | Y100: 101990 | Z100: Exempt from Overtime | AB100: Full-Time | AC100: 44718 | AD100: 2022 | AL100: CAD | AM100: 174672 | AU100: Yes | AV100: No | AW100: 0 | AY100: 174672 | BN100: USD | BO100: Yes | BP100: 560 | BQ100: 6.34 | CC100: 174672 | CH100: Yes | CI100: 174672 | CO100: Sales 05 Canada Sales | CQ100: 145000 | DC100: No | DK100: 0 | DO100: Individual | DP100: Individual | ED100: 1991 | EE100: Female | EJ100: 40 | EK100: 100 | EL100: Virtual
B101: 26118CX0 | C101: 101182 | D101: CA | E101: Canada | F101: K2B 8K5 | G101: Ottawa | H101: Ontario | I101: TEC | J101: EN | K101: SO | L101: DE | M101: P2 | N101: EN.SODE.P2 | O101: Technology Solutions | P101: Engineering | Q101: Software | R101: Software Development Engineering | S101: Developing (P2) | T101: Engineering - Software - Software Development Engineering | U101: TS01 - Software Products/Services | W101: Software Engineer | X101: Software Engineer II | Y101: 100822 | Z101: Exempt from Overtime | AB101: Full-Time | AC101: 44760 | AD101: 2023 | AL101: CAD | AM101: 163200 | AU101: No | AV101: No | AW101: 0 | AY101: 0 | BN101: USD | BO101: Yes | BP101: 1656 | BQ101: 6.34 | CC101: 165648 | CH101: No | CI101: 0 | CO101: 07 Canada Base | CQ101: 151160 | DC101: No | DK101: 0 | ED101: 1990 | EE101: Male | EJ101: 40 | EK101: 100 | EL101: Virtual
...

Sheet Jobs & Descriptions
B1: Radford McLagan Compensation Database (2024)
B2: Job Attributes, Attribute Codes & Definitions
P3: RMCD Valid Level Tracks
B4: Module Name | C4: Module Code | D4: Module Definition | E4: Function Name | F4: Function Code | G4: Function Definition | H4: Area Name | I4: Area Code | J4: Area Definition | K4: Focus Name | L4: Focus Code | M4: Focus Definition | N4: Job Code excl. Level | O4: Full RMCD Job Title | P4: Executive | Q4: Management | R4: Professional | S4: Financial | T4: Life Sciences Research | U4: Support
B5: Executive | C5: EXE | D5: Executive roles that cover activities related to firm-wide, function, or area leadership. Note that some executive roles reside in other modules that are specific to their function (e.g., Sales, Manufacturing, Technology, Life Sciences, Banking, etc.). | E5: Leadership | F5: LE | G5: The Leadership function is responsible for setting and executing the organization's overall strategy across businesses, products, and infrastructure areas. The Leadership function is reserved for the firm's most senior-level positions. | H5: General | I5: GL | J5: The General area is typically reserved for roles that either: (1) are fully described by their function description; or (2) span multiple disciplines, products, or areas of expertise; or (3) executive level positions. | K5: Executive Chairman | L5: XC | M5: Executive Chairman of the firm’s board of directors is responsible for leading the board of directors, facilitating board meetings, annual shareholders meetings, and working closely with senior management and shareholders to ensure long-term financial success for the firm. Incumbent must be an employee of the firm, do not match non-executive Chairs. If incumbent is Chairman and CEO, match to Chief Executive Officer. | N5: LE.GLXC | O5: Leadership - General - Executive Chairman | P5: E6 | Q5: n/a | R5: n/a | S5: n/a | T5: n/a | U5: n/a
B6: Executive | C6: EXE | D6: Executive roles that cover activities related to firm-wide, function, or area leadership. Note that some executive roles reside in other modules that are specific to their function (e.g., Sales, Manufacturing, Technology, Life Sciences, Banking, etc.). | E6: Leadership | F6: LE | G6: The Leadership function is responsible for setting and executing the organization's overall strategy across businesses, products, and infrastructure areas. The Leadership function is reserved for the firm's most senior-level positions. | H6: General | I6: GL | J6: The General area is typically reserved for roles that either: (1) are fully described by their function description; or (2) span multiple disciplines, products, or areas of expertise; or (3) executive level positions. | K6: Chief Executive Officer (CEO) - Corporate | L6: EC | M6: Chief Executive Officer is the top executive in an independent corporation accountable for the entire firm. | N6: LE.GLEC | O6: Leadership - General - Chief Executive Officer (CEO) - Corporate | P6: E6 | Q6: n/a | R6: n/a | S6: n/a | T6: n/a | U6: n/a
B7: Executive | C7: EXE | D7: Executive roles that cover activities related to firm-wide, function, or area leadership. Note that some executive roles reside in other modules that are specific to their function (e.g., Sales, Manufacturing, Technology, Life Sciences, Banking, etc.). | E7: Leadership | F7: LE | G7: The Leadership function is responsible for setting and executing the organization's overall strategy across businesses, products, and infrastructure areas. The Leadership function is reserved for the firm's most senior-level positions. | H7: General | I7: GL | J7: The General area is typically reserved for roles that either: (1) are fully described by their function description; or (2) span multiple disciplines, products, or areas of expertise; or (3) executive level positions. | K7: Chief Operating Officer - Corporate | L7: OC | M7: Chief Operating Officer is the firm’s second highest ranking role with line rather than staff responsibility. Single incumbent position. | N7: LE.GLOC | O7: Leadership - General - Chief Operating Officer - Corporate | P7: E3-5 | Q7: n/a | R7: n/a | S7: n/a | T7: n/a | U7: n/a
B8: Executive | C8: EXE | D8: Executive roles that cover activities related to firm-wide, function, or area leadership. Note that some executive roles reside in other modules that are specific to their function (e.g., Sales, Manufacturing, Technology, Life Sciences, Banking, etc.). | E8: Leadership | F8: LE | G8: The Leadership function is responsible for setting and executing the organization's overall strategy across businesses, products, and infrastructure areas. The Leadership function is reserved for the firm's most senior-level positions. | H8: General | I8: GL | J8: The General area is typically reserved for roles that either: (1) are fully described by their function description; or (2) span multiple disciplines, products, or areas of expertise; or (3) executive level positions. | K8: Chief Operating Officer - Business Unit | L8: CX | M8: Chief Operating Officer is the firm’s second highest ranking role for a Business Unit (i.e., Group, Division, Region, Country) of the firm. Single incumbent position at each Business Unit. | N8: LE.GLCX | O8: Leadership - General - Chief Operating Officer - Business Unit | P8: E1-4 | Q8: n/a | R8: n/a | S8: n/a | T8: n/a | U8: n/a
B9: Executive | C9: EXE | D9: Executive roles that cover activities related to firm-wide, function, or area leadership. Note that some executive roles reside in other modules that are specific to their function (e.g., Sales, Manufacturing, Technology, Life Sciences, Banking, etc.). | E9: Leadership | F9: LE | G9: The Leadership function is responsible for setting and executing the organization's overall strategy across businesses, products, and infrastructure areas. The Leadership function is reserved for the firm's most senior-level positions. | H9: General | I9: GL | J9: The General area is typically reserved for roles that either: (1) are fully described by their function description; or (2) span multiple disciplines, products, or areas of expertise; or (3) executive level positions. | K9: Chief Operating Officer - Country Leadership | L9: CE | M9: The Chief Operating Officer - Country Leadership is responsible for providing direction, coordination, and control for the effective and profitable operation of a country's various businesses. Advises and counsels the Country/Regional Chief Executive Officer on planning the scope and direction of all firm operations, and recommends future plans and objectives. | N9: LE.GLCE | O9: Leadership - General - Chief Operating Officer - Country Leadership | P9: E1-5 | Q9: n/a | R9: n/a | S9: n/a | T9: n/a | U9: n/a
B10: Executive | C10: EXE | D10: Executive roles that cover activities related to firm-wide, function, or area leadership. Note that some executive roles reside in other modules that are specific to their function (e.g., Sales, Manufacturing, Technology, Life Sciences, Banking, etc.). | E10: Leadership | F10: LE | G10: The Leadership function is responsible for setting and executing the organization's overall strategy across businesses, products, and infrastructure areas. The Leadership function is reserved for the firm's most senior-level positions. | H10: General | I10: GL | J10: The General area is typically reserved for roles that either: (1) are fully described by their function description; or (2) span multiple disciplines, products, or areas of expertise; or (3) executive level positions. | K10: Chief Operating Officer - Regional Leadership | L10: RL | M10: The Chief Operating Officer - Regional Leadership is responsible for providing direction, coordination, and control for the effective and profitable operation of a region's various businesses. Advises and counsels the Regional Chief Executive Officer on planning the scope and direction of all firm operations, and recommends future plans and objectives. | N10: LE.GLRL | O10: Leadership - General - Chief Operating Officer - Regional Leadership | P10: E1-5 | Q10: n/a | R10: n/a | S10: n/a | T10: n/a | U10: n/a
B11: Executive | C11: EXE | D11: Executive roles that cover activities related to firm-wide, function, or area leadership. Note that some executive roles reside in other modules that are specific to their function (e.g., Sales, Manufacturing, Technology, Life Sciences, Banking, etc.). | E11: Leadership | F11: LE | G11: The Leadership function is responsible for setting and executing the organization's overall strategy across businesses, products, and infrastructure areas. The Leadership function is reserved for the firm's most senior-level positions. | H11: General | I11: GL | J11: The General area is typically reserved for roles that either: (1) are fully described by their function description; or (2) span multiple disciplines, products, or areas of expertise; or (3) executive level positions. | K11: Leadership - Executive | L11: MF | M11: The Executive Focus attribute is reserved for roles that cannot be matched to a Top or Head role in the function or area. This is typically because the incumbent is at a business unit (e.g., group, division, region, country) and not at the Corporate organization level, or is at Corporate but not in a Head or Top role. The role is multi-incumbent; or oversees part of the function/area rather than the whole function/area. | N11: LE.GLMF | O11: Leadership - General - Leadership - Executive | P11: E1-4 | Q11: n/a | R11: n/a | S11: n/a | T11: n/a | U11: n/a
B12: Executive | C12: EXE | D12: Executive roles that cover activities related to firm-wide, function, or area leadership. Note that some executive roles reside in other modules that are specific to their function (e.g., Sales, Manufacturing, Technology, Life Sciences, Banking, etc.). | E12: Leadership | F12: LE | G12: The Leadership function is responsible for setting and executing the organization's overall strategy across businesses, products, and infrastructure areas. The Leadership function is reserved for the firm's most senior-level positions. | H12: General | I12: GL | J12: The General area is typically reserved for roles that either: (1) are fully described by their function description; or (2) span multiple disciplines, products, or areas of expertise; or (3) executive level positions. | K12: Division President | L12: PD | M12: Division President is the top executive responsible for overseeing all operations in a Division (single profit line). Responsible for a profit and loss center. Directs a full complement of Division senior management to ensure the attainment of financial and strategic business goals. Establishes objectives, plans and budgets. Relies on corporate senior management for setting strategic direction, guidance and implementation of firm-wide policies within the division. Single incumbent position in each Division, typically reporting to Group President, or in organizations without Groups (i.e., multi-profit centers) the Chief Executive Officer. If responsible for a multi-function business unit that is not a separate division, match to Business Unit Executive at the Division organization level. | N12: LE.GLPD | O12: Leadership - General - Division President | P12: E1-4 | Q12: n/a | R12: n/a | S12: n/a | T12: n/a | U12: n/a
B13: Executive | C13: EXE | D13: Executive roles that cover activities related to firm-wide, function, or area leadership. Note that some executive roles reside in other modules that are specific to their function (e.g., Sales, Manufacturing, Technology, Life Sciences, Banking, etc.). | E13: Leadership | F13: LE | G13: The Leadership function is responsible for setting and executing the organization's overall strategy across businesses, products, and infrastructure areas. The Leadership function is reserved for the firm's most senior-level positions. | H13: General | I13: GL | J13: The General area is typically reserved for roles that either: (1) are fully described by their function description; or (2) span multiple disciplines, products, or areas of expertise; or (3) executive level positions. | K13: Group President | L13: PG | M13: Group President is the top executive responsible for overseeing all operations in a Group (a collection of two or more divisions). Single incumbent position in each Group. | N13: LE.GLPG | O13: Leadership - General - Group President | P13: E3-5 | Q13: n/a | R13: n/a | S13: n/a | T13: n/a | U13: n/a
B14: Executive | C14: EXE | D14: Executive roles that cover activities related to firm-wide, function, or area leadership. Note that some executive roles reside in other modules that are specific to their function (e.g., Sales, Manufacturing, Technology, Life Sciences, Banking, etc.). | E14: Leadership | F14: LE | G14: The Leadership function is responsible for setting and executing the organization's overall strategy across businesses, products, and infrastructure areas. The Leadership function is reserved for the firm's most senior-level positions. | H14: General | I14: GL | J14: The General area is typically reserved for roles that either: (1) are fully described by their function description; or (2) span multiple disciplines, products, or areas of expertise; or (3) executive level positions. | K14: Business Unit Executive | L14: BE | M14: Business Unit Executive is responsible for overseeing the lifecycle of a specific product or for directing activities of a business unit within a firm that is not a separate internal Group or Division. | N14: LE.GLBE | O14: Leadership - General - Business Unit Executive | P14: E1-4 | Q14: n/a | R14: n/a | S14: n/a | T14: n/a | U14: n/a
B15: Executive | C15: EXE | D15: Executive roles that cover activities related to firm-wide, function, or area leadership. Note that some executive roles reside in other modules that are specific to their function (e.g., Sales, Manufacturing, Technology, Life Sciences, Banking, etc.). | E15: Leadership | F15: LE | G15: The Leadership function is responsible for setting and executing the organization's overall strategy across businesses, products, and infrastructure areas. The Leadership function is reserved for the firm's most senior-level positions. | H15: Administration | I15: AM | J15: The Administration area is comprised of roles supporting executive leadership and the Chief Administrative Officer. | K15: Chief Administrative Officer - Corporate | L15: AC | M15: Chief Administrative Officer is the head of two or more major, non-related staff functions such as finance, human resources, law, information technology, corporate affairs, or strategic planning for the entire firm. Senior management position with significant policy-setting responsibility. Single incumbent position, typically reporting to Chief Executive Officer. | N15: LE.AMAC | O15: Leadership - Administration - Chief Administrative Officer - Corporate | P15: E1-5 | Q15: n/a | R15: n/a | S15: n/a | T15: n/a | U15: n/a
... B2818: Investor Services | C2818: IVS | D2818: Investor Services covers activities related to the custody, safekeeping, and maintenance of assets for asset managers, mutual funds, and alternative investors. Services within this business cover collateral management, clearing, fund services, administration, sub-custody, and depositary receipts. | E2818: Third-Party Administration | F2818: TN | G2818: The Third-Party Administration function is responsible for managing relationships with, and ensuring the quality of services provided by, third-party vendors (e.g., fund accounting firms, transfer agents, custodians, etc.). Has comprehensive understanding of fund accounting, shareholder services, operations, and transfer agency processes. | H2818: Multi-Area | I2818: MA | J2818: The Multi-Area attribute is typically reserved for roles that either: (1) are fully described by their function description; or (2) span multiple disciplines, products, or areas of expertise. | K2818: Multi-Focus | L2818: MF | M2818: The Multi-Focus attribute is typically reserved for roles that either: (1) are fully described by their area or function description; or (2) span multiple disciplines, products, or focuses of expertise. | N2818: TN.MAMF | O2818: Third-Party Administration - Multi-Area - Multi-Focus | P2818: n/a | Q2818: n/a | R2818: n/a | S2818: F1-7 | T2818: n/a | U2818: n/a
B2819: Life Sciences | C2819: LSC | D2819: Life Sciences covers activities related to scientific research and development of products, such as pharmaceuticals, biologics, therapeutics, diagnostics, medical devices, animal health, etc. | E2819: Compliance & Regulatory | F2819: CP | G2819: The Compliance & Regulatory function is responsible for ensuring that all activities comply with regulatory requirements, including financial crime, anti-money laundering, anti-bribery and corruption, data privacy, and sanctions. | H2819: Regulatory Affairs | I2819: RA | K2819: Healthcare Compliance | L2819: HE | M2819: The Healthcare Compliance focus specializes in collecting, tracking, reporting and auditing payments and transfers of value made to physicians, teaching hospitals and other research entities. Manages compliance with government and regulatory requirements (e.g., Sunshine Act). | N2819: CP.RAHE | O2819: Compliance & Regulatory - Regulatory Affairs - Healthcare Compliance | P2819: n/a | Q2819: M2-6 | R2819: P1-6 | S2819: n/a | T2819: n/a | U2819: n/a
B2820: Life Sciences | C2820: LSC | D2820: Life Sciences covers activities related to scientific research and development of products, such as pharmaceuticals, biologics, therapeutics, diagnostics, medical devices, animal health, etc. | E2820: Compliance & Regulatory | F2820: CP | G2820: The Compliance & Regulatory function is responsible for ensuring that all activities comply with regulatory requirements, including financial crime, anti-money laundering, anti-bribery and corruption, data privacy, and sanctions. | H2820: Regulatory Response | I2820: RR | J2820: The Regulatory Response area is responsible for understanding and interpreting regulations to assess and evaluate the impacts of regulatory response failures, including analysis through the use of data and analytics, strategic reputation analysis and develop appropriate, targeted response strategies. | K2820: Submission | L2820: SU | M2820: The Submission focus specializes in preparing, publishing, corresponding, reporting and amending of submissions, for authorization of applications, notices and submission forms required by regulatory agencies. Coordinates submission issues interdepartmentally to ensure compliance and to document management standards. | N2820: CP.RRSU | O2820: Compliance & Regulatory - Regulatory Response - Submission | P2820: n/a | Q2820: M1-6 | R2820: P1-6 | S2820: n/a | T2820: n/a | U2820: S1-5
B2821: Life Sciences | C2821: LSC | D2821: Life Sciences covers activities related to scientific research and development of products, such as pharmaceuticals, biologics, therapeutics, diagnostics, medical devices, animal health, etc. | E2821: Legal | F2821: LG | G2821: The Legal function is responsible for providing legal advice to the firm and ensuring the firm operates in accordance with legal parameters. Specialists provide support across the firm's activities ensuring that legal issues, contracts, disputes, and complex transactions are conducted within the due diligence of the legal framework. | H2821: Contracts | I2821: CO | J2821: The Contracts area is responsible for overseeing the preparation, negotiation, acceptance, and management of contracts and subcontracts with both governmental and/or non-governmental organizations. | K2821: Managed Care | L2821: MC | M2821: The Managed Care focus specializes in developing and implementing bid contracts to institutions, including hospital and national managed care accounts. Monitors contract life cycle, develops and analyzes pricing strategies and contract language which defines performance parameters and administrative procedures for rebate programs. | N2821: LG.COMC | O2821: Legal - Contracts - Managed Care | P2821: n/a | Q2821: M1-6 | R2821: P1-5 | S2821: n/a | T2821: n/a | U2821: n/a
B2822: Life Sciences | C2822: LSC | D2822: Life Sciences covers activities related to scientific research and development of products, such as pharmaceuticals, biologics, therapeutics, diagnostics, medical devices, animal health, etc. | E2822: Manufacturing | F2822: MF | G2822: The Manufacturing function is responsible for activities related to the operation and production of goods while achieving speed, quality and cost targets. | H2822: Chemistry, Manufacturing & Controls (CMC) | I2822: CM | J2822: The Chemistry, Manufacturing & Controls area is responsible for developing, implementing and directing all strategies for new and mature products and interacting with regulatory agencies. Provides strategic input, risk assessments and oversees preparation of regulatory submissions. | K2822: Chemistry, Manufacturing & Controls (CMC) | L2822: CM | M2822: The Chemistry, Manufacturing & Controls focus specializes in developing, implementing and directing all strategies for new and mature products and interacting with regulatory agencies. Provides strategic input, risk assessments and oversees preparation of regulatory submissions. | N2822: MF.CMCM | O2822: Manufacturing - Chemistry, Manufacturing & Controls (CMC) - Chemistry, Manufacturing & Controls (CMC) | P2822: n/a | Q2822: M1-6 | R2822: P1-6 | S2822: n/a | T2822: n/a | U2822: n/a
